Workbook
Name Active: Reference!$R$2:$R$6
Name BachS1: Reference!$K$25:$K$39
Name DATA: 'Data Employee'!$A$2:$AG$247
Name Degree3: Reference!$K$10:$K$24
Name Dept_CM: Reference!$S$20:$S$21
Name Dept_Corporate: Reference!$S$31:$S$34
Name Dept_HRD: Reference!$S$19
Name Dept_IT: Reference!$S$28
Name Dept_Legal: Reference!$S$30
Name Dept_Management: Reference!$S$16:$S$18
Name Dept_MFG: Reference!$S$25:$S$27
Name Dept_RND: Reference!$S$29
Name Dept_SCM: Reference!$S$22:$S$24
Name Dept_TopMan: Reference!$S$35
Name DeptList: INDIRECT(_xlfn.XLOOKUP(INDEX('Data Employee'!$T:$T,ROW()),Reference!$AA$2:$AA$11,Reference!$AB$2:$AB$11))
Name DocS3: Reference!$K$55:$K$69
Name HighSchool: Reference!$K$2:$K$3
Name HR: Reference!$S$19
Name Pemotong_Divison: #N/A
Name Pemotong_Job_Level: #N/A
Name Range_Admin_ACC: Reference!$H$40
Name Range_Admin_FIN: Reference!$H$41
Name Range_Admin_HR: Reference!$H$19
Name Range_Admin_PPIC: Reference!$H$80:$H$81
Name Range_Admin_Prod: Reference!$H$54
Name Range_Admin_PURC: Reference!$H$82
Name Range_Admin_RND: Reference!$H$71
Name Range_Admin_Sales: Reference!$H$2
Name Range_Admin_TAX: Reference!$H$42
Name Range_Admin_WRHS: Reference!$H$83
Name Range_Analytst_IT: Reference!$H$31:$H$33
Name Range_Chairman: Reference!$H$12
Name Range_Commissioner: Reference!$H$13
Name Range_GM: Reference!$H$43
Name Range_Intern_HR: Reference!$H$20
Name Range_Intern_MAR: Reference!$H$3
Name Range_Intern_Prod: Reference!$H$55
Name Range_Intern_PURC: Reference!$H$84
Name Range_Intern_Sales: Reference!$H$4
Name Range_Intern_WRHS: Reference!$H$85
Name Range_Lead_Prod: Reference!$H$56:$H$57
Name Range_Lead_WRHS: Reference!$H$86
Name Range_MNGR_Audit: Reference!$H$14
Name Range_MNGR_FIN: Reference!$H$44
Name Range_MNGR_HR: Reference!$H$21
Name Range_MNGR_IT: Reference!$H$29
Name Range_MNGR_Legal: Reference!$H$39
Name Range_MNGR_MAR: Reference!$H$5
Name Range_MNGR_Nomi: Reference!$H$15
Name Range_MNGR_PPIC: Reference!$H$87
Name Range_MNGR_Prod: Reference!$H$58
Name Range_MNGR_PURC: Reference!$H$88
Name Range_MNGR_QA: Reference!$H$59
Name Range_MNGR_QE: Reference!$H$60
Name Range_MNGR_RND: Reference!$H$72
Name Range_MNGR_Sales: Reference!$H$6
Name Range_MNGR_WRHS: Reference!$H$89
Name Range_Officer_ACC: Reference!$H$45
Name Range_Officer_Corporate: Reference!$H$16
Name Range_Officer_FIN: Reference!$H$46

Sheet Dashboard
A1: HR METRICS PT. Dumi Bumi Tbk
A3: Created by Wahyudiansyah

Sheet Monitoring Contract
A1: Employee Number | B1: Full Name | C1: Gender | D1: No. Contract | E1: Duration (Month) | F1: Divison | G1: Departemen | H1: Job Title | I1: Job Level | J1: Join Date | K1: End Date | L1: Contract Balance | M1: Status Reminder
A2: 201743091 | B2: =INDEX('Data Employee'!$B$2:$B$1000, MATCH(A2, 'Data Employee'!$A$2:$A$1000, 0)) -> Dewi Pratama | C2: =INDEX('Data Employee'!$G$2:$G$1000,MATCH(A2,'Data Employee'!$A$2:$A$1000,0)) -> Female | D2: {=IF(J2="","",_xlfn.IFS(DATEDIF(J2,TODAY(),"M")<12,"Contract 1",DATEDIF(J2,TODAY(),"M")<36,"Contract 2",DATEDIF(J2,TODAY(),"M")<60,"Contract 3",DATEDIF(J2,TODAY(),"M")<63,"Probation",TRUE,"Permanent"))} -> Permanent | E2: =IF(D2="Permanent","Permanent",IF(D2="Contract 1","12 Month",IF(D2="Contract 2","24 Month",IF(D2="Contract 3","60 Month",IF(D2="Probation","63 Month",""))))) -> Permanent | F2: =VLOOKUP(A2, 'Data Employee'!$A$2:$U$1000, 19, FALSE) -> Accounting | G2: =VLOOKUP(A2, 'Data Employee'!$A$2:$U$1000, 20, FALSE) -> Management | H2: =INDEX('Data Employee'!$W$2:$W$1000, MATCH(A2, 'Data Employee'!$A$2:$A$1000, 0)) -> Accounting Officer | I2: =INDEX('Data Employee'!$V$2:$V$1000,MATCH(A2,'Data Employee'!$A$2:$A$1000,0)) -> Officer / Executive | J2: =INDEX('Data Employee'!$L$2:$L$1000, MATCH(A2, 'Data Employee'!$A$2:$A$1000, 0)) -> 43091 | K2: =IFERROR(IF(INDEX('Data Employee'!M:M,MATCH(A2,'Data Employee'!A:A,0))="","",INDEX('Data Employee'!M:M,MATCH(A2,'Data Employee'!A:A,0))),"") | L2: =IF(OR(K2="",K2<TODAY()),IF(K2="","","Expired"),DATEDIF(TODAY(),K2,"D")&" Days") | M2: =IF(OR(K2="", D2="Permanent", NOT(ISNUMBER(K2))), "Active", IF(K2<TODAY(), "Expired", IF(K2-TODAY()<=30, "Urgent Renewal", IF(K2-TODAY()<=60, "Review Needed", "Active")))) -> Active
A3: 201843228 | B3: =INDEX('Data Employee'!$B$2:$B$1000, MATCH(A3, 'Data Employee'!$A$2:$A$1000, 0)) -> Aulia Kurniawan | C3: =INDEX('Data Employee'!$G$2:$G$1000,MATCH(A3,'Data Employee'!$A$2:$A$1000,0)) -> Female | D3: {=IF(J3="","",_xlfn.IFS(DATEDIF(J3,TODAY(),"M")<12,"Contract 1",DATEDIF(J3,TODAY(),"M")<36,"Contract 2",DATEDIF(J3,TODAY(),"M")<60,"Contract 3",DATEDIF(J3,TODAY(),"M")<63,"Probation",TRUE,"Permanent"))} -> Permanent | E3: =IF(D3="Permanent","Permanent",IF(D3="Contract 1","12 Month",IF(D3="Contract 2","24 Month",IF(D3="Contract 3","60 Month",IF(D3="Probation","63 Month",""))))) -> Permanent | F3: =VLOOKUP(A3, 'Data Employee'!$A$2:$U$1000, 19, FALSE) -> Accounting | G3: =VLOOKUP(A3, 'Data Employee'!$A$2:$U$1000, 20, FALSE) -> Management | H3: =INDEX('Data Employee'!$W$2:$W$1000, MATCH(A3, 'Data Employee'!$A$2:$A$1000, 0)) -> Accounting Officer | I3: =INDEX('Data Employee'!$V$2:$V$1000,MATCH(A3,'Data Employee'!$A$2:$A$1000,0)) -> Officer / Executive | J3: =INDEX('Data Employee'!$L$2:$L$1000, MATCH(A3, 'Data Employee'!$A$2:$A$1000, 0)) -> 43228 | K3: =IFERROR(IF(INDEX('Data Employee'!M:M,MATCH(A3,'Data Employee'!A:A,0))="","",INDEX('Data Employee'!M:M,MATCH(A3,'Data Employee'!A:A,0))),"") | L3: =IF(OR(K3="",K3<TODAY()),IF(K3="","","Expired"),DATEDIF(TODAY(),K3,"D")&" Days") | M3: =IF(OR(K3="", D3="Permanent", NOT(ISNUMBER(K3))), "Active", IF(K3<TODAY(), "Expired", IF(K3-TODAY()<=30, "Urgent Renewal", IF(K3-TODAY()<=60, "Review Needed", "Active")))) -> Active
A4: 202043936 | B4: =INDEX('Data Employee'!$B$2:$B$1000, MATCH(A4, 'Data Employee'!$A$2:$A$1000, 0)) -> Putri Ramadhan | C4: =INDEX('Data Employee'!$G$2:$G$1000,MATCH(A4,'Data Employee'!$A$2:$A$1000,0)) -> Female | D4: {=IF(J4="","",_xlfn.IFS(DATEDIF(J4,TODAY(),"M")<12,"Contract 1",DATEDIF(J4,TODAY(),"M")<36,"Contract 2",DATEDIF(J4,TODAY(),"M")<60,"Contract 3",DATEDIF(J4,TODAY(),"M")<63,"Probation",TRUE,"Permanent"))} -> Contract 3 | E4: =IF(D4="Permanent","Permanent",IF(D4="Contract 1","12 Month",IF(D4="Contract 2","24 Month",IF(D4="Contract 3","60 Month",IF(D4="Probation","63 Month",""))))) -> 60 Month | F4: =VLOOKUP(A4, 'Data Employee'!$A$2:$U$1000, 19, FALSE) -> Accounting | G4: =VLOOKUP(A4, 'Data Employee'!$A$2:$U$1000, 20, FALSE) -> Management | H4: =INDEX('Data Employee'!$W$2:$W$1000, MATCH(A4, 'Data Employee'!$A$2:$A$1000, 0)) -> Accounting Staff | I4: =INDEX('Data Employee'!$V$2:$V$1000,MATCH(A4,'Data Employee'!$A$2:$A$1000,0)) -> Staff | J4: =INDEX('Data Employee'!$L$2:$L$1000, MATCH(A4, 'Data Employee'!$A$2:$A$1000, 0)) -> 45031 | K4: =IFERROR(IF(INDEX('Data Employee'!M:M,MATCH(A4,'Data Employee'!A:A,0))="","",INDEX('Data Employee'!M:M,MATCH(A4,'Data Employee'!A:A,0))),"") -> 46858 | L4: =IF(OR(K4="",K4<TODAY()),IF(K4="","","Expired"),DATEDIF(TODAY(),K4,"D")&" Days") -> 622 Days | M4: =IF(OR(K4="", D4="Permanent", NOT(ISNUMBER(K4))), "Active", IF(K4<TODAY(), "Expired", IF(K4-TODAY()<=30, "Urgent Renewal", IF(K4-TODAY()<=60, "Review Needed", "Active")))) -> Active
A5: 201743026 | B5: =INDEX('Data Employee'!$B$2:$B$1000, MATCH(A5, 'Data Employee'!$A$2:$A$1000, 0)) -> Indah Wijaya | C5: =INDEX('Data Employee'!$G$2:$G$1000,MATCH(A5,'Data Employee'!$A$2:$A$1000,0)) -> Female | D5: {=IF(J5="","",_xlfn.IFS(DATEDIF(J5,TODAY(),"M")<12,"Contract 1",DATEDIF(J5,TODAY(),"M")<36,"Contract 2",DATEDIF(J5,TODAY(),"M")<60,"Contract 3",DATEDIF(J5,TODAY(),"M")<63,"Probation",TRUE,"Permanent"))} -> Contract 2 | E5: =IF(D5="Permanent","Permanent",IF(D5="Contract 1","12 Month",IF(D5="Contract 2","24 Month",IF(D5="Contract 3","60 Month",IF(D5="Probation","63 Month",""))))) -> 24 Month | F5: =VLOOKUP(A5, 'Data Employee'!$A$2:$U$1000, 19, FALSE) -> Economics | G5: =VLOOKUP(A5, 'Data Employee'!$A$2:$U$1000, 20, FALSE) -> Management | H5: =INDEX('Data Employee'!$W$2:$W$1000, MATCH(A5, 'Data Employee'!$A$2:$A$1000, 0)) -> Accounting Staff | I5: =INDEX('Data Employee'!$V$2:$V$1000,MATCH(A5,'Data Employee'!$A$2:$A$1000,0)) -> Staff | J5: =INDEX('Data Employee'!$L$2:$L$1000, MATCH(A5, 'Data Employee'!$A$2:$A$1000, 0)) -> 45583 | K5: =IFERROR(IF(INDEX('Data Employee'!M:M,MATCH(A5,'Data Employee'!A:A,0))="","",INDEX('Data Employee'!M:M,MATCH(A5,'Data Employee'!A:A,0))),"") -> 47409 | L5: =IF(OR(K5="",K5<TODAY()),IF(K5="","","Expired"),DATEDIF(TODAY(),K5,"D")&" Days") -> 1173 Days | M5: =IF(OR(K5="", D5="Permanent", NOT(ISNUMBER(K5))), "Active", IF(K5<TODAY(), "Expired", IF(K5-TODAY()<=30, "Urgent Renewal", IF(K5-TODAY()<=60, "Review Needed", "Active")))) -> Active
A6: 201642668 | B6: =INDEX('Data Employee'!$B$2:$B$1000, MATCH(A6, 'Data Employee'!$A$2:$A$1000, 0)) -> Yulia Kurniawan | C6: =INDEX('Data Employee'!$G$2:$G$1000,MATCH(A6,'Data Employee'!$A$2:$A$1000,0)) -> Female | D6: {=IF(J6="","",_xlfn.IFS(DATEDIF(J6,TODAY(),"M")<12,"Contract 1",DATEDIF(J6,TODAY(),"M")<36,"Contract 2",DATEDIF(J6,TODAY(),"M")<60,"Contract 3",DATEDIF(J6,TODAY(),"M")<63,"Probation",TRUE,"Permanent"))} -> Contract 3 | E6: =IF(D6="Permanent","Permanent",IF(D6="Contract 1","12 Month",IF(D6="Contract 2","24 Month",IF(D6="Contract 3","60 Month",IF(D6="Probation","63 Month",""))))) -> 60 Month | F6: =VLOOKUP(A6, 'Data Employee'!$A$2:$U$1000, 19, FALSE) -> Business Administration | G6: =VLOOKUP(A6, 'Data Employee'!$A$2:$U$1000, 20, FALSE) -> Management | H6: =INDEX('Data Employee'!$W$2:$W$1000, MATCH(A6, 'Data Employee'!$A$2:$A$1000, 0)) -> Accounting Administration Staff | I6: =INDEX('Data Employee'!$V$2:$V$1000,MATCH(A6,'Data Employee'!$A$2:$A$1000,0)) -> Administrator | J6: =INDEX('Data Employee'!$L$2:$L$1000, MATCH(A6, 'Data Employee'!$A$2:$A$1000, 0)) -> 44494 | K6: =IFERROR(IF(INDEX('Data Employee'!M:M,MATCH(A6,'Data Employee'!A:A,0))="","",INDEX('Data Employee'!M:M,MATCH(A6,'Data Employee'!A:A,0))),"") -> 46412 | L6: =IF(OR(K6="",K6<TODAY()),IF(K6="","","Expired"),DATEDIF(TODAY(),K6,"D")&" Days") -> 176 Days | M6: =IF(OR(K6="", D6="Permanent", NOT(ISNUMBER(K6))), "Active", IF(K6<TODAY(), "Expired", IF(K6-TODAY()<=30, "Urgent Renewal", IF(K6-TODAY()<=60, "Review Needed", "Active")))) -> Active
A7: 201843210 | B7: =INDEX('Data Employee'!$B$2:$B$1000, MATCH(A7, 'Data Employee'!$A$2:$A$1000, 0)) -> Rudi Saputra | C7: =INDEX('Data Employee'!$G$2:$G$1000,MATCH(A7,'Data Employee'!$A$2:$A$1000,0)) -> Male | D7: {=IF(J7="","",_xlfn.IFS(DATEDIF(J7,TODAY(),"M")<12,"Contract 1",DATEDIF(J7,TODAY(),"M")<36,"Contract 2",DATEDIF(J7,TODAY(),"M")<60,"Contract 3",DATEDIF(J7,TODAY(),"M")<63,"Probation",TRUE,"Permanent"))} -> Permanent | E7: =IF(D7="Permanent","Permanent",IF(D7="Contract 1","12 Month",IF(D7="Contract 2","24 Month",IF(D7="Contract 3","60 Month",IF(D7="Probation","63 Month",""))))) -> Permanent | F7: =VLOOKUP(A7, 'Data Employee'!$A$2:$U$1000, 19, FALSE) -> Accounting | G7: =VLOOKUP(A7, 'Data Employee'!$A$2:$U$1000, 20, FALSE) -> Management | H7: =INDEX('Data Employee'!$W$2:$W$1000, MATCH(A7, 'Data Employee'!$A$2:$A$1000, 0)) -> Accounting Supervisor | I7: =INDEX('Data Employee'!$V$2:$V$1000,MATCH(A7,'Data Employee'!$A$2:$A$1000,0)) -> Supervisor | J7: =INDEX('Data Employee'!$L$2:$L$1000, MATCH(A7, 'Data Employee'!$A$2:$A$1000, 0)) -> 43210 | K7: =IFERROR(IF(INDEX('Data Employee'!M:M,MATCH(A7,'Data Employee'!A:A,0))="","",INDEX('Data Employee'!M:M,MATCH(A7,'Data Employee'!A:A,0))),"") | L7: =IF(OR(K7="",K7<TODAY()),IF(K7="","","Expired"),DATEDIF(TODAY(),K7,"D")&" Days") | M7: =IF(OR(K7="", D7="Permanent", NOT(ISNUMBER(K7))), "Active", IF(K7<TODAY(), "Expired", IF(K7-TODAY()<=30, "Urgent Renewal", IF(K7-TODAY()<=60, "Review Needed", "Active")))) -> Active
A8: 202043917 | B8: =INDEX('Data Employee'!$B$2:$B$1000, MATCH(A8, 'Data Employee'!$A$2:$A$1000, 0)) -> Nadia Wijaya | C8: =INDEX('Data Employee'!$G$2:$G$1000,MATCH(A8,'Data Employee'!$A$2:$A$1000,0)) -> Female | D8: {=IF(J8="","",_xlfn.IFS(DATEDIF(J8,TODAY(),"M")<12,"Contract 1",DATEDIF(J8,TODAY(),"M")<36,"Contract 2",DATEDIF(J8,TODAY(),"M")<60,"Contract 3",DATEDIF(J8,TODAY(),"M")<63,"Probation",TRUE,"Permanent"))} -> Permanent | E8: =IF(D8="Permanent","Permanent",IF(D8="Contract 1","12 Month",IF(D8="Contract 2","24 Month",IF(D8="Contract 3","60 Month",IF(D8="Probation","63 Month",""))))) -> Permanent | F8: =VLOOKUP(A8, 'Data Employee'!$A$2:$U$1000, 19, FALSE) -> Accounting | G8: =VLOOKUP(A8, 'Data Employee'!$A$2:$U$1000, 20, FALSE) -> Corporate Governance | H8: =INDEX('Data Employee'!$W$2:$W$1000, MATCH(A8, 'Data Employee'!$A$2:$A$1000, 0)) -> Audit Committee Staff | I8: =INDEX('Data Employee'!$V$2:$V$1000,MATCH(A8,'Data Employee'!$A$2:$A$1000,0)) -> Staff | J8: =INDEX('Data Employee'!$L$2:$L$1000, MATCH(A8, 'Data Employee'!$A$2:$A$1000, 0)) -> 43186 | K8: =IFERROR(IF(INDEX('Data Employee'!M:M,MATCH(A8,'Data Employee'!A:A,0))="","",INDEX('Data Employee'!M:M,MATCH(A8,'Data Employee'!A:A,0))),"") | L8: =IF(OR(K8="",K8<TODAY()),IF(K8="","","Expired"),DATEDIF(TODAY(),K8,"D")&" Days") | M8: =IF(OR(K8="", D8="Permanent", NOT(ISNUMBER(K8))), "Active", IF(K8<TODAY(), "Expired", IF(K8-TODAY()<=30, "Urgent Renewal", IF(K8-TODAY()<=60, "Review Needed", "Active")))) -> Active
A9: 201642597 | B9: =INDEX('Data Employee'!$B$2:$B$1000, MATCH(A9, 'Data Employee'!$A$2:$A$1000, 0)) -> Dedi Wijaya | C9: =INDEX('Data Employee'!$G$2:$G$1000,MATCH(A9,'Data Employee'!$A$2:$A$1000,0)) -> Male | D9: {=IF(J9="","",_xlfn.IFS(DATEDIF(J9,TODAY(),"M")<12,"Contract 1",DATEDIF(J9,TODAY(),"M")<36,"Contract 2",DATEDIF(J9,TODAY(),"M")<60,"Contract 3",DATEDIF(J9,TODAY(),"M")<63,"Probation",TRUE,"Permanent"))} -> Permanent | E9: =IF(D9="Permanent","Permanent",IF(D9="Contract 1","12 Month",IF(D9="Contract 2","24 Month",IF(D9="Contract 3","60 Month",IF(D9="Probation","63 Month",""))))) -> Permanent | F9: =VLOOKUP(A9, 'Data Employee'!$A$2:$U$1000, 19, FALSE) -> Accounting | G9: =VLOOKUP(A9, 'Data Employee'!$A$2:$U$1000, 20, FALSE) -> Corporate Governance | H9: =INDEX('Data Employee'!$W$2:$W$1000, MATCH(A9, 'Data Employee'!$A$2:$A$1000, 0)) -> Audit Committee Manager | I9: =INDEX('Data Employee'!$V$2:$V$1000,MATCH(A9,'Data Employee'!$A$2:$A$1000,0)) -> Manager | J9: =INDEX('Data Employee'!$L$2:$L$1000, MATCH(A9, 'Data Employee'!$A$2:$A$1000, 0)) -> 42597 | K9: =IFERROR(IF(INDEX('Data Employee'!M:M,MATCH(A9,'Data Employee'!A:A,0))="","",INDEX('Data Employee'!M:M,MATCH(A9,'Data Employee'!A:A,0))),"") | L9: =IF(OR(K9="",K9<TODAY()),IF(K9="","","Expired"),DATEDIF(TODAY(),K9,"D")&" Days") | M9: =IF(OR(K9="", D9="Permanent", NOT(ISNUMBER(K9))), "Active", IF(K9<TODAY(), "Expired", IF(K9-TODAY()<=30, "Urgent Renewal", IF(K9-TODAY()<=60, "Review Needed", "Active")))) -> Active
A10: 202043908 | B10: =INDEX('Data Employee'!$B$2:$B$1000, MATCH(A10, 'Data Employee'!$A$2:$A$1000, 0)) -> Andi Ramadhan | C10: =INDEX('Data Employee'!$G$2:$G$1000,MATCH(A10,'Data Employee'!$A$2:$A$1000,0)) -> Male | D10: {=IF(J10="","",_xlfn.IFS(DATEDIF(J10,TODAY(),"M")<12,"Contract 1",DATEDIF(J10,TODAY(),"M")<36,"Contract 2",DATEDIF(J10,TODAY(),"M")<60,"Contract 3",DATEDIF(J10,TODAY(),"M")<63,"Probation",TRUE,"Permanent"))} -> Permanent | E10: =IF(D10="Permanent","Permanent",IF(D10="Contract 1","12 Month",IF(D10="Contract 2","24 Month",IF(D10="Contract 3","60 Month",IF(D10="Probation","63 Month",""))))) -> Permanent | F10: =VLOOKUP(A10, 'Data Employee'!$A$2:$U$1000, 19, FALSE) -> Management | G10: =VLOOKUP(A10, 'Data Employee'!$A$2:$U$1000, 20, FALSE) -> Corporate Governance | H10: =INDEX('Data Employee'!$W$2:$W$1000, MATCH(A10, 'Data Employee'!$A$2:$A$1000, 0)) -> Audit Committee Staff | I10: =INDEX('Data Employee'!$V$2:$V$1000,MATCH(A10,'Data Employee'!$A$2:$A$1000,0)) -> Staff | J10: =INDEX('Data Employee'!$L$2:$L$1000, MATCH(A10, 'Data Employee'!$A$2:$A$1000, 0)) -> 43542 | K10: =IFERROR(IF(INDEX('Data Employee'!M:M,MATCH(A10,'Data Employee'!A:A,0))="","",INDEX('Data Employee'!M:M,MATCH(A10,'Data Employee'!A:A,0))),"") | L10: =IF(OR(K10="",K10<TODAY()),IF(K10="","","Expired"),DATEDIF(TODAY(),K10,"D")&" Days") | M10: =IF(OR(K10="", D10="Permanent", NOT(ISNUMBER(K10))), "Active", IF(K10<TODAY(), "Expired", IF(K10-TODAY()<=30, "Urgent Renewal", IF(K10-TODAY()<=60, "Review Needed", "Active")))) -> Active
A11: 202043954 | B11: =INDEX('Data Employee'!$B$2:$B$1000, MATCH(A11, 'Data Employee'!$A$2:$A$1000, 0)) -> Nadia Lestari | C11: =INDEX('Data Employee'!$G$2:$G$1000,MATCH(A11,'Data Employee'!$A$2:$A$1000,0)) -> Female | D11: {=IF(J11="","",_xlfn.IFS(DATEDIF(J11,TODAY(),"M")<12,"Contract 1",DATEDIF(J11,TODAY(),"M")<36,"Contract 2",DATEDIF(J11,TODAY(),"M")<60,"Contract 3",DATEDIF(J11,TODAY(),"M")<63,"Probation",TRUE,"Permanent"))} -> Permanent | E11: =IF(D11="Permanent","Permanent",IF(D11="Contract 1","12 Month",IF(D11="Contract 2","24 Month",IF(D11="Contract 3","60 Month",IF(D11="Probation","63 Month",""))))) -> Permanent | F11: =VLOOKUP(A11, 'Data Employee'!$A$2:$U$1000, 19, FALSE) -> Psychology | G11: =VLOOKUP(A11, 'Data Employee'!$A$2:$U$1000, 20, FALSE) -> Corporate Governance | H11: =INDEX('Data Employee'!$W$2:$W$1000, MATCH(A11, 'Data Employee'!$A$2:$A$1000, 0)) -> Chairman Commissioner | I11: =INDEX('Data Employee'!$V$2:$V$1000,MATCH(A11,'Data Employee'!$A$2:$A$1000,0)) -> Chairman Commissioner | J11: =INDEX('Data Employee'!$L$2:$L$1000, MATCH(A11, 'Data Employee'!$A$2:$A$1000, 0)) -> 38110 | K11: =IFERROR(IF(INDEX('Data Employee'!M:M,MATCH(A11,'Data Employee'!A:A,0))="","",INDEX('Data Employee'!M:M,MATCH(A11,'Data Employee'!A:A,0))),"") | L11: =IF(OR(K11="",K11<TODAY()),IF(K11="","","Expired"),DATEDIF(TODAY(),K11,"D")&" Days") | M11: =IF(OR(K11="", D11="Permanent", NOT(ISNUMBER(K11))), "Active", IF(K11<TODAY(), "Expired", IF(K11-TODAY()<=30, "Urgent Renewal", IF(K11-TODAY()<=60, "Review Needed", "Active")))) -> Active
A12: 201943658 | B12: =INDEX('Data Employee'!$B$2:$B$1000, MATCH(A12, 'Data Employee'!$A$2:$A$1000, 0)) -> Yusuf Pratama | C12: =INDEX('Data Employee'!$G$2:$G$1000,MATCH(A12,'Data Employee'!$A$2:$A$1000,0)) -> Male | D12: {=IF(J12="","",_xlfn.IFS(DATEDIF(J12,TODAY(),"M")<12,"Contract 1",DATEDIF(J12,TODAY(),"M")<36,"Contract 2",DATEDIF(J12,TODAY(),"M")<60,"Contract 3",DATEDIF(J12,TODAY(),"M")<63,"Probation",TRUE,"Permanent"))} -> Permanent | E12: =IF(D12="Permanent","Permanent",IF(D12="Contract 1","12 Month",IF(D12="Contract 2","24 Month",IF(D12="Contract 3","60 Month",IF(D12="Probation","63 Month",""))))) -> Permanent | F12: =VLOOKUP(A12, 'Data Employee'!$A$2:$U$1000, 19, FALSE) -> Law | G12: =VLOOKUP(A12, 'Data Employee'!$A$2:$U$1000, 20, FALSE) -> Corporate Governance | H12: =INDEX('Data Employee'!$W$2:$W$1000, MATCH(A12, 'Data Employee'!$A$2:$A$1000, 0)) -> Commissioner | I12: =INDEX('Data Employee'!$V$2:$V$1000,MATCH(A12,'Data Employee'!$A$2:$A$1000,0)) -> Commissioner | J12: =INDEX('Data Employee'!$L$2:$L$1000, MATCH(A12, 'Data Employee'!$A$2:$A$1000, 0)) -> 37084 | K12: =IFERROR(IF(INDEX('Data Employee'!M:M,MATCH(A12,'Data Employee'!A:A,0))="","",INDEX('Data Employee'!M:M,MATCH(A12,'Data Employee'!A:A,0))),"") | L12: =IF(OR(K12="",K12<TODAY()),IF(K12="","","Expired"),DATEDIF(TODAY(),K12,"D")&" Days") | M12: =IF(OR(K12="", D12="Permanent", NOT(ISNUMBER(K12))), "Active", IF(K12<TODAY(), "Expired", IF(K12-TODAY()<=30, "Urgent Renewal", IF(K12-TODAY()<=60, "Review Needed", "Active")))) -> Active
A13: 201441797 | B13: =INDEX('Data Employee'!$B$2:$B$1000, MATCH(A13, 'Data Employee'!$A$2:$A$1000, 0)) -> Dedi Permata | C13: =INDEX('Data Employee'!$G$2:$G$1000,MATCH(A13,'Data Employee'!$A$2:$A$1000,0)) -> Male | D13: {=IF(J13="","",_xlfn.IFS(DATEDIF(J13,TODAY(),"M")<12,"Contract 1",DATEDIF(J13,TODAY(),"M")<36,"Contract 2",DATEDIF(J13,TODAY(),"M")<60,"Contract 3",DATEDIF(J13,TODAY(),"M")<63,"Probation",TRUE,"Permanent"))} -> Permanent | E13: =IF(D13="Permanent","Permanent",IF(D13="Contract 1","12 Month",IF(D13="Contract 2","24 Month",IF(D13="Contract 3","60 Month",IF(D13="Probation","63 Month",""))))) -> Permanent | F13: =VLOOKUP(A13, 'Data Employee'!$A$2:$U$1000, 19, FALSE) -> Accounting | G13: =VLOOKUP(A13, 'Data Employee'!$A$2:$U$1000, 20, FALSE) -> Corporate Governance | H13: =INDEX('Data Employee'!$W$2:$W$1000, MATCH(A13, 'Data Employee'!$A$2:$A$1000, 0)) -> Commissioner | I13: =INDEX('Data Employee'!$V$2:$V$1000,MATCH(A13,'Data Employee'!$A$2:$A$1000,0)) -> Commissioner | J13: =INDEX('Data Employee'!$L$2:$L$1000, MATCH(A13, 'Data Employee'!$A$2:$A$1000, 0)) -> 37414 | K13: =IFERROR(IF(INDEX('Data Employee'!M:M,MATCH(A13,'Data Employee'!A:A,0))="","",INDEX('Data Employee'!M:M,MATCH(A13,'Data Employee'!A:A,0))),"") | L13: =IF(OR(K13="",K13<TODAY()),IF(K13="","","Expired"),DATEDIF(TODAY(),K13,"D")&" Days") | M13: =IF(OR(K13="", D13="Permanent", NOT(ISNUMBER(K13))), "Active", IF(K13<TODAY(), "Expired", IF(K13-TODAY()<=30, "Urgent Renewal", IF(K13-TODAY()<=60, "Review Needed", "Active")))) -> Active
... A307: 202545996 | B307: =INDEX('Data Employee'!$B$2:$B$1000, MATCH(A307, 'Data Employee'!$A$2:$A$1000, 0)) -> Dwi Kusnandar | C307: =INDEX('Data Employee'!$G$2:$G$1000,MATCH(A307,'Data Employee'!$A$2:$A$1000,0)) -> Male | D307: {=IF(J307="","",_xlfn.IFS(DATEDIF(J307,TODAY(),"M")<12,"Contract 1",DATEDIF(J307,TODAY(),"M")<36,"Contract 2",DATEDIF(J307,TODAY(),"M")<60,"Contract 3",DATEDIF(J307,TODAY(),"M")<63,"Probation",TRUE,"Permanent"))} -> Contract 1 | E307: =IF(D307="Permanent","Permanent",IF(D307="Contract 1","12 Month",IF(D307="Contract 2","24 Month",IF(D307="Contract 3","60 Month",IF(D307="Probation","63 Month",""))))) -> 12 Month | F307: =VLOOKUP(A307, 'Data Employee'!$A$2:$U$1000, 19, FALSE) -> Automotive Engineering | G307: =VLOOKUP(A307, 'Data Employee'!$A$2:$U$1000, 20, FALSE) -> Supply Chain Management | H307: =INDEX('Data Employee'!$W$2:$W$1000, MATCH(A307, 'Data Employee'!$A$2:$A$1000, 0)) -> Data Entry Intern | I307: =INDEX('Data Employee'!$V$2:$V$1000,MATCH(A307,'Data Employee'!$A$2:$A$1000,0)) -> Internship | J307: =INDEX('Data Employee'!$L$2:$L$1000, MATCH(A307, 'Data Employee'!$A$2:$A$1000, 0)) -> 45996 | K307: =IFERROR(IF(INDEX('Data Employee'!M:M,MATCH(A307,'Data Employee'!A:A,0))="","",INDEX('Data Employee'!M:M,MATCH(A307,'Data Employee'!A:A,0))),"") -> 46361 | L307: =IF(OR(K307="",K307<TODAY()),IF(K307="","","Expired"),DATEDIF(TODAY(),K307,"D")&" Days") -> 125 Days | M307: =IF(OR(K307="", D307="Permanent", NOT(ISNUMBER(K307))), "Active", IF(K307<TODAY(), "Expired", IF(K307-TODAY()<=30, "Urgent Renewal", IF(K307-TODAY()<=60, "Review Needed", "Active")))) -> Active

Sheet Data Employee
A1: Employee Number | B1: Full Name | C1: National ID Number (NIK) | D1: Family Card Number (KK) | E1: Place of Birth | F1: Date of Birth | G1: Gender | H1: Marital Status | I1: Dependent count | J1: Religion | K1: Blood Type | L1: Join Date | M1: End Date | N1: Exit Date | O1: Reason Saparation | P1: Employee Status | Q1: Employment Status | R1: Education | S1: Major | T1: Divison | U1: Departemen | V1: Job Level | W1: Job Title | X1: Grade | Y1: PTKP | Z1: Tax IDE (NPWP) | AA1: BPJS KPJ | AB1: BPJS JKN | AC1: Bank Name | AD1: Bank Acount | AE1: Mobile Phone | AF1: Email | AG1: Current Address
A2: 201743091 | B2: Dewi Pratama | C2: 3673261338071485 | D2: 4271920405157968 | E2: Padang | F2: 35084 | G2: Female | H2: Married | I2: =MIN(COUNTIFS('Data Family'!A:A,A2,'Data Family'!F:F,"Child")+COUNTIFS('Data Family'!A:A,A2,'Data Family'!F:F,"<>Child",'Data Family'!J:J,"Housewife")+COUNTIFS('Data Family'!A:A,A2,'Data Family'!F:F,"<>Child",'Data Family'!J:J,"Unemployment"),3) -> 0 | J2: Islam | K2: B | L2: 43091 | O2: =IF(AND(M2<>"", M2<=TODAY(), N2=""), "End of Contract", "") | P2: =IF(OR(N2<>"", AND(M2<>"",M2<=TODAY())),"Non-Active","Active") -> Active | Q2: =IF(M2="","PKWTT",IF(DATEDIF(L2,M2,"M")>63,"PKWTT",IF(DATEDIF(L2,M2,"M")>60,"PKWT",IF(DATEDIF(L2,M2,"M")>36,"PKWT",IF(DATEDIF(L2,M2,"M")>12, "PKWT","PKWT"))))) -> PKWTT | R2: Bachelor's Degree (S1) | S2: Accounting | T2: Management | U2: Accounting | V2: Officer / Executive | W2: Accounting Officer | X2: =_xlfn.XLOOKUP(V2,Reference!$O:$O,Reference!$N:$N,"Tidak Ketemu") -> G10 | Y2: =IF(AND(G2="Female",H2="Married"),"TK/0",IF(H2="Married","K/"&I2,"TK/"&I2)) -> TK/0 | Z2: 709598720199151 | AA2: 82725055991 | AB2: 7530534521305 | AC2: BANK BCA | AD2: 8222713255 | AE2: 087436886061 | AF2: dewi.pratama@dumibumi.co.id | AG2: Depok, Indonesia
A3: 201843228 | B3: Aulia Kurniawan | C3: 6583433931378082 | D3: 5074515261456100 | E3: Padang | F3: 35687 | G3: Female | H3: Married | I3: =MIN(COUNTIFS('Data Family'!A:A,A3,'Data Family'!F:F,"Child")+COUNTIFS('Data Family'!A:A,A3,'Data Family'!F:F,"<>Child",'Data Family'!J:J,"Housewife")+COUNTIFS('Data Family'!A:A,A3,'Data Family'!F:F,"<>Child",'Data Family'!J:J,"Unemployment"),3) -> 0 | J3: Islam | K3: A | L3: 43228 | O3: =IF(AND(M3<>"", M3<=TODAY(), N3=""), "End of Contract", "") | P3: =IF(OR(N3<>"", AND(M3<>"",M3<=TODAY())),"Non-Active","Active") -> Active | Q3: =IF(M3="","PKWTT",IF(DATEDIF(L3,M3,"M")>63,"PKWTT",IF(DATEDIF(L3,M3,"M")>60,"PKWT",IF(DATEDIF(L3,M3,"M")>36,"PKWT",IF(DATEDIF(L3,M3,"M")>12, "PKWT","PKWT"))))) -> PKWTT | R3: Bachelor's Degree (S1) | S3: Accounting | T3: Management | U3: Accounting | V3: Officer / Executive | W3: Accounting Officer | X3: =_xlfn.XLOOKUP(V3,Reference!$O:$O,Reference!$N:$N,"Tidak Ketemu") -> G10 | Y3: =IF(AND(G3="Female",H3="Married"),"TK/0",IF(H3="Married","K/"&I3,"TK/"&I3)) -> TK/0 | Z3: 697817412081533 | AA3: 02808925599 | AB3: 2285754017046 | AC3: BANK BCA | AD3: 2075046802 | AE3: 089998014789 | AF3: aulia.kurniawan@dumibumi.co.id | AG3: Depok, Indonesia
A4: 202043936 | B4: Putri Ramadhan | C4: 1641203662345718 | D4: 4630131291841621 | E4: Banjarbaru | F4: 32901 | G4: Female | H4: Married | I4: =MIN(COUNTIFS('Data Family'!A:A,A4,'Data Family'!F:F,"Child")+COUNTIFS('Data Family'!A:A,A4,'Data Family'!F:F,"<>Child",'Data Family'!J:J,"Housewife")+COUNTIFS('Data Family'!A:A,A4,'Data Family'!F:F,"<>Child",'Data Family'!J:J,"Unemployment"),3) -> 0 | J4: Islam | K4: A | L4: 45031 | M4: 46858 | O4: =IF(AND(M4<>"", M4<=TODAY(), N4=""), "End of Contract", "") | P4: =IF(OR(N4<>"", AND(M4<>"",M4<=TODAY())),"Non-Active","Active") -> Active | Q4: =IF(M4="","PKWTT",IF(DATEDIF(L4,M4,"M")>63,"PKWTT",IF(DATEDIF(L4,M4,"M")>60,"PKWT",IF(DATEDIF(L4,M4,"M")>36,"PKWT",IF(DATEDIF(L4,M4,"M")>12, "PKWT","PKWT"))))) -> PKWT | R4: Bachelor's Degree (S1) | S4: Accounting | T4: Management | U4: Accounting | V4: Staff | W4: Accounting Staff | X4: =_xlfn.XLOOKUP(V4,Reference!$O:$O,Reference!$N:$N,"Tidak Ketemu") -> G11 | Y4: =IF(AND(G4="Female",H4="Married"),"TK/0",IF(H4="Married","K/"&I4,"TK/"&I4)) -> TK/0 | Z4: 155058597700709 | AA4: 11885951137 | AB4: 2735238535208 | AC4: BANK BCA | AD4: 1619300215 | AE4: 085093968164 | AF4: putri.ramadhan@dumibumi.co.id | AG4: Bekasi, Indonesia
A5: 201743026 | B5: Indah Wijaya | C5: 3103831033928140 | D5: 5183770246714878 | E5: Padang | F5: 35653 | G5: Female | H5: Widowed | I5: =MIN(COUNTIFS('Data Family'!A:A,A5,'Data Family'!F:F,"Child")+COUNTIFS('Data Family'!A:A,A5,'Data Family'!F:F,"<>Child",'Data Family'!J:J,"Housewife")+COUNTIFS('Data Family'!A:A,A5,'Data Family'!F:F,"<>Child",'Data Family'!J:J,"Unemployment"),3) -> 1 | J5: Islam | K5: B | L5: 45583 | M5: 47409 | O5: =IF(AND(M5<>"", M5<=TODAY(), N5=""), "End of Contract", "") | P5: =IF(OR(N5<>"", AND(M5<>"",M5<=TODAY())),"Non-Active","Active") -> Active | Q5: =IF(M5="","PKWTT",IF(DATEDIF(L5,M5,"M")>63,"PKWTT",IF(DATEDIF(L5,M5,"M")>60,"PKWT",IF(DATEDIF(L5,M5,"M")>36,"PKWT",IF(DATEDIF(L5,M5,"M")>12, "PKWT","PKWT"))))) -> PKWT | R5: Bachelor's Degree (S1) | S5: Economics | T5: Management | U5: Accounting | V5: Staff | W5: Accounting Staff | X5: =_xlfn.XLOOKUP(V5,Reference!$O:$O,Reference!$N:$N,"Tidak Ketemu") -> G11 | Y5: =IF(AND(G5="Female",H5="Married"),"TK/0",IF(H5="Married","K/"&I5,"TK/"&I5)) -> TK/1 | Z5: 222635371015359 | AA5: 55677325613 | AB5: 5210410376198 | AC5: BANK BCA | AD5: 3973522993 | AE5: 088482832207 | AF5: indah.wijaya@dumibumi.co.id | AG5: Depok, Indonesia
A6: 201642668 | B6: Yulia Kurniawan | C6: 9357104470892611 | D6: 5396268764900697 | E6: Pasuruan | F6: 34390 | G6: Female | H6: Widowed | I6: =MIN(COUNTIFS('Data Family'!A:A,A6,'Data Family'!F:F,"Child")+COUNTIFS('Data Family'!A:A,A6,'Data Family'!F:F,"<>Child",'Data Family'!J:J,"Housewife")+COUNTIFS('Data Family'!A:A,A6,'Data Family'!F:F,"<>Child",'Data Family'!J:J,"Unemployment"),3) -> 2 | J6: Islam | K6: AB | L6: 44494 | M6: 46412 | O6: =IF(AND(M6<>"", M6<=TODAY(), N6=""), "End of Contract", "") | P6: =IF(OR(N6<>"", AND(M6<>"",M6<=TODAY())),"Non-Active","Active") -> Active | Q6: =IF(M6="","PKWTT",IF(DATEDIF(L6,M6,"M")>63,"PKWTT",IF(DATEDIF(L6,M6,"M")>60,"PKWT",IF(DATEDIF(L6,M6,"M")>36,"PKWT",IF(DATEDIF(L6,M6,"M")>12, "PKWT","PKWT"))))) -> PKWT | R6: Bachelor's Degree (S1) | S6: Business Administration | T6: Management | U6: Accounting | V6: Administrator | W6: Accounting Administration Staff | X6: =_xlfn.XLOOKUP(V6,Reference!$O:$O,Reference!$N:$N,"Tidak Ketemu") -> G12 | Y6: =IF(AND(G6="Female",H6="Married"),"TK/0",IF(H6="Married","K/"&I6,"TK/"&I6)) -> TK/2 | Z6: 828882004717425 | AA6: 55597668759 | AB6: 8721093658871 | AC6: BANK BCA | AD6: 5420497304 | AE6: 087695039746 | AF6: aulia.kurniawan@dumibumi.co.id | AG6: Subang, Indonesia
A7: 201843210 | B7: Rudi Saputra | C7: 2569196375513447 | D7: 5523131890314821 | E7: Bontang | F7: 32679 | G7: Male | H7: Married | I7: =MIN(COUNTIFS('Data Family'!A:A,A7,'Data Family'!F:F,"Child")+COUNTIFS('Data Family'!A:A,A7,'Data Family'!F:F,"<>Child",'Data Family'!J:J,"Housewife")+COUNTIFS('Data Family'!A:A,A7,'Data Family'!F:F,"<>Child",'Data Family'!J:J,"Unemployment"),3) -> 0 | J7: Islam | K7: AB | L7: 43210 | O7: =IF(AND(M7<>"", M7<=TODAY(), N7=""), "End of Contract", "") | P7: =IF(OR(N7<>"", AND(M7<>"",M7<=TODAY())),"Non-Active","Active") -> Active | Q7: =IF(M7="","PKWTT",IF(DATEDIF(L7,M7,"M")>63,"PKWTT",IF(DATEDIF(L7,M7,"M")>60,"PKWT",IF(DATEDIF(L7,M7,"M")>36,"PKWT",IF(DATEDIF(L7,M7,"M")>12, "PKWT","PKWT"))))) -> PKWTT | R7: Master's Degree (S2) | S7: Accounting | T7: Management | U7: Accounting | V7: Supervisor | W7: Accounting Supervisor | X7: =_xlfn.XLOOKUP(V7,Reference!$O:$O,Reference!$N:$N,"Tidak Ketemu") -> G07 | Y7: =IF(AND(G7="Female",H7="Married"),"TK/0",IF(H7="Married","K/"&I7,"TK/"&I7)) -> K/0 | Z7: 428422055744441 | AA7: 20032461858 | AB7: 6902535603224 | AC7: BANK BCA | AD7: 3288481171 | AE7: 080186359431 | AF7: rudi.saputra@dumibumi.co.id | AG7: Bekasi, Indonesia
A8: 202043917 | B8: Nadia Wijaya | C8: 0320996696887233 | D8: 8975850746827978 | E8: Bondowoso | F8: 32615 | G8: Female | H8: Married | I8: =MIN(COUNTIFS('Data Family'!A:A,A8,'Data Family'!F:F,"Child")+COUNTIFS('Data Family'!A:A,A8,'Data Family'!F:F,"<>Child",'Data Family'!J:J,"Housewife")+COUNTIFS('Data Family'!A:A,A8,'Data Family'!F:F,"<>Child",'Data Family'!J:J,"Unemployment"),3) -> 0 | J8: Islam | K8: AB | L8: 43186 | O8: =IF(AND(M8<>"", M8<=TODAY(), N8=""), "End of Contract", "") | P8: =IF(OR(N8<>"", AND(M8<>"",M8<=TODAY())),"Non-Active","Active") -> Active | Q8: =IF(M8="","PKWTT",IF(DATEDIF(L8,M8,"M")>63,"PKWTT",IF(DATEDIF(L8,M8,"M")>60,"PKWT",IF(DATEDIF(L8,M8,"M")>36,"PKWT",IF(DATEDIF(L8,M8,"M")>12, "PKWT","PKWT"))))) -> PKWTT | R8: Bachelor's Degree (S1) | S8: Accounting | T8: Corporate Governance | U8: Audit Committee | V8: Staff | W8: Audit Committee Staff | X8: =_xlfn.XLOOKUP(V8,Reference!$O:$O,Reference!$N:$N,"Tidak Ketemu") -> G11 | Y8: =IF(AND(G8="Female",H8="Married"),"TK/0",IF(H8="Married","K/"&I8,"TK/"&I8)) -> TK/0 | Z8: 611782068952825 | AA8: 32355111769 | AB8: 3580119418707 | AC8: BANK BCA | AD8: 6095340079 | AE8: 086097085665 | AF8: nadia.wijaya@dumibumi.co.id | AG8: Depok, Indonesia
A9: 201642597 | B9: Dedi Wijaya | C9: 9179297091629184 | D9: 1009783596581448 | E9: Jakarta | F9: 28543 | G9: Male | H9: Married | I9: =MIN(COUNTIFS('Data Family'!A:A,A9,'Data Family'!F:F,"Child")+COUNTIFS('Data Family'!A:A,A9,'Data Family'!F:F,"<>Child",'Data Family'!J:J,"Housewife")+COUNTIFS('Data Family'!A:A,A9,'Data Family'!F:F,"<>Child",'Data Family'!J:J,"Unemployment"),3) -> 2 | J9: Catholicism | K9: A | L9: 42597 | O9: =IF(AND(M9<>"", M9<=TODAY(), N9=""), "End of Contract", "") | P9: =IF(OR(N9<>"", AND(M9<>"",M9<=TODAY())),"Non-Active","Active") -> Active | Q9: =IF(M9="","PKWTT",IF(DATEDIF(L9,M9,"M")>63,"PKWTT",IF(DATEDIF(L9,M9,"M")>60,"PKWT",IF(DATEDIF(L9,M9,"M")>36,"PKWT",IF(DATEDIF(L9,M9,"M")>12, "PKWT","PKWT"))))) -> PKWTT | R9: Doctoral Degree (S3) | S9: Accounting | T9: Corporate Governance | U9: Audit Committee | V9: Manager | W9: Audit Committee Manager | X9: =_xlfn.XLOOKUP(V9,Reference!$O:$O,Reference!$N:$N,"Tidak Ketemu") -> G06 | Y9: =IF(AND(G9="Female",H9="Married"),"TK/0",IF(H9="Married","K/"&I9,"TK/"&I9)) -> K/2 | Z9: 949524386002951 | AA9: 38036856604 | AB9: 5675077907837 | AC9: BANK BCA | AD9: 3273225386 | AE9: 080222778568 | AF9: dedi.wijaya@dumibumi.co.id | AG9: Tangerang, Indonesia
A10: 202043908 | B10: Andi Ramadhan | C10: 9160452801959615 | D10: 1981732621458966 | E10: Blitar | F10: 33124 | G10: Male | H10: Married | I10: =MIN(COUNTIFS('Data Family'!A:A,A10,'Data Family'!F:F,"Child")+COUNTIFS('Data Family'!A:A,A10,'Data Family'!F:F,"<>Child",'Data Family'!J:J,"Housewife")+COUNTIFS('Data Family'!A:A,A10,'Data Family'!F:F,"<>Child",'Data Family'!J:J,"Unemployment"),3) -> 1 | J10: Islam | K10: B | L10: 43542 | O10: =IF(AND(M10<>"", M10<=TODAY(), N10=""), "End of Contract", "") | P10: =IF(OR(N10<>"", AND(M10<>"",M10<=TODAY())),"Non-Active","Active") -> Active | Q10: =IF(M10="","PKWTT",IF(DATEDIF(L10,M10,"M")>63,"PKWTT",IF(DATEDIF(L10,M10,"M")>60,"PKWT",IF(DATEDIF(L10,M10,"M")>36,"PKWT",IF(DATEDIF(L10,M10,"M")>12, "PKWT","PKWT"))))) -> PKWTT | R10: Master's Degree (S2) | S10: Management | T10: Corporate Governance | U10: Audit Committee | V10: Staff | W10: Audit Committee Staff | X10: =_xlfn.XLOOKUP(V10,Reference!$O:$O,Reference!$N:$N,"Tidak Ketemu") -> G11 | Y10: =IF(AND(G10="Female",H10="Married"),"TK/0",IF(H10="Married","K/"&I10,"TK/"&I10)) -> K/1 | Z10: 688059400228650 | AA10: 81699686056 | AB10: 7271450042870 | AC10: BANK BCA | AD10: 7280495357 | AE10: 083040551531 | AF10: andi.ramadhan@dumibumi.co.id | AG10: Bandung, Indonesia
A11: 202043954 | B11: Nadia Lestari | C11: 7134371159410775 | D11: 7257837349082723 | E11: Bandung | F11: 28118 | G11: Female | H11: Married | I11: =MIN(COUNTIFS('Data Family'!A:A,A11,'Data Family'!F:F,"Child")+COUNTIFS('Data Family'!A:A,A11,'Data Family'!F:F,"<>Child",'Data Family'!J:J,"Housewife")+COUNTIFS('Data Family'!A:A,A11,'Data Family'!F:F,"<>Child",'Data Family'!J:J,"Unemployment"),3) -> 0 | J11: Islam | K11: AB | L11: 38110 | O11: =IF(AND(M11<>"", M11<=TODAY(), N11=""), "End of Contract", "") | P11: =IF(OR(N11<>"", AND(M11<>"",M11<=TODAY())),"Non-Active","Active") -> Active | Q11: =IF(M11="","PKWTT",IF(DATEDIF(L11,M11,"M")>63,"PKWTT",IF(DATEDIF(L11,M11,"M")>60,"PKWT",IF(DATEDIF(L11,M11,"M")>36,"PKWT",IF(DATEDIF(L11,M11,"M")>12, "PKWT","PKWT"))))) -> PKWTT | R11: Master's Degree (S2) | S11: Psychology | T11: Corporate Governance | U11: Board of Commissioners | V11: Chairman Commissioner | W11: Chairman Commissioner | X11: =_xlfn.XLOOKUP(V11,Reference!$O:$O,Reference!$N:$N,"Tidak Ketemu") -> G02 | Y11: =IF(AND(G11="Female",H11="Married"),"TK/0",IF(H11="Married","K/"&I11,"TK/"&I11)) -> TK/0 | Z11: 695365629362010 | AA11: 45394320070 | AB11: 0749322108059 | AC11: BANK BCA | AD11: 1582000195 | AE11: 089416729767 | AF11: nadia.pratama@dumibumi.co.id | AG11: Jakarta, Indonesia
A12: 201943658 | B12: Yusuf Pratama | C12: 5291622520708200 | D12: 2473439042449944 | E12: Pontianak | F12: 28095 | G12: Male | H12: Married | I12: =MIN(COUNTIFS('Data Family'!A:A,A12,'Data Family'!F:F,"Child")+COUNTIFS('Data Family'!A:A,A12,'Data Family'!F:F,"<>Child",'Data Family'!J:J,"Housewife")+COUNTIFS('Data Family'!A:A,A12,'Data Family'!F:F,"<>Child",'Data Family'!J:J,"Unemployment"),3) -> 1 | J12: Islam | K12: O | L12: 37084 | O12: =IF(AND(M12<>"", M12<=TODAY(), N12=""), "End of Contract", "") | P12: =IF(OR(N12<>"", AND(M12<>"",M12<=TODAY())),"Non-Active","Active") -> Active | Q12: =IF(M12="","PKWTT",IF(DATEDIF(L12,M12,"M")>63,"PKWTT",IF(DATEDIF(L12,M12,"M")>60,"PKWT",IF(DATEDIF(L12,M12,"M")>36,"PKWT",IF(DATEDIF(L12,M12,"M")>12, "PKWT","PKWT"))))) -> PKWTT | R12: Master's Degree (S2) | S12: Law | T12: Corporate Governance | U12: Board of Commissioners | V12: Commissioner | W12: Commissioner | X12: =_xlfn.XLOOKUP(V12,Reference!$O:$O,Reference!$N:$N,"Tidak Ketemu") -> G03 | Y12: =IF(AND(G12="Female",H12="Married"),"TK/0",IF(H12="Married","K/"&I12,"TK/"&I12)) -> K/1 | Z12: 544369555345556 | AA12: 75285941818 | AB12: 8437463760121 | AC12: BANK BCA | AD12: 4014998198 | AE12: 080931955459 | AF12: yusuf.pratama@dumibumi.co.id | AG12: Tangerang, Indonesia
A13: 201441797 | B13: Dedi Permata | C13: 1693422781672131 | D13: 6297683498710681 | E13: Banjarmasin | F13: 26323 | G13: Male | H13: Married | I13: =MIN(COUNTIFS('Data Family'!A:A,A13,'Data Family'!F:F,"Child")+COUNTIFS('Data Family'!A:A,A13,'Data Family'!F:F,"<>Child",'Data Family'!J:J,"Housewife")+COUNTIFS('Data Family'!A:A,A13,'Data Family'!F:F,"<>Child",'Data Family'!J:J,"Unemployment"),3) -> 2 | J13: Hinduism | K13: A | L13: 37414 | O13: =IF(AND(M13<>"", M13<=TODAY(), N13=""), "End of Contract", "") | P13: =IF(OR(N13<>"", AND(M13<>"",M13<=TODAY())),"Non-Active","Active") -> Active | Q13: =IF(M13="","PKWTT",IF(DATEDIF(L13,M13,"M")>63,"PKWTT",IF(DATEDIF(L13,M13,"M")>60,"PKWT",IF(DATEDIF(L13,M13,"M")>36,"PKWT",IF(DATEDIF(L13,M13,"M")>12, "PKWT","PKWT"))))) -> PKWTT | R13: Doctoral Degree (S3) | S13: Accounting | T13: Corporate Governance | U13: Board of Commissioners | V13: Commissioner | W13: Commissioner | X13: =_xlfn.XLOOKUP(V13,Reference!$O:$O,Reference!$N:$N,"Tidak Ketemu") -> G03 | Y13: =IF(AND(G13="Female",H13="Married"),"TK/0",IF(H13="Married","K/"&I13,"TK/"&I13)) -> K/2 | Z13: 761373300266873 | AA13: 71401237162 | AB13: 1682486458067 | AC13: BANK BCA | AD13: 6054335163 | AE13: 081075935793 | AF13: dedi.permata@dumibumi.co.id | AG13: Bogor, Indonesia
A14: 202244911 | B14: Monica Putri Ayu | C14: 8868713042755589 | D14: 7700585616611204 | E14: Sukabumi | F14: 32692 | G14: Female | H14: Married | I14: =MIN(COUNTIFS('Data Family'!A:A,A14,'Data Family'!F:F,"Child")+COUNTIFS('Data Family'!A:A,A14,'Data Family'!F:F,"<>Child",'Data Family'!J:J,"Housewife")+COUNTIFS('Data Family'!A:A,A14,'Data Family'!F:F,"<>Child",'Data Family'!J:J,"Unemployment"),3) -> 0 | J14: Catholicism | K14: B | L14: 44911 | M14: 46737 | O14: =IF(AND(M14<>"", M14<=TODAY(), N14=""), "End of Contract", "") | P14: =IF(OR(N14<>"", AND(M14<>"",M14<=TODAY())),"Non-Active","Active") -> Active | Q14: =IF(M14="","PKWTT",IF(DATEDIF(L14,M14,"M")>63,"PKWTT",IF(DATEDIF(L14,M14,"M")>60,"PKWT",IF(DATEDIF(L14,M14,"M")>36,"PKWT",IF(DATEDIF(L14,M14,"M")>12, "PKWT","PKWT"))))) -> PKWT | R14: Master's Degree (S2) | S14: Business Administration | T14: Corporate Governance | U14: Corporate Secretary | V14: Officer / Executive | W14: Corporate Secretary | X14: =_xlfn.XLOOKUP(V14,Reference!$O:$O,Reference!$N:$N,"Tidak Ketemu") -> G10 | Y14: =IF(AND(G14="Female",H14="Married"),"TK/0",IF(H14="Married","K/"&I14,"TK/"&I14)) -> TK/0 | Z14: 495344004861489 | AA14: 73880099287 | AB14: 8313499899159 | AC14: BANK BCA | AD14: 8781658784 | AE14: 088688061334 | AF14: lina.wijaya@dumibumi.co.id | AG14: Tangerang, Indonesia
A15: 201542050 | B15: Fajar Hidayat | C15: 6898050111354868 | D15: 0069685671645996 | E15: Karawang | F15: 33170 | G15: Male | H15: Married | I15: =MIN(COUNTIFS('Data Family'!A:A,A15,'Data Family'!F:F,"Child")+COUNTIFS('Data Family'!A:A,A15,'Data Family'!F:F,"<>Child",'Data Family'!J:J,"Housewife")+COUNTIFS('Data Family'!A:A,A15,'Data Family'!F:F,"<>Child",'Data Family'!J:J,"Unemployment"),3) -> 0 | J15: Protestantism | K15: A | L15: 42050 | O15: =IF(AND(M15<>"", M15<=TODAY(), N15=""), "End of Contract", "") | P15: =IF(OR(N15<>"", AND(M15<>"",M15<=TODAY())),"Non-Active","Active") -> Active | Q15: =IF(M15="","PKWTT",IF(DATEDIF(L15,M15,"M")>63,"PKWTT",IF(DATEDIF(L15,M15,"M")>60,"PKWT",IF(DATEDIF(L15,M15,"M")>36,"PKWT",IF(DATEDIF(L15,M15,"M")>12, "PKWT","PKWT"))))) -> PKWTT | R15: Bachelor's Degree (S1) | S15: Economics | T15: Management | U15: Finance | V15: Officer / Executive | W15: Finance Officer | X15: =_xlfn.XLOOKUP(V15,Reference!$O:$O,Reference!$N:$N,"Tidak Ketemu") -> G10 | Y15: =IF(AND(G15="Female",H15="Married"),"TK/0",IF(H15="Married","K/"&I15,"TK/"&I15)) -> K/0 | Z15: 898971049654288 | AA15: 94680223451 | AB15: 5094269625937 | AC15: BANK BCA | AD15: 2879944152 | AE15: 082061927319 | AF15: fajar.hidayat@dumibumi.co.id | AG15: Bandung, Indonesia
A16: 202144304 | B16: Aulia Wijaya | C16: 5982503451061249 | D16: 9725075839427925 | E16: Banjarbaru | F16: 32735 | G16: Female | H16: Married | I16: =MIN(COUNTIFS('Data Family'!A:A,A16,'Data Family'!F:F,"Child")+COUNTIFS('Data Family'!A:A,A16,'Data Family'!F:F,"<>Child",'Data Family'!J:J,"Housewife")+COUNTIFS('Data Family'!A:A,A16,'Data Family'!F:F,"<>Child",'Data Family'!J:J,"Unemployment"),3) -> 1 | J16: Protestantism | K16: AB | L16: 45765 | M16: 46495 | O16: =IF(AND(M16<>"", M16<=TODAY(), N16=""), "End of Contract", "") | P16: =IF(OR(N16<>"", AND(M16<>"",M16<=TODAY())),"Non-Active","Active") -> Active | Q16: =IF(M16="","PKWTT",IF(DATEDIF(L16,M16,"M")>63,"PKWTT",IF(DATEDIF(L16,M16,"M")>60,"PKWT",IF(DATEDIF(L16,M16,"M")>36,"PKWT",IF(DATEDIF(L16,M16,"M")>12, "PKWT","PKWT"))))) -> PKWT | R16: Bachelor's Degree (S1) | S16: Economics | T16: Management | U16: Finance | V16: Officer / Executive | W16: Finance Officer | X16: =_xlfn.XLOOKUP(V16,Reference!$O:$O,Reference!$N:$N,"Tidak Ketemu") -> G10 | Y16: =IF(AND(G16="Female",H16="Married"),"TK/0",IF(H16="Married","K/"&I16,"TK/"&I16)) -> TK/0 | Z16: 366164511585083 | AA16: 52628474546 | AB16: 2472644929257 | AC16: BANK BCA | AD16: 0653257942 | AE16: 080397593061 | AF16: aulia.wijaya@dumibumi.co.id | AG16: Jakarta, Indonesia
A17: 202043907 | B17: Dewi Sari | C17: 7046351185862305 | D17: 9459454797742185 | E17: Samarinda | F17: 34844 | G17: Female | H17: Widowed | I17: =MIN(COUNTIFS('Data Family'!A:A,A17,'Data Family'!F:F,"Child")+COUNTIFS('Data Family'!A:A,A17,'Data Family'!F:F,"<>Child",'Data Family'!J:J,"Housewife")+COUNTIFS('Data Family'!A:A,A17,'Data Family'!F:F,"<>Child",'Data Family'!J:J,"Unemployment"),3) -> 2 | J17: Islam | K17: O | L17: 43907 | O17: =IF(AND(M17<>"", M17<=TODAY(), N17=""), "End of Contract", "") | P17: =IF(OR(N17<>"", AND(M17<>"",M17<=TODAY())),"Non-Active","Active") -> Active | Q17: =IF(M17="","PKWTT",IF(DATEDIF(L17,M17,"M")>63,"PKWTT",IF(DATEDIF(L17,M17,"M")>60,"PKWT",IF(DATEDIF(L17,M17,"M")>36,"PKWT",IF(DATEDIF(L17,M17,"M")>12, "PKWT","PKWT"))))) -> PKWTT | R17: Bachelor's Degree (S1) | S17: Accounting | T17: Management | U17: Finance | V17: Staff | W17: Finance Staff | X17: =_xlfn.XLOOKUP(V17,Reference!$O:$O,Reference!$N:$N,"Tidak Ketemu") -> G11 | Y17: =IF(AND(G17="Female",H17="Married"),"TK/0",IF(H17="Married","K/"&I17,"TK/"&I17)) -> TK/2 | Z17: 263396533418708 | AA17: 93397124597 | AB17: 3914679964832 | AC17: BANK BCA | AD17: 9298907969 | AE17: 087685367471 | AF17: dewi.sari@dumibumi.co.id | AG17: Depok, Indonesia
A18: 201742744 | B18: Nadia Santoso | C18: 6756449784102128 | D18: 0832902389588048 | E18: Pasuruan | F18: 35872 | G18: Female | H18: Married | I18: =MIN(COUNTIFS('Data Family'!A:A,A18,'Data Family'!F:F,"Child")+COUNTIFS('Data Family'!A:A,A18,'Data Family'!F:F,"<>Child",'Data Family'!J:J,"Housewife")+COUNTIFS('Data Family'!A:A,A18,'Data Family'!F:F,"<>Child",'Data Family'!J:J,"Unemployment"),3) -> 0 | J18: Islam | K18: O | L18: 46031 | M18: 46396 | O18: =IF(AND(M18<>"", M18<=TODAY(), N18=""), "End of Contract", "") | P18: =IF(OR(N18<>"", AND(M18<>"",M18<=TODAY())),"Non-Active","Active") -> Active | Q18: =IF(M18="","PKWTT",IF(DATEDIF(L18,M18,"M")>63,"PKWTT",IF(DATEDIF(L18,M18,"M")>60,"PKWT",IF(DATEDIF(L18,M18,"M")>36,"PKWT",IF(DATEDIF(L18,M18,"M")>12, "PKWT","PKWT"))))) -> PKWT | R18: Bachelor's Degree (S1) | S18: Communication | T18: Management | U18: Finance | V18: Administrator | W18: Finance Administration Staff | X18: =_xlfn.XLOOKUP(V18,Reference!$O:$O,Reference!$N:$N,"Tidak Ketemu") -> G12 | Y18: =IF(AND(G18="Female",H18="Married"),"TK/0",IF(H18="Married","K/"&I18,"TK/"&I18)) -> TK/0 | Z18: 439711887629562 | AA18: 85155573251 | AB18: 1472671998475 | AC18: BANK BCA | AD18: 4733934962 | AE18: 082766903492 | AF18: nadia.santoso@dumibumi.co.id | AG18: Bogor, Indonesia
A19: 202445629 | B19: Jajang Kusuma | C19: 3877001018943814 | D19: 2.2066493e+15 | E19: Pasuruan | F19: 31364 | G19: Male | H19: Married | I19: =MIN(COUNTIFS('Data Family'!A:A,A19,'Data Family'!F:F,"Child")+COUNTIFS('Data Family'!A:A,A19,'Data Family'!F:F,"<>Child",'Data Family'!J:J,"Housewife")+COUNTIFS('Data Family'!A:A,A19,'Data Family'!F:F,"<>Child",'Data Family'!J:J,"Unemployment"),3) -> 0 | J19: Catholicism | K19: B | L19: 42707 | O19: =IF(AND(M19<>"", M19<=TODAY(), N19=""), "End of Contract", "") | P19: =IF(OR(N19<>"", AND(M19<>"",M19<=TODAY())),"Non-Active","Active") -> Active | Q19: =IF(M19="","PKWTT",IF(DATEDIF(L19,M19,"M")>63,"PKWTT",IF(DATEDIF(L19,M19,"M")>60,"PKWT",IF(DATEDIF(L19,M19,"M")>36,"PKWT",IF(DATEDIF(L19,M19,"M")>12, "PKWT","PKWT"))))) -> PKWTT | R19: Master's Degree (S2) | S19: Accounting | T19: Management | U19: Finance | V19: Manager | W19: Finance Manager | X19: =_xlfn.XLOOKUP(V19,Reference!$O:$O,Reference!$N:$N,"Tidak Ketemu") -> G06 | Y19: =IF(AND(G19="Female",H19="Married"),"TK/0",IF(H19="Married","K/"&I19,"TK/"&I19)) -> K/0 | Z19: 143803499431951 | AA19: 06411236925 | AB19: 8723672671458 | AC19: BANK BCA | AD19: 4821837876 | AE19: 085964897453 | AF19: aulia.kusuma@dumibumi.co.id | AG19: Bandung, Indonesia
A20: 201743013 | B20: Bayu Santoso | C20: 9964177721912332 | D20: 2008506307534749 | E20: Karawang | F20: 28809 | G20: Male | H20: Married | I20: =MIN(COUNTIFS('Data Family'!A:A,A20,'Data Family'!F:F,"Child")+COUNTIFS('Data Family'!A:A,A20,'Data Family'!F:F,"<>Child",'Data Family'!J:J,"Housewife")+COUNTIFS('Data Family'!A:A,A20,'Data Family'!F:F,"<>Child",'Data Family'!J:J,"Unemployment"),3) -> 2 | J20: Catholicism | K20: B | L20: 43013 | O20: =IF(AND(M20<>"", M20<=TODAY(), N20=""), "End of Contract", "") | P20: =IF(OR(N20<>"", AND(M20<>"",M20<=TODAY())),"Non-Active","Active") -> Active | Q20: =IF(M20="","PKWTT",IF(DATEDIF(L20,M20,"M")>63,"PKWTT",IF(DATEDIF(L20,M20,"M")>60,"PKWT",IF(DATEDIF(L20,M20,"M")>36,"PKWT",IF(DATEDIF(L20,M20,"M")>12, "PKWT","PKWT"))))) -> PKWTT | R20: Doctoral Degree (S3) | S20: Accounting | T20: Management | U20: Finance | V20: General Manager | W20: General Manager | X20: =_xlfn.XLOOKUP(V20,Reference!$O:$O,Reference!$N:$N,"Tidak Ketemu") -> G05 | Y20: =IF(AND(G20="Female",H20="Married"),"TK/0",IF(H20="Married","K/"&I20,"TK/"&I20)) -> K/2 | Z20: 199317952841093 | AA20: 44115713928 | AB20: 8483334572963 | AC20: BANK BCA | AD20: 0975713985 | AE20: 080595210902 | AF20: bayu.santoso@dumibumi.co.id | AG20: Bandung, Indonesia
A21: 202244751 | B21: Fajar Saputra | C21: 4752176185887151 | D21: 6232132117560140 | E21: Jakarta | F21: 31683 | G21: Male | H21: Married | I21: =MIN(COUNTIFS('Data Family'!A:A,A21,'Data Family'!F:F,"Child")+COUNTIFS('Data Family'!A:A,A21,'Data Family'!F:F,"<>Child",'Data Family'!J:J,"Housewife")+COUNTIFS('Data Family'!A:A,A21,'Data Family'!F:F,"<>Child",'Data Family'!J:J,"Unemployment"),3) -> 0 | J21: Islam | K21: A | L21: 42194 | O21: =IF(AND(M21<>"", M21<=TODAY(), N21=""), "End of Contract", "") | P21: =IF(OR(N21<>"", AND(M21<>"",M21<=TODAY())),"Non-Active","Active") -> Active | Q21: =IF(M21="","PKWTT",IF(DATEDIF(L21,M21,"M")>63,"PKWTT",IF(DATEDIF(L21,M21,"M")>60,"PKWT",IF(DATEDIF(L21,M21,"M")>36,"PKWT",IF(DATEDIF(L21,M21,"M")>12, "PKWT","PKWT"))))) -> PKWTT | R21: Master's Degree (S2) | S21: Accounting | T21: Management | U21: Finance | V21: Supervisor | W21: Finance Supervisor | X21: =_xlfn.XLOOKUP(V21,Reference!$O:$O,Reference!$N:$N,"Tidak Ketemu") -> G07 | Y21: =IF(AND(G21="Female",H21="Married"),"TK/0",IF(H21="Married","K/"&I21,"TK/"&I21)) -> K/0 | Z21: 494080087700032 | AA21: 47670283666 | AB21: 1929086667506 | AC21: BANK BCA | AD21: 3785409084 | AE21: 080993139962 | AF21: fajar.saputra@dumibumi.co.id | AG21: Bandung, Indonesia
A22: 201943709 | B22: Farhan Arif Firmansyah | C22: 7224481878566736 | D22: 2794564114648111 | E22: Jakarta | F22: 32348 | G22: Male | H22: Married | I22: =MIN(COUNTIFS('Data Family'!A:A,A22,'Data Family'!F:F,"Child")+COUNTIFS('Data Family'!A:A,A22,'Data Family'!F:F,"<>Child",'Data Family'!J:J,"Housewife")+COUNTIFS('Data Family'!A:A,A22,'Data Family'!F:F,"<>Child",'Data Family'!J:J,"Unemployment"),3) -> 0 | J22: Islam | K22: A | L22: 42979 | O22: =IF(AND(M22<>"", M22<=TODAY(), N22=""), "End of Contract", "") | P22: =IF(OR(N22<>"", AND(M22<>"",M22<=TODAY())),"Non-Active","Active") -> Active | Q22: =IF(M22="","PKWTT",IF(DATEDIF(L22,M22,"M")>63,"PKWTT",IF(DATEDIF(L22,M22,"M")>60,"PKWT",IF(DATEDIF(L22,M22,"M")>36,"PKWT",IF(DATEDIF(L22,M22,"M")>12, "PKWT","PKWT"))))) -> PKWTT | R22: Master's Degree (S2) | S22: Law | T22: Human Resources | U22: Human Resources & General Affairs | V22: Manager | W22: Human Resources Manager | X22: =_xlfn.XLOOKUP(V22,Reference!$O:$O,Reference!$N:$N,"Tidak Ketemu") -> G06 | Y22: =IF(AND(G22="Female",H22="Married"),"TK/0",IF(H22="Married","K/"&I22,"TK/"&I22)) -> K/0 | Z22: 676791160188610 | AA22: 80544586070 | AB22: 5907762254884 | AC22: BANK BCA | AD22: 4105124328 | AE22: 086298054608 | AF22: farhan.sari@dumibumi.co.id | AG22: Tangerang, Indonesia
A23: 201743013 | B23: Rudi Nugroho | C23: 8497101319935159 | D23: 0197669065659725 | E23: Pontianak | F23: 32853 | G23: Male | H23: Married | I23: =MIN(COUNTIFS('Data Family'!A:A,A23,'Data Family'!F:F,"Child")+COUNTIFS('Data Family'!A:A,A23,'Data Family'!F:F,"<>Child",'Data Family'!J:J,"Housewife")+COUNTIFS('Data Family'!A:A,A23,'Data Family'!F:F,"<>Child",'Data Family'!J:J,"Unemployment"),3) -> 2 | J23: Islam | K23: A | L23: 43743 | O23: =IF(AND(M23<>"", M23<=TODAY(), N23=""), "End of Contract", "") | P23: =IF(OR(N23<>"", AND(M23<>"",M23<=TODAY())),"Non-Active","Active") -> Active | Q23: =IF(M23="","PKWTT",IF(DATEDIF(L23,M23,"M")>63,"PKWTT",IF(DATEDIF(L23,M23,"M")>60,"PKWT",IF(DATEDIF(L23,M23,"M")>36,"PKWT",IF(DATEDIF(L23,M23,"M")>12, "PKWT","PKWT"))))) -> PKWTT | R23: Master's Degree (S2) | S23: Psychology | T23: Human Resources | U23: Human Resources & General Affairs | V23: Supervisor | W23: HR Ops & GA Supervisor | X23: =_xlfn.XLOOKUP(V23,Reference!$O:$O,Reference!$N:$N,"Tidak Ketemu") -> G07 | Y23: =IF(AND(G23="Female",H23="Married"),"TK/0",IF(H23="Married","K/"&I23,"TK/"&I23)) -> K/2 | Z23: 358552492655382 | AA23: 57099509411 | AB23: 2661899472091 | AC23: BANK BCA | AD23: 6415986560 | AE23: 083952384227 | AF23: rudi.nugroho@dumibumi.co.id | AG23: Bandung, Indonesia
A24: 202044117 | B24: Reza Nurfadilah Restu | C24: 7290990647659812 | D24: 6598383403479966 | E24: Pontianak | F24: 33071 | G24: Male | H24: Married | I24: =MIN(COUNTIFS('Data Family'!A:A,A24,'Data Family'!F:F,"Child")+COUNTIFS('Data Family'!A:A,A24,'Data Family'!F:F,"<>Child",'Data Family'!J:J,"Housewife")+COUNTIFS('Data Family'!A:A,A24,'Data Family'!F:F,"<>Child",'Data Family'!J:J,"Unemployment"),3) -> 0 | J24: Islam | K24: O | L24: 43386 | O24: =IF(AND(M24<>"", M24<=TODAY(), N24=""), "End of Contract", "") | P24: =IF(OR(N24<>"", AND(M24<>"",M24<=TODAY())),"Non-Active","Active") -> Active | Q24: =IF(M24="","PKWTT",IF(DATEDIF(L24,M24,"M")>63,"PKWTT",IF(DATEDIF(L24,M24,"M")>60,"PKWT",IF(DATEDIF(L24,M24,"M")>36,"PKWT",IF(DATEDIF(L24,M24,"M")>12, "PKWT","PKWT"))))) -> PKWTT | R24: Master's Degree (S2) | S24: Psychology | T24: Human Resources | U24: Human Resources & General Affairs | V24: Officer / Executive | W24: Learning & Development Officer | X24: =_xlfn.XLOOKUP(V24,Reference!$O:$O,Reference!$N:$N,"Tidak Ketemu") -> G10 | Y24: =IF(AND(G24="Female",H24="Married"),"TK/0",IF(H24="Married","K/"&I24,"TK/"&I24)) -> K/0 | Z24: 924206916648484 | AA24: 72572281606 | AB24: 4689461181583 | AC24: BANK BCA | AD24: 5777535686 | AE24: 083007658580 | AF24: farhan.permata@dumibumi.co.id | AG24: Tangerang, Indonesia
A25: 202043987 | B25: Musdalifah | C25: 2329496771686555 | D25: 8037517371109425 | E25: Singkawang | F25: 33684 | G25: Female | H25: Married | I25: =MIN(COUNTIFS('Data Family'!A:A,A25,'Data Family'!F:F,"Child")+COUNTIFS('Data Family'!A:A,A25,'Data Family'!F:F,"<>Child",'Data Family'!J:J,"Housewife")+COUNTIFS('Data Family'!A:A,A25,'Data Family'!F:F,"<>Child",'Data Family'!J:J,"Unemployment"),3) -> 0 | J25: Islam | K25: AB | L25: 43987 | O25: =IF(AND(M25<>"", M25<=TODAY(), N25=""), "End of Contract", "") | P25: =IF(OR(N25<>"", AND(M25<>"",M25<=TODAY())),"Non-Active","Active") -> Active | Q25: =IF(M25="","PKWTT",IF(DATEDIF(L25,M25,"M")>63,"PKWTT",IF(DATEDIF(L25,M25,"M")>60,"PKWT",IF(DATEDIF(L25,M25,"M")>36,"PKWT",IF(DATEDIF(L25,M25,"M")>12, "PKWT","PKWT"))))) -> PKWTT | R25: Bachelor's Degree (S1) | S25: Psychology | T25: Human Resources | U25: Human Resources & General Affairs | V25: Officer / Executive | W25: HR Communications Officer | X25: =_xlfn.XLOOKUP(V25,Reference!$O:$O,Reference!$N:$N,"Tidak Ketemu") -> G10 | Y25: =IF(AND(G25="Female",H25="Married"),"TK/0",IF(H25="Married","K/"&I25,"TK/"&I25)) -> TK/0 | Z25: 937009148998113 | AA25: 72008129905 | AB25: 2326690143540 | AC25: BANK BCA | AD25: 9553316196 | AE25: 084516707178 | AF25: nadia.wijaya@dumibumi.co.id | AG25: Bogor, Indonesia
A26: 201943752 | B26: Rizky Permata | C26: 4901950672851294 | D26: 9749050973474001 | E26: Banjarmasin | F26: 34230 | G26: Male | H26: Married | I26: =MIN(COUNTIFS('Data Family'!A:A,A26,'Data Family'!F:F,"Child")+COUNTIFS('Data Family'!A:A,A26,'Data Family'!F:F,"<>Child",'Data Family'!J:J,"Housewife")+COUNTIFS('Data Family'!A:A,A26,'Data Family'!F:F,"<>Child",'Data Family'!J:J,"Unemployment"),3) -> 0 | J26: Islam | K26: B | L26: 43752 | O26: =IF(AND(M26<>"", M26<=TODAY(), N26=""), "End of Contract", "") | P26: =IF(OR(N26<>"", AND(M26<>"",M26<=TODAY())),"Non-Active","Active") -> Active | Q26: =IF(M26="","PKWTT",IF(DATEDIF(L26,M26,"M")>63,"PKWTT",IF(DATEDIF(L26,M26,"M")>60,"PKWT",IF(DATEDIF(L26,M26,"M")>36,"PKWT",IF(DATEDIF(L26,M26,"M")>12, "PKWT","PKWT"))))) -> PKWTT | R26: Bachelor's Degree (S1) | S26: Management | T26: Human Resources | U26: Human Resources & General Affairs | V26: Officer / Executive | W26: Payroll & Benefits Officer | X26: =_xlfn.XLOOKUP(V26,Reference!$O:$O,Reference!$N:$N,"Tidak Ketemu") -> G10 | Y26: =IF(AND(G26="Female",H26="Married"),"TK/0",IF(H26="Married","K/"&I26,"TK/"&I26)) -> K/0 | Z26: 063449011015272 | AA26: 33802505957 | AB26: 8905850993780 | AC26: BANK BCA | AD26: 6664172510 | AE26: 080774942620 | AF26: rizky.permata@dumibumi.co.id | AG26: Tangerang, Indonesia
A27: 202144365 | B27: Aulia Pratama | C27: 3061485360217420 | D27: 5592059614579362 | E27: Karawang | F27: 34595 | G27: Female | H27: Married | I27: =MIN(COUNTIFS('Data Family'!A:A,A27,'Data Family'!F:F,"Child")+COUNTIFS('Data Family'!A:A,A27,'Data Family'!F:F,"<>Child",'Data Family'!J:J,"Housewife")+COUNTIFS('Data Family'!A:A,A27,'Data Family'!F:F,"<>Child",'Data Family'!J:J,"Unemployment"),3) -> 2 | J27: Islam | K27: A | L27: 45887 | M27: 46617 | O27: =IF(AND(M27<>"", M27<=TODAY(), N27=""), "End of Contract", "") | P27: =IF(OR(N27<>"", AND(M27<>"",M27<=TODAY())),"Non-Active","Active") -> Active | Q27: =IF(M27="","PKWTT",IF(DATEDIF(L27,M27,"M")>63,"PKWTT",IF(DATEDIF(L27,M27,"M")>60,"PKWT",IF(DATEDIF(L27,M27,"M")>36,"PKWT",IF(DATEDIF(L27,M27,"M")>12, "PKWT","PKWT"))))) -> PKWT | R27: Bachelor's Degree (S1) | S27: Psychology | T27: Human Resources | U27: Human Resources & General Affairs | V27: Staff | W27: Recruitment Staff | X27: =_xlfn.XLOOKUP(V27,Reference!$O:$O,Reference!$N:$N,"Tidak Ketemu") -> G11 | Y27: =IF(AND(G27="Female",H27="Married"),"TK/0",IF(H27="Married","K/"&I27,"TK/"&I27)) -> TK/0 | Z27: 991047804901327 | AA27: 68860886361 | AB27: 5887798353371 | AC27: BANK BCA | AD27: 2838186500 | AE27: 084900489759 | AF27: aulia.pratama@dumibumi.co.id | AG27: Jakarta, Indonesia
A28: 202044146 | B28: Dedi Hidayat | C28: 3682503993384988 | D28: 3784794058906662 | E28: Jakarta | F28: 35139 | G28: Male | H28: Married | I28: =MIN(COUNTIFS('Data Family'!A:A,A28,'Data Family'!F:F,"Child")+COUNTIFS('Data Family'!A:A,A28,'Data Family'!F:F,"<>Child",'Data Family'!J:J,"Housewife")+COUNTIFS('Data Family'!A:A,A28,'Data Family'!F:F,"<>Child",'Data Family'!J:J,"Unemployment"),3) -> 2 | J28: Islam | K28: B | L28: 44146 | O28: =IF(AND(M28<>"", M28<=TODAY(), N28=""), "End of Contract", "") | P28: =IF(OR(N28<>"", AND(M28<>"",M28<=TODAY())),"Non-Active","Active") -> Active | Q28: =IF(M28="","PKWTT",IF(DATEDIF(L28,M28,"M")>63,"PKWTT",IF(DATEDIF(L28,M28,"M")>60,"PKWT",IF(DATEDIF(L28,M28,"M")>36,"PKWT",IF(DATEDIF(L28,M28,"M")>12, "PKWT","PKWT"))))) -> PKWTT | R28: Bachelor's Degree (S1) | S28: Psychology | T28: Human Resources | U28: Human Resources & General Affairs | V28: Staff | W28: Recruitment Staff | X28: =_xlfn.XLOOKUP(V28,Reference!$O:$O,Reference!$N:$N,"Tidak Ketemu") -> G11 | Y28: =IF(AND(G28="Female",H28="Married"),"TK/0",IF(H28="Married","K/"&I28,"TK/"&I28)) -> K/2 | Z28: 504743316587698 | AA28: 13786953244 | AB28: 9580774748841 | AC28: BANK BCA | AD28: 3159217760 | AE28: 089449845925 | AF28: dedi.hidayat@dumibumi.co.id | AG28: Subang, Indonesia
A29: 202044084 | B29: Nisa Noor F. Halimah | C29: 2715407782759011 | D29: 0137335151447948 | E29: Karawang | F29: 35523 | G29: Female | H29: Single | I29: =MIN(COUNTIFS('Data Family'!A:A,A29,'Data Family'!F:F,"Child")+COUNTIFS('Data Family'!A:A,A29,'Data Family'!F:F,"<>Child",'Data Family'!J:J,"Housewife")+COUNTIFS('Data Family'!A:A,A29,'Data Family'!F:F,"<>Child",'Data Family'!J:J,"Unemployment"),3) -> 1 | J29: Islam | K29: O | L29: 44084 | O29: =IF(AND(M29<>"", M29<=TODAY(), N29=""), "End of Contract", "") | P29: =IF(OR(N29<>"", AND(M29<>"",M29<=TODAY())),"Non-Active","Active") -> Active | Q29: =IF(M29="","PKWTT",IF(DATEDIF(L29,M29,"M")>63,"PKWTT",IF(DATEDIF(L29,M29,"M")>60,"PKWT",IF(DATEDIF(L29,M29,"M")>36,"PKWT",IF(DATEDIF(L29,M29,"M")>12, "PKWT","PKWT"))))) -> PKWTT | R29: Bachelor's Degree (S1) | S29: Business Administration | T29: Human Resources | U29: Human Resources & General Affairs | V29: Staff | W29: HR Operations & General Affairs Staff | X29: =_xlfn.XLOOKUP(V29,Reference!$O:$O,Reference!$N:$N,"Tidak Ketemu") -> G11 | Y29: =IF(AND(G29="Female",H29="Married"),"TK/0",IF(H29="Married","K/"&I29,"TK/"&I29)) -> TK/1 | Z29: 073322594670363 | AA29: 08939101080 | AB29: 7377166617547 | AC29: BANK BCA | AD29: 5007694002 | AE29: 088932742962 | AF29: indah.wijaya@dumibumi.co.id | AG29: Bekasi, Indonesia
A30: 201642614 | B30: Andi Maulana | C30: 3496496638576534 | D30: 7959468099866577 | E30: Jakarta | F30: 35692 | G30: Male | H30: Married | I30: =MIN(COUNTIFS('Data Family'!A:A,A30,'Data Family'!F:F,"Child")+COUNTIFS('Data Family'!A:A,A30,'Data Family'!F:F,"<>Child",'Data Family'!J:J,"Housewife")+COUNTIFS('Data Family'!A:A,A30,'Data Family'!F:F,"<>Child",'Data Family'!J:J,"Unemployment"),3) -> 1 | J30: Islam | K30: A | L30: 45536 | M30: 46266 | O30: =IF(AND(M30<>"", M30<=TODAY(), N30=""), "End of Contract", "") | P30: =IF(OR(N30<>"", AND(M30<>"",M30<=TODAY())),"Non-Active","Active") -> Active | Q30: =IF(M30="","PKWTT",IF(DATEDIF(L30,M30,"M")>63,"PKWTT",IF(DATEDIF(L30,M30,"M")>60,"PKWT",IF(DATEDIF(L30,M30,"M")>36,"PKWT",IF(DATEDIF(L30,M30,"M")>12, "PKWT","PKWT"))))) -> PKWT | R30: Bachelor's Degree (S1) | S30: Communication | T30: Human Resources | U30: Human Resources & General Affairs | V30: Staff | W30: Employer Branding Staff | X30: =_xlfn.XLOOKUP(V30,Reference!$O:$O,Reference!$N:$N,"Tidak Ketemu") -> G11 | Y30: =IF(AND(G30="Female",H30="Married"),"TK/0",IF(H30="Married","K/"&I30,"TK/"&I30)) -> K/1 | Z30: 205474012330126 | AA30: 16523507644 | AB30: 2434280652279 | AC30: BANK BCA | AD30: 9927022456 | AE30: 086711232999 | AF30: andi.maulana@dumibumi.co.id | AG30: Subang, Indonesia
A31: 202044094 | B31: Fajar Pratama | C31: 5458739022794273 | D31: 5128183397341910 | E31: Mojokerto | F31: 35927 | G31: Male | H31: Married | I31: =MIN(COUNTIFS('Data Family'!A:A,A31,'Data Family'!F:F,"Child")+COUNTIFS('Data Family'!A:A,A31,'Data Family'!F:F,"<>Child",'Data Family'!J:J,"Housewife")+COUNTIFS('Data Family'!A:A,A31,'Data Family'!F:F,"<>Child",'Data Family'!J:J,"Unemployment"),3) -> 0 | J31: Islam | K31: B | L31: 44094 | O31: =IF(AND(M31<>"", M31<=TODAY(), N31=""), "End of Contract", "") | P31: =IF(OR(N31<>"", AND(M31<>"",M31<=TODAY())),"Non-Active","Active") -> Active | Q31: =IF(M31="","PKWTT",IF(DATEDIF(L31,M31,"M")>63,"PKWTT",IF(DATEDIF(L31,M31,"M")>60,"PKWT",IF(DATEDIF(L31,M31,"M")>36,"PKWT",IF(DATEDIF(L31,M31,"M")>12, "PKWT","PKWT"))))) -> PKWTT | R31: Bachelor's Degree (S1) | S31: Human Resource Management | T31: Human Resources | U31: Human Resources & General Affairs | V31: Staff | W31: HR Operations & General Affairs Staff | X31: =_xlfn.XLOOKUP(V31,Reference!$O:$O,Reference!$N:$N,"Tidak Ketemu") -> G11 | Y31: =IF(AND(G31="Female",H31="Married"),"TK/0",IF(H31="Married","K/"&I31,"TK/"&I31)) -> K/0 | Z31: 605083663912059 | AA31: 67659009859 | AB31: 0202040135988 | AC31: BANK BCA | AD31: 9391913684 | AE31: 083397307192 | AF31: fajar.pratama@dumibumi.co.id | AG31: Bekasi, Indonesia
A32: 202044053 | B32: Dewi Pangestu | C32: 2569700081836758 | D32: 1217641947828083 | E32: Kota Metro | F32: 35803 | G32: Female | H32: Single | I32: =MIN(COUNTIFS('Data Family'!A:A,A32,'Data Family'!F:F,"Child")+COUNTIFS('Data Family'!A:A,A32,'Data Family'!F:F,"<>Child",'Data Family'!J:J,"Housewife")+COUNTIFS('Data Family'!A:A,A32,'Data Family'!F:F,"<>Child",'Data Family'!J:J,"Unemployment"),3) -> 0 | J32: Islam | K32: A | L32: 44053 | O32: =IF(AND(M32<>"", M32<=TODAY(), N32=""), "End of Contract", "") | P32: =IF(OR(N32<>"", AND(M32<>"",M32<=TODAY())),"Non-Active","Active") -> Active | Q32: =IF(M32="","PKWTT",IF(DATEDIF(L32,M32,"M")>63,"PKWTT",IF(DATEDIF(L32,M32,"M")>60,"PKWT",IF(DATEDIF(L32,M32,"M")>36,"PKWT",IF(DATEDIF(L32,M32,"M")>12, "PKWT","PKWT"))))) -> PKWTT | R32: Bachelor's Degree (S1) | S32: Human Resource Management | T32: Human Resources | U32: Human Resources & General Affairs | V32: Staff | W32: HR Operations & General Affairs Staff | X32: =_xlfn.XLOOKUP(V32,Reference!$O:$O,Reference!$N:$N,"Tidak Ketemu") -> G11 | Y32: =IF(AND(G32="Female",H32="Married"),"TK/0",IF(H32="Married","K/"&I32,"TK/"&I32)) -> TK/0 | Z32: 189578904144550 | AA32: 36009597651 | AB32: 3673806833311 | AC32: BANK BCA | AD32: 2522120877 | AE32: 084930023893 | AF32: dewi.pangestu@dumibumi.co.id | AG32: Jakarta, Indonesia
A33: 201642722 | B33: Andi Santoso | C33: 5119088522931083 | D33: 5332839755320470 | E33: Bandung | F33: 35665 | G33: Male | H33: Married | I33: =MIN(COUNTIFS('Data Family'!A:A,A33,'Data Family'!F:F,"Child")+COUNTIFS('Data Family'!A:A,A33,'Data Family'!F:F,"<>Child",'Data Family'!J:J,"Housewife")+COUNTIFS('Data Family'!A:A,A33,'Data Family'!F:F,"<>Child",'Data Family'!J:J,"Unemployment"),3) -> 2 | J33: Islam | K33: A | L33: 45278 | M33: 46374 | O33: =IF(AND(M33<>"", M33<=TODAY(), N33=""), "End of Contract", "") | P33: =IF(OR(N33<>"", AND(M33<>"",M33<=TODAY())),"Non-Active","Active") -> Active | Q33: =IF(M33="","PKWTT",IF(DATEDIF(L33,M33,"M")>63,"PKWTT",IF(DATEDIF(L33,M33,"M")>60,"PKWT",IF(DATEDIF(L33,M33,"M")>36,"PKWT",IF(DATEDIF(L33,M33,"M")>12, "PKWT","PKWT"))))) -> PKWT | R33: Bachelor's Degree (S1) | S33: Law | T33: Human Resources | U33: Human Resources & General Affairs | V33: Staff | W33: Recruitment Staff | X33: =_xlfn.XLOOKUP(V33,Reference!$O:$O,Reference!$N:$N,"Tidak Ketemu") -> G11 | Y33: =IF(AND(G33="Female",H33="Married"),"TK/0",IF(H33="Married","K/"&I33,"TK/"&I33)) -> K/2 | Z33: 732279796893091 | AA33: 78086839561 | AB33: 0160903528526 | AC33: BANK BCA | AD33: 8126968217 | AE33: 086937932951 | AF33: andi.santoso@dumibumi.co.id | AG33: Depok, Indonesia
A34: 202545684 | B34: Siti Nugroho | C34: 5285585449523200 | D34: 9469919393268893 | E34: Depok | F34: 40409 | G34: Female | H34: Single | I34: =MIN(COUNTIFS('Data Family'!A:A,A34,'Data Family'!F:F,"Child")+COUNTIFS('Data Family'!A:A,A34,'Data Family'!F:F,"<>Child",'Data Family'!J:J,"Housewife")+COUNTIFS('Data Family'!A:A,A34,'Data Family'!F:F,"<>Child",'Data Family'!J:J,"Unemployment"),3) -> 0 | J34: Islam | K34: B | L34: 46049 | M34: 46414 | O34: =IF(AND(M34<>"", M34<=TODAY(), N34=""), "End of Contract", "") | P34: =IF(OR(N34<>"", AND(M34<>"",M34<=TODAY())),"Non-Active","Active") -> Active | Q34: =IF(M34="","PKWTT",IF(DATEDIF(L34,M34,"M")>63,"PKWTT",IF(DATEDIF(L34,M34,"M")>60,"PKWT",IF(DATEDIF(L34,M34,"M")>36,"PKWT",IF(DATEDIF(L34,M34,"M")>12, "PKWT","PKWT"))))) -> PKWT | R34: Vocational High School | S34: Marketing | T34: Human Resources | U34: Human Resources & General Affairs | V34: Internship | W34: HR Intern | X34: =_xlfn.XLOOKUP(V34,Reference!$O:$O,Reference!$N:$N,"Tidak Ketemu") -> G14 | Y34: =IF(AND(G34="Female",H34="Married"),"TK/0",IF(H34="Married","K/"&I34,"TK/"&I34)) -> TK/0 | Z34: 830409726072302 | AA34: 56398787625 | AB34: 2164056638379 | AC34: BANK BNI | AD34: 3230524079 | AE34: 088075558518 | AF34: siti.nugroho@dumibumi.co.id | AG34: Bekasi, Indonesia
A35: 202044026 | B35: Ine Agraeni | C35: 9083339653697797 | D35: 6513051105371010 | E35: Bandung | F35: 38615 | G35: Female | H35: Single | I35: =MIN(COUNTIFS('Data Family'!A:A,A35,'Data Family'!F:F,"Child")+COUNTIFS('Data Family'!A:A,A35,'Data Family'!F:F,"<>Child",'Data Family'!J:J,"Housewife")+COUNTIFS('Data Family'!A:A,A35,'Data Family'!F:F,"<>Child",'Data Family'!J:J,"Unemployment"),3) -> 0 | J35: Islam | K35: A | L35: 44026 | O35: =IF(AND(M35<>"", M35<=TODAY(), N35=""), "End of Contract", "") | P35: =IF(OR(N35<>"", AND(M35<>"",M35<=TODAY())),"Non-Active","Active") -> Active | Q35: =IF(M35="","PKWTT",IF(DATEDIF(L35,M35,"M")>63,"PKWTT",IF(DATEDIF(L35,M35,"M")>60,"PKWT",IF(DATEDIF(L35,M35,"M")>36,"PKWT",IF(DATEDIF(L35,M35,"M")>12, "PKWT","PKWT"))))) -> PKWTT | R35: High School | S35: Natural Sciences (IPA) | T35: Human Resources | U35: Human Resources & General Affairs | V35: Administrator | W35: HR Administration | X35: =_xlfn.XLOOKUP(V35,Reference!$O:$O,Reference!$N:$N,"Tidak Ketemu") -> G12 | Y35: =IF(AND(G35="Female",H35="Married"),"TK/0",IF(H35="Married","K/"&I35,"TK/"&I35)) -> TK/0 | Z35: 983767810529223 | AA35: 98210689429 | AB35: 1918407141285 | AC35: BANK BCA | AD35: 3788927309 | AE35: 085063958691 | AF35: aulia.permata@dumibumi.co.id | AG35: Bekasi, Indonesia
A36: 202244602 | B36: Nadia Hidayat | C36: 9334227202863188 | D36: 3586963884205365 | E36: Jakarta | F36: 38615 | G36: Female | H36: Single | I36: =MIN(COUNTIFS('Data Family'!A:A,A36,'Data Family'!F:F,"Child")+COUNTIFS('Data Family'!A:A,A36,'Data Family'!F:F,"<>Child",'Data Family'!J:J,"Housewife")+COUNTIFS('Data Family'!A:A,A36,'Data Family'!F:F,"<>Child",'Data Family'!J:J,"Unemployment"),3) -> 0 | J36: Islam | K36: AB | L36: 44602 | M36: 46428 | O36: =IF(AND(M36<>"", M36<=TODAY(), N36=""), "End of Contract", "") | P36: =IF(OR(N36<>"", AND(M36<>"",M36<=TODAY())),"Non-Active","Active") -> Active | Q36: =IF(M36="","PKWTT",IF(DATEDIF(L36,M36,"M")>63,"PKWTT",IF(DATEDIF(L36,M36,"M")>60,"PKWT",IF(DATEDIF(L36,M36,"M")>36,"PKWT",IF(DATEDIF(L36,M36,"M")>12, "PKWT","PKWT"))))) -> PKWT | R36: High School | S36: Social Sciences (IPS) | T36: Human Resources | U36: Human Resources & General Affairs | V36: Administrator | W36: HR Administration | X36: =_xlfn.XLOOKUP(V36,Reference!$O:$O,Reference!$N:$N,"Tidak Ketemu") -> G12 | Y36: =IF(AND(G36="Female",H36="Married"),"TK/0",IF(H36="Married","K/"&I36,"TK/"&I36)) -> TK/0 | Z36: 927401037922305 | AA36: 10466971453 | AB36: 3101054984658 | AC36: BANK BCA | AD36: 7214975040 | AE36: 081574338885 | AF36: nadia.hidayat@dumibumi.co.id | AG36: Bekasi, Indonesia
A37: 202043999 | B37: Nadia Pangestu | C37: 0473824630353299 | D37: 0919141542823420 | E37: Kota Metro | F37: 08/05/1890 | G37: Male | H37: Married | I37: =MIN(COUNTIFS('Data Family'!A:A,A37,'Data Family'!F:F,"Child")+COUNTIFS('Data Family'!A:A,A37,'Data Family'!F:F,"<>Child",'Data Family'!J:J,"Housewife")+COUNTIFS('Data Family'!A:A,A37,'Data Family'!F:F,"<>Child",'Data Family'!J:J,"Unemployment"),3) -> 0 | J37: Islam | K37: B | L37: 42355 | O37: =IF(AND(M37<>"", M37<=TODAY(), N37=""), "End of Contract", "") | P37: =IF(OR(N37<>"", AND(M37<>"",M37<=TODAY())),"Non-Active","Active") -> Active | Q37: =IF(M37="","PKWTT",IF(DATEDIF(L37,M37,"M")>63,"PKWTT",IF(DATEDIF(L37,M37,"M")>60,"PKWT",IF(DATEDIF(L37,M37,"M")>36,"PKWT",IF(DATEDIF(L37,M37,"M")>12, "PKWT","PKWT"))))) -> PKWTT | R37: Master's Degree (S2) | S37: Information Systems | T37: Information Technology | U37: Information Technology | V37: Manager | W37: IT Manager | X37: =_xlfn.XLOOKUP(V37,Reference!$O:$O,Reference!$N:$N,"Tidak Ketemu") -> G06 | Y37: =IF(AND(G37="Female",H37="Married"),"TK/0",IF(H37="Married","K/"&I37,"TK/"&I37)) -> K/0 | Z37: 930864167101961 | AA37: 11438546054 | AB37: 8323047658039 | AC37: BANK BCA | AD37: 0446261013 | AE37: 088021336142 | AF37: nadia.pangestu@dumibumi.co.id | AG37: Bogor, Indonesia
A38: 201743014 | B38: Putri Sari | C38: 5707066304454774 | D38: 8828781563937789 | E38: Bekasi | F38: 34109 | G38: Male | H38: Married | I38: =MIN(COUNTIFS('Data Family'!A:A,A38,'Data Family'!F:F,"Child")+COUNTIFS('Data Family'!A:A,A38,'Data Family'!F:F,"<>Child",'Data Family'!J:J,"Housewife")+COUNTIFS('Data Family'!A:A,A38,'Data Family'!F:F,"<>Child",'Data Family'!J:J,"Unemployment"),3) -> 0 | J38: Islam | K38: AB | L38: 43014 | O38: =IF(AND(M38<>"", M38<=TODAY(), N38=""), "End of Contract", "") | P38: =IF(OR(N38<>"", AND(M38<>"",M38<=TODAY())),"Non-Active","Active") -> Active | Q38: =IF(M38="","PKWTT",IF(DATEDIF(L38,M38,"M")>63,"PKWTT",IF(DATEDIF(L38,M38,"M")>60,"PKWT",IF(DATEDIF(L38,M38,"M")>36,"PKWT",IF(DATEDIF(L38,M38,"M")>12, "PKWT","PKWT"))))) -> PKWTT | R38: Master's Degree (S2) | S38: Electrical Engineering | T38: Information Technology | U38: Information Technology | V38: Supervisor | W38: IT Supervisor | X38: =_xlfn.XLOOKUP(V38,Reference!$O:$O,Reference!$N:$N,"Tidak Ketemu") -> G07 | Y38: =IF(AND(G38="Female",H38="Married"),"TK/0",IF(H38="Married","K/"&I38,"TK/"&I38)) -> K/0 | Z38: 560980240575843 | AA38: 79695900450 | AB38: 3670292841036 | AC38: BANK BCA | AD38: 9921229167 | AE38: 082466795969 | AF38: putri.sari@dumibumi.co.id | AG38: Tangerang, Indonesia
A39: 201642621 | B39: Siti Kurniawan | C39: 1114736441675886 | D39: 2462027223851864 | E39: Tanjung Pinang | F39: 35425 | G39: Male | H39: Married | I39: =MIN(COUNTIFS('Data Family'!A:A,A39,'Data Family'!F:F,"Child")+COUNTIFS('Data Family'!A:A,A39,'Data Family'!F:F,"<>Child",'Data Family'!J:J,"Housewife")+COUNTIFS('Data Family'!A:A,A39,'Data Family'!F:F,"<>Child",'Data Family'!J:J,"Unemployment"),3) -> 2 | J39: Islam | K39: A | L39: 42621 | O39: =IF(AND(M39<>"", M39<=TODAY(), N39=""), "End of Contract", "") | P39: =IF(OR(N39<>"", AND(M39<>"",M39<=TODAY())),"Non-Active","Active") -> Active | Q39: =IF(M39="","PKWTT",IF(DATEDIF(L39,M39,"M")>63,"PKWTT",IF(DATEDIF(L39,M39,"M")>60,"PKWT",IF(DATEDIF(L39,M39,"M")>36,"PKWT",IF(DATEDIF(L39,M39,"M")>12, "PKWT","PKWT"))))) -> PKWTT | R39: Bachelor's Degree (S1) | S39: Information Systems | T39: Information Technology | U39: Information Technology | V39: Senior Professional / Engineer / Analyst | W39: UI / UX Design | X39: =_xlfn.XLOOKUP(V39,Reference!$O:$O,Reference!$N:$N,"Tidak Ketemu") -> G09 | Y39: =IF(AND(G39="Female",H39="Married"),"TK/0",IF(H39="Married","K/"&I39,"TK/"&I39)) -> K/2 | Z39: 131527098422306 | AA39: 59484094706 | AB39: 5565844127344 | AC39: BANK BCA | AD39: 6284267987 | AE39: 081613550129 | AF39: siti.kurniawan@dumibumi.co.id | AG39: Jakarta, Indonesia
A40: 201642522 | B40: Lina Kurniawan | C40: 5347049884384806 | D40: 4992489172846821 | E40: Depok | F40: 35514 | G40: Male | H40: Married | I40: =MIN(COUNTIFS('Data Family'!A:A,A40,'Data Family'!F:F,"Child")+COUNTIFS('Data Family'!A:A,A40,'Data Family'!F:F,"<>Child",'Data Family'!J:J,"Housewife")+COUNTIFS('Data Family'!A:A,A40,'Data Family'!F:F,"<>Child",'Data Family'!J:J,"Unemployment"),3) -> 2 | J40: Islam | K40: B | L40: 42522 | O40: =IF(AND(M40<>"", M40<=TODAY(), N40=""), "End of Contract", "") | P40: =IF(OR(N40<>"", AND(M40<>"",M40<=TODAY())),"Non-Active","Active") -> Active | Q40: =IF(M40="","PKWTT",IF(DATEDIF(L40,M40,"M")>63,"PKWTT",IF(DATEDIF(L40,M40,"M")>60,"PKWT",IF(DATEDIF(L40,M40,"M")>36,"PKWT",IF(DATEDIF(L40,M40,"M")>12, "PKWT","PKWT"))))) -> PKWTT | R40: Bachelor's Degree (S1) | S40: Information Systems | T40: Information Technology | U40: Information Technology | V40: Senior Professional / Engineer / Analyst | W40: UI / UX Design | X40: =_xlfn.XLOOKUP(V40,Reference!$O:$O,Reference!$N:$N,"Tidak Ketemu") -> G09 | Y40: =IF(AND(G40="Female",H40="Married"),"TK/0",IF(H40="Married","K/"&I40,"TK/"&I40)) -> K/2 | Z40: 654622580915603 | AA40: 99427726824 | AB40: 0668948227055 | AC40: BANK BCA | AD40: 2110317332 | AE40: 084297499812 | AF40: lina.kurniawan@dumibumi.co.id | AG40: Bekasi, Indonesia
A41: 202043964 | B41: Nadia Sari | C41: 4024870709749381 | D41: 7272656753019484 | E41: Depok | F41: 35282 | G41: Male | H41: Married | I41: =MIN(COUNTIFS('Data Family'!A:A,A41,'Data Family'!F:F,"Child")+COUNTIFS('Data Family'!A:A,A41,'Data Family'!F:F,"<>Child",'Data Family'!J:J,"Housewife")+COUNTIFS('Data Family'!A:A,A41,'Data Family'!F:F,"<>Child",'Data Family'!J:J,"Unemployment"),3) -> 1 | J41: Islam | K41: B | L41: 43964 | O41: =IF(AND(M41<>"", M41<=TODAY(), N41=""), "End of Contract", "") | P41: =IF(OR(N41<>"", AND(M41<>"",M41<=TODAY())),"Non-Active","Active") -> Active | Q41: =IF(M41="","PKWTT",IF(DATEDIF(L41,M41,"M")>63,"PKWTT",IF(DATEDIF(L41,M41,"M")>60,"PKWT",IF(DATEDIF(L41,M41,"M")>36,"PKWT",IF(DATEDIF(L41,M41,"M")>12, "PKWT","PKWT"))))) -> PKWTT | R41: Bachelor's Degree (S1) | S41: Information Systems | T41: Information Technology | U41: Information Technology | V41: Senior Professional / Engineer / Analyst | W41: Front End Developer | X41: =_xlfn.XLOOKUP(V41,Reference!$O:$O,Reference!$N:$N,"Tidak Ketemu") -> G09 | Y41: =IF(AND(G41="Female",H41="Married"),"TK/0",IF(H41="Married","K/"&I41,"TK/"&I41)) -> K/1 | Z41: 630039378918151 | AA41: 03091788144 | AB41: 1181637930921 | AC41: BANK BCA | AD41: 7768583172 | AE41: 085701776251 | AF41: nadia.sari@dumibumi.co.id | AG41: Bandung, Indonesia
A42: 202044158 | B42: Indah Wijaya | C42: 4874411048949839 | D42: 7247852454896329 | E42: Bandung | F42: 35295 | G42: Male | H42: Married | I42: =MIN(COUNTIFS('Data Family'!A:A,A42,'Data Family'!F:F,"Child")+COUNTIFS('Data Family'!A:A,A42,'Data Family'!F:F,"<>Child",'Data Family'!J:J,"Housewife")+COUNTIFS('Data Family'!A:A,A42,'Data Family'!F:F,"<>Child",'Data Family'!J:J,"Unemployment"),3) -> 1 | J42: Islam | K42: AB | L42: 44158 | O42: =IF(AND(M42<>"", M42<=TODAY(), N42=""), "End of Contract", "") | P42: =IF(OR(N42<>"", AND(M42<>"",M42<=TODAY())),"Non-Active","Active") -> Active | Q42: =IF(M42="","PKWTT",IF(DATEDIF(L42,M42,"M")>63,"PKWTT",IF(DATEDIF(L42,M42,"M")>60,"PKWT",IF(DATEDIF(L42,M42,"M")>36,"PKWT",IF(DATEDIF(L42,M42,"M")>12, "PKWT","PKWT"))))) -> PKWTT | R42: Bachelor's Degree (S1) | S42: Information Systems | T42: Information Technology | U42: Information Technology | V42: Senior Professional / Engineer / Analyst | W42: Front End Developer | X42: =_xlfn.XLOOKUP(V42,Reference!$O:$O,Reference!$N:$N,"Tidak Ketemu") -> G09 | Y42: =IF(AND(G42="Female",H42="Married"),"TK/0",IF(H42="Married","K/"&I42,"TK/"&I42)) -> K/1 | Z42: 617046602803586 | AA42: 19766353148 | AB42: 4804177692857 | AC42: BANK BCA | AD42: 0755821072 | AE42: 084182337177 | AF42: indah.wijaya@dumibumi.co.id | AG42: Depok, Indonesia
A43: 202144222 | B43: Nadia Kusuma | C43: 3957605305883060 | D43: 7601986664536922 | E43: Tanjung Pinang | F43: 35851 | G43: Male | H43: Single | I43: =MIN(COUNTIFS('Data Family'!A:A,A43,'Data Family'!F:F,"Child")+COUNTIFS('Data Family'!A:A,A43,'Data Family'!F:F,"<>Child",'Data Family'!J:J,"Housewife")+COUNTIFS('Data Family'!A:A,A43,'Data Family'!F:F,"<>Child",'Data Family'!J:J,"Unemployment"),3) -> 0 | J43: Islam | K43: AB | L43: 44222 | O43: =IF(AND(M43<>"", M43<=TODAY(), N43=""), "End of Contract", "") | P43: =IF(OR(N43<>"", AND(M43<>"",M43<=TODAY())),"Non-Active","Active") -> Active | Q43: =IF(M43="","PKWTT",IF(DATEDIF(L43,M43,"M")>63,"PKWTT",IF(DATEDIF(L43,M43,"M")>60,"PKWT",IF(DATEDIF(L43,M43,"M")>36,"PKWT",IF(DATEDIF(L43,M43,"M")>12, "PKWT","PKWT"))))) -> PKWTT | R43: Bachelor's Degree (S1) | S43: Information Systems | T43: Information Technology | U43: Information Technology | V43: Senior Professional / Engineer / Analyst | W43: Back End Developer | X43: =_xlfn.XLOOKUP(V43,Reference!$O:$O,Reference!$N:$N,"Tidak Ketemu") -> G09 | Y43: =IF(AND(G43="Female",H43="Married"),"TK/0",IF(H43="Married","K/"&I43,"TK/"&I43)) -> TK/0 | Z43: 563404768625934 | AA43: 78082684373 | AB43: 9314776012877 | AC43: BANK BCA | AD43: 8162934541 | AE43: 086035963276 | AF43: nadia.kusuma@dumibumi.co.id | AG43: Tangerang, Indonesia
A44: 201642559 | B44: Lina Ramadhan | C44: 5728118943433613 | D44: 6956113246972637 | E44: Depok | F44: 35743 | G44: Female | H44: Single | I44: =MIN(COUNTIFS('Data Family'!A:A,A44,'Data Family'!F:F,"Child")+COUNTIFS('Data Family'!A:A,A44,'Data Family'!F:F,"<>Child",'Data Family'!J:J,"Housewife")+COUNTIFS('Data Family'!A:A,A44,'Data Family'!F:F,"<>Child",'Data Family'!J:J,"Unemployment"),3) -> 0 | J44: Islam | K44: AB | L44: 42559 | O44: =IF(AND(M44<>"", M44<=TODAY(), N44=""), "End of Contract", "") | P44: =IF(OR(N44<>"", AND(M44<>"",M44<=TODAY())),"Non-Active","Active") -> Active | Q44: =IF(M44="","PKWTT",IF(DATEDIF(L44,M44,"M")>63,"PKWTT",IF(DATEDIF(L44,M44,"M")>60,"PKWT",IF(DATEDIF(L44,M44,"M")>36,"PKWT",IF(DATEDIF(L44,M44,"M")>12, "PKWT","PKWT"))))) -> PKWTT | R44: Bachelor's Degree (S1) | S44: Informatics Engineering | T44: Information Technology | U44: Information Technology | V44: Senior Professional / Engineer / Analyst | W44: Back End Developer | X44: =_xlfn.XLOOKUP(V44,Reference!$O:$O,Reference!$N:$N,"Tidak Ketemu") -> G09 | Y44: =IF(AND(G44="Female",H44="Married"),"TK/0",IF(H44="Married","K/"&I44,"TK/"&I44)) -> TK/0 | Z44: 014353514789242 | AA44: 98621455915 | AB44: 1360476448114 | AC44: BANK BCA | AD44: 8270595963 | AE44: 088632444496 | AF44: lina.ramadhan@dumibumi.co.id | AG44: Subang, Indonesia
A45: 201642499 | B45: Rina Santoso | C45: 2443479625063998 | D45: 5260052675651565 | E45: Depok | F45: 36073 | G45: Female | H45: Married | I45: =MIN(COUNTIFS('Data Family'!A:A,A45,'Data Family'!F:F,"Child")+COUNTIFS('Data Family'!A:A,A45,'Data Family'!F:F,"<>Child",'Data Family'!J:J,"Housewife")+COUNTIFS('Data Family'!A:A,A45,'Data Family'!F:F,"<>Child",'Data Family'!J:J,"Unemployment"),3) -> 0 | J45: Islam | K45: AB | L45: 45055 | M45: 46882 | O45: =IF(AND(M45<>"", M45<=TODAY(), N45=""), "End of Contract", "") | P45: =IF(OR(N45<>"", AND(M45<>"",M45<=TODAY())),"Non-Active","Active") -> Active | Q45: =IF(M45="","PKWTT",IF(DATEDIF(L45,M45,"M")>63,"PKWTT",IF(DATEDIF(L45,M45,"M")>60,"PKWT",IF(DATEDIF(L45,M45,"M")>36,"PKWT",IF(DATEDIF(L45,M45,"M")>12, "PKWT","PKWT"))))) -> PKWT | R45: Bachelor's Degree (S1) | S45: Informatics Engineering | T45: Information Technology | U45: Information Technology | V45: Officer / Executive | W45: Programmer | X45: =_xlfn.XLOOKUP(V45,Reference!$O:$O,Reference!$N:$N,"Tidak Ketemu") -> G10 | Y45: =IF(AND(G45="Female",H45="Married"),"TK/0",IF(H45="Married","K/"&I45,"TK/"&I45)) -> TK/0 | Z45: 380114681646630 | AA45: 73025623605 | AB45: 2767046758705 | AC45: BANK BCA | AD45: 4561371186 | AE45: 086411638889 | AF45: rina.santoso@dumibumi.co.id | AG45: Bekasi, Indonesia
A46: 201943613 | B46: Nadia Maulana | C46: 4108960729480398 | D46: 4490598474260364 | E46: Bengkulu | F46: 36059 | G46: Male | H46: Single | I46: =MIN(COUNTIFS('Data Family'!A:A,A46,'Data Family'!F:F,"Child")+COUNTIFS('Data Family'!A:A,A46,'Data Family'!F:F,"<>Child",'Data Family'!J:J,"Housewife")+COUNTIFS('Data Family'!A:A,A46,'Data Family'!F:F,"<>Child",'Data Family'!J:J,"Unemployment"),3) -> 0 | J46: Islam | K46: O | L46: 45440 | M46: 47266 | O46: =IF(AND(M46<>"", M46<=TODAY(), N46=""), "End of Contract", "") | P46: =IF(OR(N46<>"", AND(M46<>"",M46<=TODAY())),"Non-Active","Active") -> Active | Q46: =IF(M46="","PKWTT",IF(DATEDIF(L46,M46,"M")>63,"PKWTT",IF(DATEDIF(L46,M46,"M")>60,"PKWT",IF(DATEDIF(L46,M46,"M")>36,"PKWT",IF(DATEDIF(L46,M46,"M")>12, "PKWT","PKWT"))))) -> PKWT | R46: Bachelor's Degree (S1) | S46: Informatics Engineering | T46: Information Technology | U46: Information Technology | V46: Officer / Executive | W46: Programmer | X46: =_xlfn.XLOOKUP(V46,Reference!$O:$O,Reference!$N:$N,"Tidak Ketemu") -> G10 | Y46: =IF(AND(G46="Female",H46="Married"),"TK/0",IF(H46="Married","K/"&I46,"TK/"&I46)) -> TK/0 | Z46: 045800047417302 | AA46: 35908729103 | AB46: 8925481235171 | AC46: BANK BCA | AD46: 6948413087 | AE46: 083422856524 | AF46: nadia.maulana@dumibumi.co.id | AG46: Bogor, Indonesia
A47: 202043913 | B47: Indah Saputra | C47: 8355332453862826 | D47: 5841745763698831 | E47: Bandung | F47: 36091 | G47: Male | H47: Single | I47: =MIN(COUNTIFS('Data Family'!A:A,A47,'Data Family'!F:F,"Child")+COUNTIFS('Data Family'!A:A,A47,'Data Family'!F:F,"<>Child",'Data Family'!J:J,"Housewife")+COUNTIFS('Data Family'!A:A,A47,'Data Family'!F:F,"<>Child",'Data Family'!J:J,"Unemployment"),3) -> 0 | J47: Islam | K47: AB | L47: 45739 | M47: 46469 | O47: =IF(AND(M47<>"", M47<=TODAY(), N47=""), "End of Contract", "") | P47: =IF(OR(N47<>"", AND(M47<>"",M47<=TODAY())),"Non-Active","Active") -> Active | Q47: =IF(M47="","PKWTT",IF(DATEDIF(L47,M47,"M")>63,"PKWTT",IF(DATEDIF(L47,M47,"M")>60,"PKWT",IF(DATEDIF(L47,M47,"M")>36,"PKWT",IF(DATEDIF(L47,M47,"M")>12, "PKWT","PKWT"))))) -> PKWT | R47: Bachelor's Degree (S1) | S47: Informatics Engineering | T47: Information Technology | U47: Information Technology | V47: Officer / Executive | W47: Programmer | X47: =_xlfn.XLOOKUP(V47,Reference!$O:$O,Reference!$N:$N,"Tidak Ketemu") -> G10 | Y47: =IF(AND(G47="Female",H47="Married"),"TK/0",IF(H47="Married","K/"&I47,"TK/"&I47)) -> TK/0 | Z47: 163453660811325 | AA47: 21456815181 | AB47: 2568381463485 | AC47: BANK BCA | AD47: 7878359876 | AE47: 081796317337 | AF47: indah.saputra@dumibumi.co.id | AG47: Bogor, Indonesia
A48: 202244621 | B48: Adi Hidayat | C48: 5995011732001160 | D48: 6989533581855561 | E48: Subang | F48: 36302 | G48: Male | H48: Single | I48: =MIN(COUNTIFS('Data Family'!A:A,A48,'Data Family'!F:F,"Child")+COUNTIFS('Data Family'!A:A,A48,'Data Family'!F:F,"<>Child",'Data Family'!J:J,"Housewife")+COUNTIFS('Data Family'!A:A,A48,'Data Family'!F:F,"<>Child",'Data Family'!J:J,"Unemployment"),3) -> 0 | J48: Islam | K48: AB | L48: 44621 | M48: 46447 | O48: =IF(AND(M48<>"", M48<=TODAY(), N48=""), "End of Contract", "") | P48: =IF(OR(N48<>"", AND(M48<>"",M48<=TODAY())),"Non-Active","Active") -> Active | Q48: =IF(M48="","PKWTT",IF(DATEDIF(L48,M48,"M")>63,"PKWTT",IF(DATEDIF(L48,M48,"M")>60,"PKWT",IF(DATEDIF(L48,M48,"M")>36,"PKWT",IF(DATEDIF(L48,M48,"M")>12, "PKWT","PKWT"))))) -> PKWT | R48: Bachelor's Degree (S1) | S48: Law | T48: Legal & Compliance | U48: Legal | V48: Officer / Executive | W48: Legal Officer | X48: =_xlfn.XLOOKUP(V48,Reference!$O:$O,Reference!$N:$N,"Tidak Ketemu") -> G10 | Y48: =IF(AND(G48="Female",H48="Married"),"TK/0",IF(H48="Married","K/"&I48,"TK/"&I48)) -> TK/0 | Z48: 484883283654523 | AA48: 61125878094 | AB48: 4555983397827 | AC48: BANK BCA | AD48: 1701745986 | AE48: 083113698790 | AF48: siti.hidayat@dumibumi.co.id | AG48: Depok, Indonesia
A49: 201742985 | B49: Aulia Lestari | C49: 6066822057382880 | D49: 1654518842360613 | E49: Depok | F49: 35723 | G49: Male | H49: Married | I49: =MIN(COUNTIFS('Data Family'!A:A,A49,'Data Family'!F:F,"Child")+COUNTIFS('Data Family'!A:A,A49,'Data Family'!F:F,"<>Child",'Data Family'!J:J,"Housewife")+COUNTIFS('Data Family'!A:A,A49,'Data Family'!F:F,"<>Child",'Data Family'!J:J,"Unemployment"),3) -> 0 | J49: Islam | K49: AB | L49: 44081 | O49: =IF(AND(M49<>"", M49<=TODAY(), N49=""), "End of Contract", "") | P49: =IF(OR(N49<>"", AND(M49<>"",M49<=TODAY())),"Non-Active","Active") -> Active | Q49: =IF(M49="","PKWTT",IF(DATEDIF(L49,M49,"M")>63,"PKWTT",IF(DATEDIF(L49,M49,"M")>60,"PKWT",IF(DATEDIF(L49,M49,"M")>36,"PKWT",IF(DATEDIF(L49,M49,"M")>12, "PKWT","PKWT"))))) -> PKWTT | R49: Bachelor's Degree (S1) | S49: Electrical Engineering | T49: Information Technology | U49: Information Technology | V49: Staff | W49: IT Support | X49: =_xlfn.XLOOKUP(V49,Reference!$O:$O,Reference!$N:$N,"Tidak Ketemu") -> G11 | Y49: =IF(AND(G49="Female",H49="Married"),"TK/0",IF(H49="Married","K/"&I49,"TK/"&I49)) -> K/0 | Z49: 406859770190964 | AA49: 14599637774 | AB49: 8928709823301 | AC49: BANK BCA | AD49: 4937108536 | AE49: 089669472628 | AF49: aulia.lestari@dumibumi.co.id | AG49: Bekasi, Indonesia
A50: 202545966 | B50: Dewi Maulana | C50: 5351551497690578 | D50: 1409403554588831 | E50: Jakarta | F50: 36348 | G50: Male | H50: Single | I50: =MIN(COUNTIFS('Data Family'!A:A,A50,'Data Family'!F:F,"Child")+COUNTIFS('Data Family'!A:A,A50,'Data Family'!F:F,"<>Child",'Data Family'!J:J,"Housewife")+COUNTIFS('Data Family'!A:A,A50,'Data Family'!F:F,"<>Child",'Data Family'!J:J,"Unemployment"),3) -> 0 | J50: Islam | K50: B | L50: 45966 | M50: 46696 | O50: =IF(AND(M50<>"", M50<=TODAY(), N50=""), "End of Contract", "") | P50: =IF(OR(N50<>"", AND(M50<>"",M50<=TODAY())),"Non-Active","Active") -> Active | Q50: =IF(M50="","PKWTT",IF(DATEDIF(L50,M50,"M")>63,"PKWTT",IF(DATEDIF(L50,M50,"M")>60,"PKWT",IF(DATEDIF(L50,M50,"M")>36,"PKWT",IF(DATEDIF(L50,M50,"M")>12, "PKWT","PKWT"))))) -> PKWT | R50: Bachelor's Degree (S1) | S50: Electrical Engineering | T50: Information Technology | U50: Information Technology | V50: Staff | W50: IT Support | X50: =_xlfn.XLOOKUP(V50,Reference!$O:$O,Reference!$N:$N,"Tidak Ketemu") -> G11 | Y50: =IF(AND(G50="Female",H50="Married"),"TK/0",IF(H50="Married","K/"&I50,"TK/"&I50)) -> TK/0 | Z50: 261362182598483 | AA50: 47791112173 | AB50: 3557543282727 | AC50: BANK BCA | AD50: 3035909920 | AE50: 082429972984 | AF50: dewi.maulana@dumibumi.co.id | AG50: Subang, Indonesia
A51: 201843438 | B51: Aulia Maulana | C51: 7415306165346308 | D51: 0671008012347717 | E51: Bogor | F51: 36581 | G51: Female | H51: Single | I51: =MIN(COUNTIFS('Data Family'!A:A,A51,'Data Family'!F:F,"Child")+COUNTIFS('Data Family'!A:A,A51,'Data Family'!F:F,"<>Child",'Data Family'!J:J,"Housewife")+COUNTIFS('Data Family'!A:A,A51,'Data Family'!F:F,"<>Child",'Data Family'!J:J,"Unemployment"),3) -> 0 | J51: Islam | K51: B | L51: 44899 | M51: 46725 | O51: =IF(AND(M51<>"", M51<=TODAY(), N51=""), "End of Contract", "") | P51: =IF(OR(N51<>"", AND(M51<>"",M51<=TODAY())),"Non-Active","Active") -> Active | Q51: =IF(M51="","PKWTT",IF(DATEDIF(L51,M51,"M")>63,"PKWTT",IF(DATEDIF(L51,M51,"M")>60,"PKWT",IF(DATEDIF(L51,M51,"M")>36,"PKWT",IF(DATEDIF(L51,M51,"M")>12, "PKWT","PKWT"))))) -> PKWT | R51: Bachelor's Degree (S1) | S51: Electrical Engineering | T51: Information Technology | U51: Information Technology | V51: Staff | W51: IT Support | X51: =_xlfn.XLOOKUP(V51,Reference!$O:$O,Reference!$N:$N,"Tidak Ketemu") -> G11 | Y51: =IF(AND(G51="Female",H51="Married"),"TK/0",IF(H51="Married","K/"&I51,"TK/"&I51)) -> TK/0 | Z51: 410262291636366 | AA51: 40660769840 | AB51: 4925611989804 | AC51: BANK BCA | AD51: 4399441423 | AE51: 089298086760 | AF51: aulia.maulana@dumibumi.co.id | AG51: Depok, Indonesia
A52: 202545815 | B52: Ardi Kusuma | C52: 1154420526768749 | D52: 2366370605188285 | E52: Bogor | F52: 36597 | G52: Male | H52: Single | I52: =MIN(COUNTIFS('Data Family'!A:A,A52,'Data Family'!F:F,"Child")+COUNTIFS('Data Family'!A:A,A52,'Data Family'!F:F,"<>Child",'Data Family'!J:J,"Housewife")+COUNTIFS('Data Family'!A:A,A52,'Data Family'!F:F,"<>Child",'Data Family'!J:J,"Unemployment"),3) -> 0 | J52: Islam | K52: A | L52: 45450 | M52: 46545 | O52: =IF(AND(M52<>"", M52<=TODAY(), N52=""), "End of Contract", "") | P52: =IF(OR(N52<>"", AND(M52<>"",M52<=TODAY())),"Non-Active","Active") -> Active | Q52: =IF(M52="","PKWTT",IF(DATEDIF(L52,M52,"M")>63,"PKWTT",IF(DATEDIF(L52,M52,"M")>60,"PKWT",IF(DATEDIF(L52,M52,"M")>36,"PKWT",IF(DATEDIF(L52,M52,"M")>12, "PKWT","PKWT"))))) -> PKWT | R52: Bachelor's Degree (S1) | S52: Law | T52: Legal & Compliance | U52: Legal | V52: Officer / Executive | W52: Legal Officer | X52: =_xlfn.XLOOKUP(V52,Reference!$O:$O,Reference!$N:$N,"Tidak Ketemu") -> G10 | Y52: =IF(AND(G52="Female",H52="Married"),"TK/0",IF(H52="Married","K/"&I52,"TK/"&I52)) -> TK/0 | Z52: 195065836024436 | AA52: 93733135915 | AB52: 3006394262150 | AC52: BANK BCA | AD52: 2056683679 | AE52: 089866785779 | AF52: putri.kusuma@dumibumi.co.id | AG52: Bandung, Indonesia
A53: 201843428 | B53: Indra Ramadhan | C53: 7938862013006593 | D53: 9293821270031290 | E53: Bekasi | F53: 40004 | G53: Male | H53: Single | I53: =MIN(COUNTIFS('Data Family'!A:A,A53,'Data Family'!F:F,"Child")+COUNTIFS('Data Family'!A:A,A53,'Data Family'!F:F,"<>Child",'Data Family'!J:J,"Housewife")+COUNTIFS('Data Family'!A:A,A53,'Data Family'!F:F,"<>Child",'Data Family'!J:J,"Unemployment"),3) -> 0 | J53: Islam | K53: A | L53: 45985 | M53: 46350 | O53: =IF(AND(M53<>"", M53<=TODAY(), N53=""), "End of Contract", "") | P53: =IF(OR(N53<>"", AND(M53<>"",M53<=TODAY())),"Non-Active","Active") -> Active | Q53: =IF(M53="","PKWTT",IF(DATEDIF(L53,M53,"M")>63,"PKWTT",IF(DATEDIF(L53,M53,"M")>60,"PKWT",IF(DATEDIF(L53,M53,"M")>36,"PKWT",IF(DATEDIF(L53,M53,"M")>12, "PKWT","PKWT"))))) -> PKWT | R53: Vocational High School | S53: Software Engineering (RPL) | T53: Information Technology | U53: Information Technology | V53: Internship | W53: Data Entry Intern | X53: =_xlfn.XLOOKUP(V53,Reference!$O:$O,Reference!$N:$N,"Tidak Ketemu") -> G14 | Y53: =IF(AND(G53="Female",H53="Married"),"TK/0",IF(H53="Married","K/"&I53,"TK/"&I53)) -> TK/0 | Z53: 801446996424805 | AA53: 79209407126 | AB53: 7933642516424 | AC53: BANK BNI | AD53: 4776206322 | AE53: 085137067219 | AF53: indah.ramadhan@dumibumi.co.id | AG53: Tangerang, Indonesia
A54: 201642522 | B54: Putra Saputra | C54: 0318891500811845 | D54: 6252886937281379 | E54: Tangerang | F54: 40080 | G54: Male | H54: Single | I54: =MIN(COUNTIFS('Data Family'!A:A,A54,'Data Family'!F:F,"Child")+COUNTIFS('Data Family'!A:A,A54,'Data Family'!F:F,"<>Child",'Data Family'!J:J,"Housewife")+COUNTIFS('Data Family'!A:A,A54,'Data Family'!F:F,"<>Child",'Data Family'!J:J,"Unemployment"),3) -> 2 | J54: Islam | K54: A | L54: 46174 | M54: 46539 | O54: =IF(AND(M54<>"", M54<=TODAY(), N54=""), "End of Contract", "") | P54: =IF(OR(N54<>"", AND(M54<>"",M54<=TODAY())),"Non-Active","Active") -> Active | Q54: =IF(M54="","PKWTT",IF(DATEDIF(L54,M54,"M")>63,"PKWTT",IF(DATEDIF(L54,M54,"M")>60,"PKWT",IF(DATEDIF(L54,M54,"M")>36,"PKWT",IF(DATEDIF(L54,M54,"M")>12, "PKWT","PKWT"))))) -> PKWT | R54: Vocational High School | S54: Software Engineering (RPL) | T54: Information Technology | U54: Information Technology | V54: Internship | W54: Data Entry Intern | X54: =_xlfn.XLOOKUP(V54,Reference!$O:$O,Reference!$N:$N,"Tidak Ketemu") -> G14 | Y54: =IF(AND(G54="Female",H54="Married"),"TK/0",IF(H54="Married","K/"&I54,"TK/"&I54)) -> TK/2 | Z54: 667967527305453 | AA54: 39997154725 | AB54: 0454696108112 | AC54: BANK BNI | AD54: 5650041799 | AE54: 089759705283 | AF54: putri.saputra@dumibumi.co.id | AG54: Jakarta, Indonesia
A55: 202345041 | B55: Putri Kusuma | C55: 1355956124799994 | D55: 9756803375309701 | E55: Cikampek | F55: 36257 | G55: Female | H55: Married | I55: =MIN(COUNTIFS('Data Family'!A:A,A55,'Data Family'!F:F,"Child")+COUNTIFS('Data Family'!A:A,A55,'Data Family'!F:F,"<>Child",'Data Family'!J:J,"Housewife")+COUNTIFS('Data Family'!A:A,A55,'Data Family'!F:F,"<>Child",'Data Family'!J:J,"Unemployment"),3) -> 1 | J55: Islam | K55: B | L55: 45041 | M55: 46868 | O55: =IF(AND(M55<>"", M55<=TODAY(), N55=""), "End of Contract", "") | P55: =IF(OR(N55<>"", AND(M55<>"",M55<=TODAY())),"Non-Active","Active") -> Active | Q55: =IF(M55="","PKWTT",IF(DATEDIF(L55,M55,"M")>63,"PKWTT",IF(DATEDIF(L55,M55,"M")>60,"PKWT",IF(DATEDIF(L55,M55,"M")>36,"PKWT",IF(DATEDIF(L55,M55,"M")>12, "PKWT","PKWT"))))) -> PKWT | R55: Bachelor's Degree (S1) | S55: Marketing | T55: Commercial & Marketing | U55: Marketing | V55: Officer / Executive | W55: Marketing Officer | X55: =_xlfn.XLOOKUP(V55,Reference!$O:$O,Reference!$N:$N,"Tidak Ketemu") -> G10 | Y55: =IF(AND(G55="Female",H55="Married"),"TK/0",IF(H55="Married","K/"&I55,"TK/"&I55)) -> TK/0 | Z55: 310517269764076 | AA55: 21143615666 | AB55: 9231851433536 | AC55: BANK BCA | AD55: 4573727421 | AE55: 084506094057 | AF55: putri.kusuma@dumibumi.co.id | AG55: Bekasi, Indonesia
A56: 201642675 | B56: Kadek Dwi Arum | C56: 8816426738794801 | D56: 3204761041223093 | E56: Bukittinggi | F56: 29875 | G56: Female | H56: Married | I56: =MIN(COUNTIFS('Data Family'!A:A,A56,'Data Family'!F:F,"Child")+COUNTIFS('Data Family'!A:A,A56,'Data Family'!F:F,"<>Child",'Data Family'!J:J,"Housewife")+COUNTIFS('Data Family'!A:A,A56,'Data Family'!F:F,"<>Child",'Data Family'!J:J,"Unemployment"),3) -> 1 | J56: Buddhism | K56: AB | L56: 43405 | O56: =IF(AND(M56<>"", M56<=TODAY(), N56=""), "End of Contract", "") | P56: =IF(OR(N56<>"", AND(M56<>"",M56<=TODAY())),"Non-Active","Active") -> Active | Q56: =IF(M56="","PKWTT",IF(DATEDIF(L56,M56,"M")>63,"PKWTT",IF(DATEDIF(L56,M56,"M")>60,"PKWT",IF(DATEDIF(L56,M56,"M")>36,"PKWT",IF(DATEDIF(L56,M56,"M")>12, "PKWT","PKWT"))))) -> PKWTT | R56: Doctoral Degree (S3) | S56: Marketing | T56: Commercial & Marketing | U56: Marketing | V56: Manager | W56: Commercial & Marketing Manager | X56: =_xlfn.XLOOKUP(V56,Reference!$O:$O,Reference!$N:$N,"Tidak Ketemu") -> G06 | Y56: =IF(AND(G56="Female",H56="Married"),"TK/0",IF(H56="Married","K/"&I56,"TK/"&I56)) -> TK/0 | Z56: 417230406882203 | AA56: 77864938861 | AB56: 1524707776238 | AC56: BANK BCA | AD56: 6321666984 | AE56: 087740537727 | AF56: dewi.pratama@dumibumi.co.id | AG56: Depok, Indonesia
A57: 202044084 | B57: Adi Hidayat | C57: 7892092783217236 | D57: 8482558623155840 | E57: Karawang | F57: 33678 | G57: Male | H57: Married | I57: =MIN(COUNTIFS('Data Family'!A:A,A57,'Data Family'!F:F,"Child")+COUNTIFS('Data Family'!A:A,A57,'Data Family'!F:F,"<>Child",'Data Family'!J:J,"Housewife")+COUNTIFS('Data Family'!A:A,A57,'Data Family'!F:F,"<>Child",'Data Family'!J:J,"Unemployment"),3) -> 1 | J57: Protestantism | K57: B | L57: 42257 | O57: =IF(AND(M57<>"", M57<=TODAY(), N57=""), "End of Contract", "") | P57: =IF(OR(N57<>"", AND(M57<>"",M57<=TODAY())),"Non-Active","Active") -> Active | Q57: =IF(M57="","PKWTT",IF(DATEDIF(L57,M57,"M")>63,"PKWTT",IF(DATEDIF(L57,M57,"M")>60,"PKWT",IF(DATEDIF(L57,M57,"M")>36,"PKWT",IF(DATEDIF(L57,M57,"M")>12, "PKWT","PKWT"))))) -> PKWTT | R57: Master's Degree (S2) | S57: Marketing | T57: Commercial & Marketing | U57: Marketing | V57: Supervisor | W57: Marketing Supervisor | X57: =_xlfn.XLOOKUP(V57,Reference!$O:$O,Reference!$N:$N,"Tidak Ketemu") -> G07 | Y57: =IF(AND(G57="Female",H57="Married"),"TK/0",IF(H57="Married","K/"&I57,"TK/"&I57)) -> K/1 | Z57: 468167542165060 | AA57: 78355514459 | AB57: 8523902549763 | AC57: BANK BCA | AD57: 3687726198 | AE57: 081777035231 | AF57: dewi.hidayat@dumibumi.co.id | AG57: Bogor, Indonesia
A58: 202545791 | B58: Siti Santoso | C58: 3376305135887154 | D58: 9763789239727901 | E58: Samarinda | F58: 36243 | G58: Female | H58: Married | I58: =MIN(COUNTIFS('Data Family'!A:A,A58,'Data Family'!F:F,"Child")+COUNTIFS('Data Family'!A:A,A58,'Data Family'!F:F,"<>Child",'Data Family'!J:J,"Housewife")+COUNTIFS('Data Family'!A:A,A58,'Data Family'!F:F,"<>Child",'Data Family'!J:J,"Unemployment"),3) -> 1 | J58: Islam | K58: B | L58: 45791 | M58: 46887 | O58: =IF(AND(M58<>"", M58<=TODAY(), N58=""), "End of Contract", "") | P58: =IF(OR(N58<>"", AND(M58<>"",M58<=TODAY())),"Non-Active","Active") -> Active | Q58: =IF(M58="","PKWTT",IF(DATEDIF(L58,M58,"M")>63,"PKWTT",IF(DATEDIF(L58,M58,"M")>60,"PKWT",IF(DATEDIF(L58,M58,"M")>36,"PKWT",IF(DATEDIF(L58,M58,"M")>12, "PKWT","PKWT"))))) -> PKWT | R58: Bachelor's Degree (S1) | S58: Marketing | T58: Commercial & Marketing | U58: Marketing | V58: Officer / Executive | W58: Marketing Officer | X58: =_xlfn.XLOOKUP(V58,Reference!$O:$O,Reference!$N:$N,"Tidak Ketemu") -> G10 | Y58: =IF(AND(G58="Female",H58="Married"),"TK/0",IF(H58="Married","K/"&I58,"TK/"&I58)) -> TK/0 | Z58: 299971637250247 | AA58: 55549966415 | AB58: 0038918465582 | AC58: BANK BCA | AD58: 6261602695 | AE58: 086341346805 | AF58: siti.santoso@dumibumi.co.id | AG58: Jakarta, Indonesia
A59: 201843255 | B59: Aulia Ramadhan | C59: 6994535688750328 | D59: 3752767456233787 | E59: Jakarta | F59: 36519 | G59: Female | H59: Married | I59: =MIN(COUNTIFS('Data Family'!A:A,A59,'Data Family'!F:F,"Child")+COUNTIFS('Data Family'!A:A,A59,'Data Family'!F:F,"<>Child",'Data Family'!J:J,"Housewife")+COUNTIFS('Data Family'!A:A,A59,'Data Family'!F:F,"<>Child",'Data Family'!J:J,"Unemployment"),3) -> 1 | J59: Islam | K59: B | L59: 43986 | O59: =IF(AND(M59<>"", M59<=TODAY(), N59=""), "End of Contract", "") | P59: =IF(OR(N59<>"", AND(M59<>"",M59<=TODAY())),"Non-Active","Active") -> Active | Q59: =IF(M59="","PKWTT",IF(DATEDIF(L59,M59,"M")>63,"PKWTT",IF(DATEDIF(L59,M59,"M")>60,"PKWT",IF(DATEDIF(L59,M59,"M")>36,"PKWT",IF(DATEDIF(L59,M59,"M")>12, "PKWT","PKWT"))))) -> PKWTT | R59: Bachelor's Degree (S1) | S59: Marketing | T59: Commercial & Marketing | U59: Marketing | V59: Officer / Executive | W59: Marketing Officer | X59: =_xlfn.XLOOKUP(V59,Reference!$O:$O,Reference!$N:$N,"Tidak Ketemu") -> G10 | Y59: =IF(AND(G59="Female",H59="Married"),"TK/0",IF(H59="Married","K/"&I59,"TK/"&I59)) -> TK/0 | Z59: 087060350503219 | AA59: 30708633962 | AB59: 2687357548424 | AC59: BANK BCA | AD59: 1553426166 | AE59: 086352494136 | AF59: aulia.ramadhan@dumibumi.co.id | AG59: Bekasi, Indonesia
A60: 201843330 | B60: Rizky Pratama | C60: 7302165213126468 | D60: 3217819719316922 | E60: Palembang | F60: 36079 | G60: Male | H60: Single | I60: =MIN(COUNTIFS('Data Family'!A:A,A60,'Data Family'!F:F,"Child")+COUNTIFS('Data Family'!A:A,A60,'Data Family'!F:F,"<>Child",'Data Family'!J:J,"Housewife")+COUNTIFS('Data Family'!A:A,A60,'Data Family'!F:F,"<>Child",'Data Family'!J:J,"Unemployment"),3) -> 0 | J60: Islam | K60: O | L60: 44791 | M60: 46617 | O60: =IF(AND(M60<>"", M60<=TODAY(), N60=""), "End of Contract", "") | P60: =IF(OR(N60<>"", AND(M60<>"",M60<=TODAY())),"Non-Active","Active") -> Active | Q60: =IF(M60="","PKWTT",IF(DATEDIF(L60,M60,"M")>63,"PKWTT",IF(DATEDIF(L60,M60,"M")>60,"PKWT",IF(DATEDIF(L60,M60,"M")>36,"PKWT",IF(DATEDIF(L60,M60,"M")>12, "PKWT","PKWT"))))) -> PKWT | R60: Bachelor's Degree (S1) | S60: Marketing | T60: Commercial & Marketing | U60: Marketing | V60: Officer / Executive | W60: Marketing Officer | X60: =_xlfn.XLOOKUP(V60,Reference!$O:$O,Reference!$N:$N,"Tidak Ketemu") -> G10 | Y60: =IF(AND(G60="Female",H60="Married"),"TK/0",IF(H60="Married","K/"&I60,"TK/"&I60)) -> TK/0 | Z60: 823460245458136 | AA60: 85181996130 | AB60: 0015117678528 | AC60: BANK BCA | AD60: 6179363152 | AE60: 085728245782 | AF60: indah.pratama@dumibumi.co.id | AG60: Bekasi, Indonesia
A61: 201843435 | B61: Lina Wijaya | C61: 8391828523321861 | D61: 8468076419278285 | E61: Palembang | F61: 36034 | G61: Female | H61: Single | I61: =MIN(COUNTIFS('Data Family'!A:A,A61,'Data Family'!F:F,"Child")+COUNTIFS('Data Family'!A:A,A61,'Data Family'!F:F,"<>Child",'Data Family'!J:J,"Housewife")+COUNTIFS('Data Family'!A:A,A61,'Data Family'!F:F,"<>Child",'Data Family'!J:J,"Unemployment"),3) -> 0 | J61: Islam | K61: O | L61: 44531 | M61: 46388 | O61: =IF(AND(M61<>"", M61<=TODAY(), N61=""), "End of Contract", "") | P61: =IF(OR(N61<>"", AND(M61<>"",M61<=TODAY())),"Non-Active","Active") -> Active | Q61: =IF(M61="","PKWTT",IF(DATEDIF(L61,M61,"M")>63,"PKWTT",IF(DATEDIF(L61,M61,"M")>60,"PKWT",IF(DATEDIF(L61,M61,"M")>36,"PKWT",IF(DATEDIF(L61,M61,"M")>12, "PKWT","PKWT"))))) -> PKWT | R61: Bachelor's Degree (S1) | S61: Economics | T61: Commercial & Marketing | U61: Marketing | V61: Officer / Executive | W61: Marketing Officer | X61: =_xlfn.XLOOKUP(V61,Reference!$O:$O,Reference!$N:$N,"Tidak Ketemu") -> G10 | Y61: =IF(AND(G61="Female",H61="Married"),"TK/0",IF(H61="Married","K/"&I61,"TK/"&I61)) -> TK/0 | Z61: 882424235147210 | AA61: 89641963835 | AB61: 4179379549358 | AC61: BANK BCA | AD61: 2725223356 | AE61: 087699227655 | AF61: lina.wijaya@dumibumi.co.id | AG61: Bogor, Indonesia
A62: 201642563 | B62: Dwi Nugroho | C62: 7340237776193665 | D62: 9143720146892514 | E62: Palembang | F62: 36877 | G62: Male | H62: Single | I62: =MIN(COUNTIFS('Data Family'!A:A,A62,'Data Family'!F:F,"Child")+COUNTIFS('Data Family'!A:A,A62,'Data Family'!F:F,"<>Child",'Data Family'!J:J,"Housewife")+COUNTIFS('Data Family'!A:A,A62,'Data Family'!F:F,"<>Child",'Data Family'!J:J,"Unemployment"),3) -> 0 | J62: Islam | K62: A | L62: 45850 | M62: 46580 | O62: =IF(AND(M62<>"", M62<=TODAY(), N62=""), "End of Contract", "") | P62: =IF(OR(N62<>"", AND(M62<>"",M62<=TODAY())),"Non-Active","Active") -> Active | Q62: =IF(M62="","PKWTT",IF(DATEDIF(L62,M62,"M")>63,"PKWTT",IF(DATEDIF(L62,M62,"M")>60,"PKWT",IF(DATEDIF(L62,M62,"M")>36,"PKWT",IF(DATEDIF(L62,M62,"M")>12, "PKWT","PKWT"))))) -> PKWT | R62: Bachelor's Degree (S1) | S62: Economics | T62: Commercial & Marketing | U62: Marketing | V62: Staff | W62: Marketing Staff | X62: =_xlfn.XLOOKUP(V62,Reference!$O:$O,Reference!$N:$N,"Tidak Ketemu") -> G11 | Y62: =IF(AND(G62="Female",H62="Married"),"TK/0",IF(H62="Married","K/"&I62,"TK/"&I62)) -> TK/0 | Z62: 358141962209613 | AA62: 06889378287 | AB62: 7922521037898 | AC62: BANK BCA | AD62: 3424772402 | AE62: 089055181705 | AF62: siti.nugroho@dumibumi.co.id | AG62: Bekasi, Indonesia
A63: 201642610 | B63: Lina Kurniawan | C63: 7184140215954258 | D63: 7744113089319337 | E63: Cianjur | F63: 36424 | G63: Female | H63: Single | I63: =MIN(COUNTIFS('Data Family'!A:A,A63,'Data Family'!F:F,"Child")+COUNTIFS('Data Family'!A:A,A63,'Data Family'!F:F,"<>Child",'Data Family'!J:J,"Housewife")+COUNTIFS('Data Family'!A:A,A63,'Data Family'!F:F,"<>Child",'Data Family'!J:J,"Unemployment"),3) -> 0 | J63: Islam | K63: AB | L63: 46081 | M63: 47177 | O63: =IF(AND(M63<>"", M63<=TODAY(), N63=""), "End of Contract", "") | P63: =IF(OR(N63<>"", AND(M63<>"",M63<=TODAY())),"Non-Active","Active") -> Active | Q63: =IF(M63="","PKWTT",IF(DATEDIF(L63,M63,"M")>63,"PKWTT",IF(DATEDIF(L63,M63,"M")>60,"PKWT",IF(DATEDIF(L63,M63,"M")>36,"PKWT",IF(DATEDIF(L63,M63,"M")>12, "PKWT","PKWT"))))) -> PKWT | R63: Bachelor's Degree (S1) | S63: Economics | T63: Commercial & Marketing | U63: Marketing | V63: Staff | W63: Marketing Staff | X63: =_xlfn.XLOOKUP(V63,Reference!$O:$O,Reference!$N:$N,"Tidak Ketemu") -> G11 | Y63: =IF(AND(G63="Female",H63="Married"),"TK/0",IF(H63="Married","K/"&I63,"TK/"&I63)) -> TK/0 | Z63: 454842782078015 | AA63: 62363385285 | AB63: 4954107409212 | AC63: BANK BCA | AD63: 7620560378 | AE63: 082858265264 | AF63: lina.kurniawan@dumibumi.co.id | AG63: Tangerang, Indonesia
A64: 201742737 | B64: Agung Kurniawan | C64: 4917954340013273 | D64: 5982989810431084 | E64: Balikpapan | F64: 36514 | G64: Male | H64: Single | I64: =MIN(COUNTIFS('Data Family'!A:A,A64,'Data Family'!F:F,"Child")+COUNTIFS('Data Family'!A:A,A64,'Data Family'!F:F,"<>Child",'Data Family'!J:J,"Housewife")+COUNTIFS('Data Family'!A:A,A64,'Data Family'!F:F,"<>Child",'Data Family'!J:J,"Unemployment"),3) -> 0 | J64: Islam | K64: A | L64: 46024 | M64: 47120 | O64: =IF(AND(M64<>"", M64<=TODAY(), N64=""), "End of Contract", "") | P64: =IF(OR(N64<>"", AND(M64<>"",M64<=TODAY())),"Non-Active","Active") -> Active | Q64: =IF(M64="","PKWTT",IF(DATEDIF(L64,M64,"M")>63,"PKWTT",IF(DATEDIF(L64,M64,"M")>60,"PKWT",IF(DATEDIF(L64,M64,"M")>36,"PKWT",IF(DATEDIF(L64,M64,"M")>12, "PKWT","PKWT"))))) -> PKWT | R64: Bachelor's Degree (S1) | S64: Economics | T64: Commercial & Marketing | U64: Marketing | V64: Staff | W64: Marketing Staff | X64: =_xlfn.XLOOKUP(V64,Reference!$O:$O,Reference!$N:$N,"Tidak Ketemu") -> G11 | Y64: =IF(AND(G64="Female",H64="Married"),"TK/0",IF(H64="Married","K/"&I64,"TK/"&I64)) -> TK/0 | Z64: 858128981900922 | AA64: 58264541850 | AB64: 2462010834925 | AC64: BANK BCA | AD64: 0531830268 | AE64: 089078566739 | AF64: aulia.kurniawan@dumibumi.co.id | AG64: Subang, Indonesia
A65: 201943726 | B65: Putri Kusuma | C65: 8334022448732764 | D65: 9510033473239496 | E65: Bogor | F65: 39988 | G65: Female | H65: Single | I65: =MIN(COUNTIFS('Data Family'!A:A,A65,'Data Family'!F:F,"Child")+COUNTIFS('Data Family'!A:A,A65,'Data Family'!F:F,"<>Child",'Data Family'!J:J,"Housewife")+COUNTIFS('Data Family'!A:A,A65,'Data Family'!F:F,"<>Child",'Data Family'!J:J,"Unemployment"),3) -> 0 | J65: Islam | K65: A | L65: 45918 | M65: 46283 | O65: =IF(AND(M65<>"", M65<=TODAY(), N65=""), "End of Contract", "") | P65: =IF(OR(N65<>"", AND(M65<>"",M65<=TODAY())),"Non-Active","Active") -> Active | Q65: =IF(M65="","PKWTT",IF(DATEDIF(L65,M65,"M")>63,"PKWTT",IF(DATEDIF(L65,M65,"M")>60,"PKWT",IF(DATEDIF(L65,M65,"M")>36,"PKWT",IF(DATEDIF(L65,M65,"M")>12, "PKWT","PKWT"))))) -> PKWT | R65: Vocational High School | S65: Marketing | T65: Commercial & Marketing | U65: Marketing | V65: Internship | W65: Data Entry Intern | X65: =_xlfn.XLOOKUP(V65,Reference!$O:$O,Reference!$N:$N,"Tidak Ketemu") -> G14 | Y65: =IF(AND(G65="Female",H65="Married"),"TK/0",IF(H65="Married","K/"&I65,"TK/"&I65)) -> TK/0 | Z65: 516408619761215 | AA65: 55514854387 | AB65: 6089088651935 | AC65: BANK BNI | AD65: 8214244657 | AE65: 083298962048 | AF65: putri.kusuma@dumibumi.co.id | AG65: Tangerang, Indonesia
A66: 202044061 | B66: Lina Permata | C66: 5108388085833704 | D66: 7730066736813181 | E66: Malang | F66: 28770 | G66: Female | H66: Married | I66: =MIN(COUNTIFS('Data Family'!A:A,A66,'Data Family'!F:F,"Child")+COUNTIFS('Data Family'!A:A,A66,'Data Family'!F:F,"<>Child",'Data Family'!J:J,"Housewife")+COUNTIFS('Data Family'!A:A,A66,'Data Family'!F:F,"<>Child",'Data Family'!J:J,"Unemployment"),3) -> 0 | J66: Catholicism | K66: B | L66: 40408 | O66: =IF(AND(M66<>"", M66<=TODAY(), N66=""), "End of Contract", "") | P66: =IF(OR(N66<>"", AND(M66<>"",M66<=TODAY())),"Non-Active","Active") -> Active | Q66: =IF(M66="","PKWTT",IF(DATEDIF(L66,M66,"M")>63,"PKWTT",IF(DATEDIF(L66,M66,"M")>60,"PKWT",IF(DATEDIF(L66,M66,"M")>36,"PKWT",IF(DATEDIF(L66,M66,"M")>12, "PKWT","PKWT"))))) -> PKWTT | R66: Doctoral Degree (S3) | S66: Economics | T66: Corporate Governance | U66: Nomination & Remuneration Committee | V66: Manager | W66: Nomination & Remuneration Committee Manager | X66: =_xlfn.XLOOKUP(V66,Reference!$O:$O,Reference!$N:$N,"Tidak Ketemu") -> G06 | Y66: =IF(AND(G66="Female",H66="Married"),"TK/0",IF(H66="Married","K/"&I66,"TK/"&I66)) -> TK/0 | Z66: 319831044725240 | AA66: 47025422194 | AB66: 9856192042673 | AC66: BANK BCA | AD66: 3810524184 | AE66: 085474863189 | AF66: lina.permata@dumibumi.co.id | AG66: Jakarta, Indonesia
A67: 201943744 | B67: Yusuf Saputra | C67: 8670785871787502 | D67: 7422164456473144 | E67: Bandung | F67: 33158 | G67: Male | H67: Married | I67: =MIN(COUNTIFS('Data Family'!A:A,A67,'Data Family'!F:F,"Child")+COUNTIFS('Data Family'!A:A,A67,'Data Family'!F:F,"<>Child",'Data Family'!J:J,"Housewife")+COUNTIFS('Data Family'!A:A,A67,'Data Family'!F:F,"<>Child",'Data Family'!J:J,"Unemployment"),3) -> 1 | J67: Islam | K67: A | L67: 43379 | O67: =IF(AND(M67<>"", M67<=TODAY(), N67=""), "End of Contract", "") | P67: =IF(OR(N67<>"", AND(M67<>"",M67<=TODAY())),"Non-Active","Active") -> Active | Q67: =IF(M67="","PKWTT",IF(DATEDIF(L67,M67,"M")>63,"PKWTT",IF(DATEDIF(L67,M67,"M")>60,"PKWT",IF(DATEDIF(L67,M67,"M")>36,"PKWT",IF(DATEDIF(L67,M67,"M")>12, "PKWT","PKWT"))))) -> PKWTT | R67: Bachelor's Degree (S1) | S67: Communication | T67: Corporate Governance | U67: Nomination & Remuneration Committee | V67: Staff | W67: Nomination & Remuneration Committee Staff | X67: =_xlfn.XLOOKUP(V67,Reference!$O:$O,Reference!$N:$N,"Tidak Ketemu") -> G11 | Y67: =IF(AND(G67="Female",H67="Married"),"TK/0",IF(H67="Married","K/"&I67,"TK/"&I67)) -> K/1 | Z67: 645676916268231 | AA67: 16877286479 | AB67: 8259190357052 | AC67: BANK BCA | AD67: 5974721750 | AE67: 086433384049 | AF67: yusuf.saputra@dumibumi.co.id | AG67: Bandung, Indonesia
A68: 202043848 | B68: Fajar Hidayat | C68: 0417119065232199 | D68: 8329678128751848 | E68: Bandung | F68: 32948 | G68: Male | H68: Married | I68: =MIN(COUNTIFS('Data Family'!A:A,A68,'Data Family'!F:F,"Child")+COUNTIFS('Data Family'!A:A,A68,'Data Family'!F:F,"<>Child",'Data Family'!J:J,"Housewife")+COUNTIFS('Data Family'!A:A,A68,'Data Family'!F:F,"<>Child",'Data Family'!J:J,"Unemployment"),3) -> 2 | J68: Islam | K68: B | L68: 43848 | O68: =IF(AND(M68<>"", M68<=TODAY(), N68=""), "End of Contract", "") | P68: =IF(OR(N68<>"", AND(M68<>"",M68<=TODAY())),"Non-Active","Active") -> Active | Q68: =IF(M68="","PKWTT",IF(DATEDIF(L68,M68,"M")>63,"PKWTT",IF(DATEDIF(L68,M68,"M")>60,"PKWT",IF(DATEDIF(L68,M68,"M")>36,"PKWT",IF(DATEDIF(L68,M68,"M")>12, "PKWT","PKWT"))))) -> PKWTT | R68: Master's Degree (S2) | S68: Statistics | T68: Corporate Governance | U68: Nomination & Remuneration Committee | V68: Staff | W68: Nomination & Remuneration Committee Staff | X68: =_xlfn.XLOOKUP(V68,Reference!$O:$O,Reference!$N:$N,"Tidak Ketemu") -> G11 | Y68: =IF(AND(G68="Female",H68="Married"),"TK/0",IF(H68="Married","K/"&I68,"TK/"&I68)) -> K/2 | Z68: 582185752372391 | AA68: 39719999163 | AB68: 4123079883737 | AC68: BANK BCA | AD68: 4689771098 | AE68: 086325844884 | AF68: fajar.hidayat@dumibumi.co.id | AG68: Subang, Indonesia
A69: 201943561 | B69: Adi Mulyadi | C69: 7105839679661585 | D69: 4072729111931520 | E69: Siduarjo | F69: 32255 | G69: Male | H69: Married | I69: =MIN(COUNTIFS('Data Family'!A:A,A69,'Data Family'!F:F,"Child")+COUNTIFS('Data Family'!A:A,A69,'Data Family'!F:F,"<>Child",'Data Family'!J:J,"Housewife")+COUNTIFS('Data Family'!A:A,A69,'Data Family'!F:F,"<>Child",'Data Family'!J:J,"Unemployment"),3) -> 0 | J69: Islam | K69: A | L69: 43561 | O69: =IF(AND(M69<>"", M69<=TODAY(), N69=""), "End of Contract", "") | P69: =IF(OR(N69<>"", AND(M69<>"",M69<=TODAY())),"Non-Active","Active") -> Active | Q69: =IF(M69="","PKWTT",IF(DATEDIF(L69,M69,"M")>63,"PKWTT",IF(DATEDIF(L69,M69,"M")>60,"PKWT",IF(DATEDIF(L69,M69,"M")>36,"PKWT",IF(DATEDIF(L69,M69,"M")>12, "PKWT","PKWT"))))) -> PKWTT | R69: Bachelor's Degree (S1) | S69: Mechanical Engineering | T69: Supply Chain Management | U69: PPIC | V69: Manager | W69: Demand & Supply Manager | X69: =_xlfn.XLOOKUP(V69,Reference!$O:$O,Reference!$N:$N,"Tidak Ketemu") -> G06 | Y69: =IF(AND(G69="Female",H69="Married"),"TK/0",IF(H69="Married","K/"&I69,"TK/"&I69)) -> K/0 | Z69: 618648607137565 | AA69: 04325330238 | AB69: 4316629142081 | AC69: BANK BCA | AD69: 8147317475 | AE69: 087053243478 | AF69: fajar.kusuma@dumibumi.co.id | AG69: Tangerang, Indonesia
A70: 202043945 | B70: Muhammad Rizal | C70: 1555234553415018 | D70: 3008216976125990 | E70: Jakarta | F70: 35041 | G70: Male | H70: Single | I70: =MIN(COUNTIFS('Data Family'!A:A,A70,'Data Family'!F:F,"Child")+COUNTIFS('Data Family'!A:A,A70,'Data Family'!F:F,"<>Child",'Data Family'!J:J,"Housewife")+COUNTIFS('Data Family'!A:A,A70,'Data Family'!F:F,"<>Child",'Data Family'!J:J,"Unemployment"),3) -> 0 | J70: Islam | K70: A | L70: 45040 | M70: 46867 | O70: =IF(AND(M70<>"", M70<=TODAY(), N70=""), "End of Contract", "") | P70: =IF(OR(N70<>"", AND(M70<>"",M70<=TODAY())),"Non-Active","Active") -> Active | Q70: =IF(M70="","PKWTT",IF(DATEDIF(L70,M70,"M")>63,"PKWTT",IF(DATEDIF(L70,M70,"M")>60,"PKWT",IF(DATEDIF(L70,M70,"M")>36,"PKWT",IF(DATEDIF(L70,M70,"M")>12, "PKWT","PKWT"))))) -> PKWT | R70: Bachelor's Degree (S1) | S70: Mechanical Engineering | T70: Supply Chain Management | U70: PPIC | V70: Supervisor | W70: Production Planning & Control Supervisor | X70: =_xlfn.XLOOKUP(V70,Reference!$O:$O,Reference!$N:$N,"Tidak Ketemu") -> G07 | Y70: =IF(AND(G70="Female",H70="Married"),"TK/0",IF(H70="Married","K/"&I70,"TK/"&I70)) -> TK/0 | Z70: 159191129755048 | AA70: 94525963455 | AB70: 3385465252088 | AC70: BANK BCA | AD70: 9710844454 | AE70: 081697614300 | AF70: yoga.wijaya@dumibumi.co.id | AG70: Tangerang, Indonesia
A71: 202244877 | B71: Guido Nagoya | C71: 2145441655168441 | D71: 9280083721226353 | E71: Jakarta | F71: 35162 | G71: Male | H71: Single | I71: =MIN(COUNTIFS('Data Family'!A:A,A71,'Data Family'!F:F,"Child")+COUNTIFS('Data Family'!A:A,A71,'Data Family'!F:F,"<>Child",'Data Family'!J:J,"Housewife")+COUNTIFS('Data Family'!A:A,A71,'Data Family'!F:F,"<>Child",'Data Family'!J:J,"Unemployment"),3) -> 0 | J71: Catholicism | K71: AB | L71: 44512 | M71: 46399 | O71: =IF(AND(M71<>"", M71<=TODAY(), N71=""), "End of Contract", "") | P71: =IF(OR(N71<>"", AND(M71<>"",M71<=TODAY())),"Non-Active","Active") -> Active | Q71: =IF(M71="","PKWTT",IF(DATEDIF(L71,M71,"M")>63,"PKWTT",IF(DATEDIF(L71,M71,"M")>60,"PKWT",IF(DATEDIF(L71,M71,"M")>36,"PKWT",IF(DATEDIF(L71,M71,"M")>12, "PKWT","PKWT"))))) -> PKWT | R71: Bachelor's Degree (S1) | S71: Mechanical Engineering | T71: Supply Chain Management | U71: PPIC | V71: Supervisor | W71: Production Planning Analyst Supervisor | X71: =_xlfn.XLOOKUP(V71,Reference!$O:$O,Reference!$N:$N,"Tidak Ketemu") -> G07 | Y71: =IF(AND(G71="Female",H71="Married"),"TK/0",IF(H71="Married","K/"&I71,"TK/"&I71)) -> TK/0 | Z71: 437873733515271 | AA71: 44309622558 | AB71: 2074653486822 | AC71: BANK BCA | AD71: 7841425244 | AE71: 083978893157 | AF71: bayu.permata@dumibumi.co.id | AG71: Tangerang, Indonesia
A72: 201843321 | B72: M. Raden Nalindra P. | C72: 5322130789845038 | D72: 6153072484024273 | E72: Yogyakarta | F72: 35500 | G72: Male | H72: Single | I72: =MIN(COUNTIFS('Data Family'!A:A,A72,'Data Family'!F:F,"Child")+COUNTIFS('Data Family'!A:A,A72,'Data Family'!F:F,"<>Child",'Data Family'!J:J,"Housewife")+COUNTIFS('Data Family'!A:A,A72,'Data Family'!F:F,"<>Child",'Data Family'!J:J,"Unemployment"),3) -> 0 | J72: Islam | K72: O | L72: 45513 | M72: 47339 | O72: =IF(AND(M72<>"", M72<=TODAY(), N72=""), "End of Contract", "") | P72: =IF(OR(N72<>"", AND(M72<>"",M72<=TODAY())),"Non-Active","Active") -> Active | Q72: =IF(M72="","PKWTT",IF(DATEDIF(L72,M72,"M")>63,"PKWTT",IF(DATEDIF(L72,M72,"M")>60,"PKWT",IF(DATEDIF(L72,M72,"M")>36,"PKWT",IF(DATEDIF(L72,M72,"M")>12, "PKWT","PKWT"))))) -> PKWT | R72: Bachelor's Degree (S1) | S72: Economics | T72: Supply Chain Management | U72: PPIC | V72: Supervisor | W72: Inventory Control & Planning Supervisor | X72: =_xlfn.XLOOKUP(V72,Reference!$O:$O,Reference!$N:$N,"Tidak Ketemu") -> G07 | Y72: =IF(AND(G72="Female",H72="Married"),"TK/0",IF(H72="Married","K/"&I72,"TK/"&I72)) -> TK/0 | Z72: 500096061929032 | AA72: 70235074213 | AB72: 4747335239025 | AC72: BANK BCA | AD72: 1525322443 | AE72: 080826191332 | AF72: yusuf.kusuma@dumibumi.co.id | AG72: Subang, Indonesia
A73: 202043868 | B73: Dea Karunisa | C73: 9763832461246165 | D73: 2171657844166987 | E73: Surabaya | F73: 34282 | G73: Male | H73: Married | I73: =MIN(COUNTIFS('Data Family'!A:A,A73,'Data Family'!F:F,"Child")+COUNTIFS('Data Family'!A:A,A73,'Data Family'!F:F,"<>Child",'Data Family'!J:J,"Housewife")+COUNTIFS('Data Family'!A:A,A73,'Data Family'!F:F,"<>Child",'Data Family'!J:J,"Unemployment"),3) -> 1 | J73: Islam | K73: B | L73: 43868 | O73: =IF(AND(M73<>"", M73<=TODAY(), N73=""), "End of Contract", "") | P73: =IF(OR(N73<>"", AND(M73<>"",M73<=TODAY())),"Non-Active","Active") -> Active | Q73: =IF(M73="","PKWTT",IF(DATEDIF(L73,M73,"M")>63,"PKWTT",IF(DATEDIF(L73,M73,"M")>60,"PKWT",IF(DATEDIF(L73,M73,"M")>36,"PKWT",IF(DATEDIF(L73,M73,"M")>12, "PKWT","PKWT"))))) -> PKWTT | R73: Bachelor's Degree (S1) | S73: Business Administration | T73: Supply Chain Management | U73: PPIC | V73: Senior Professional / Engineer / Analyst | W73: Production Planning Analyst | X73: =_xlfn.XLOOKUP(V73,Reference!$O:$O,Reference!$N:$N,"Tidak Ketemu") -> G09 | Y73: =IF(AND(G73="Female",H73="Married"),"TK/0",IF(H73="Married","K/"&I73,"TK/"&I73)) -> K/1 | Z73: 933631119813507 | AA73: 55247904234 | AB73: 4440334629087 | AC73: BANK BCA | AD73: 2335337580 | AE73: 086485414789 | AF73: rahmat.sari@dumibumi.co.id | AG73: Bekasi, Indonesia
A74: 201843367 | B74: Mummahad Agil Firmansyah | C74: 4734850393035724 | D74: 7644671232826738 | E74: Surabaya | F74: 36069 | G74: Male | H74: Married | I74: =MIN(COUNTIFS('Data Family'!A:A,A74,'Data Family'!F:F,"Child")+COUNTIFS('Data Family'!A:A,A74,'Data Family'!F:F,"<>Child",'Data Family'!J:J,"Housewife")+COUNTIFS('Data Family'!A:A,A74,'Data Family'!F:F,"<>Child",'Data Family'!J:J,"Unemployment"),3) -> 0 | J74: Islam | K74: A | L74: 43367 | O74: =IF(AND(M74<>"", M74<=TODAY(), N74=""), "End of Contract", "") | P74: =IF(OR(N74<>"", AND(M74<>"",M74<=TODAY())),"Non-Active","Active") -> Active | Q74: =IF(M74="","PKWTT",IF(DATEDIF(L74,M74,"M")>63,"PKWTT",IF(DATEDIF(L74,M74,"M")>60,"PKWT",IF(DATEDIF(L74,M74,"M")>36,"PKWT",IF(DATEDIF(L74,M74,"M")>12, "PKWT","PKWT"))))) -> PKWTT | R74: High School | S74: Automotive Engineering | T74: Supply Chain Management | U74: PPIC | V74: Administrator | W74: Inventory Planning & Control Administrator | X74: =_xlfn.XLOOKUP(V74,Reference!$O:$O,Reference!$N:$N,"Tidak Ketemu") -> G12 | Y74: =IF(AND(G74="Female",H74="Married"),"TK/0",IF(H74="Married","K/"&I74,"TK/"&I74)) -> K/0 | Z74: 909320424652080 | AA74: 40060980300 | AB74: 0316622387515 | AC74: BANK BCA | AD74: 2772134362 | AE74: 088198909466 | AF74: bayu.kurniawan@dumibumi.co.id | AG74: Bogor, Indonesia
A75: 201943543 | B75: Agus Boediono | C75: 8816524994934713 | D75: 5313204453528030 | E75: Malang | F75: 35899 | G75: Male | H75: Single | I75: =MIN(COUNTIFS('Data Family'!A:A,A75,'Data Family'!F:F,"Child")+COUNTIFS('Data Family'!A:A,A75,'Data Family'!F:F,"<>Child",'Data Family'!J:J,"Housewife")+COUNTIFS('Data Family'!A:A,A75,'Data Family'!F:F,"<>Child",'Data Family'!J:J,"Unemployment"),3) -> 0 | J75: Islam | K75: O | L75: 43543 | O75: =IF(AND(M75<>"", M75<=TODAY(), N75=""), "End of Contract", "") | P75: =IF(OR(N75<>"", AND(M75<>"",M75<=TODAY())),"Non-Active","Active") -> Active | Q75: =IF(M75="","PKWTT",IF(DATEDIF(L75,M75,"M")>63,"PKWTT",IF(DATEDIF(L75,M75,"M")>60,"PKWT",IF(DATEDIF(L75,M75,"M")>36,"PKWT",IF(DATEDIF(L75,M75,"M")>12, "PKWT","PKWT"))))) -> PKWTT | R75: High School | S75: Automotive Engineering | T75: Supply Chain Management | U75: PPIC | V75: Administrator | W75: Inventory Planning & Control Administrator | X75: =_xlfn.XLOOKUP(V75,Reference!$O:$O,Reference!$N:$N,"Tidak Ketemu") -> G12 | Y75: =IF(AND(G75="Female",H75="Married"),"TK/0",IF(H75="Married","K/"&I75,"TK/"&I75)) -> TK/0 | Z75: 656667799472908 | AA75: 12739079843 | AB75: 1485264714899 | AC75: BANK BCA | AD75: 0359637095 | AE75: 085479905718 | AF75: budi.hidayat@dumibumi.co.id | AG75: Bekasi, Indonesia
A76: 201642732 | B76: Junaedi | C76: 6573630844724199 | D76: 9798159305146066 | E76: Pasuruan | F76: 35397 | G76: Male | H76: Divorced | I76: =MIN(COUNTIFS('Data Family'!A:A,A76,'Data Family'!F:F,"Child")+COUNTIFS('Data Family'!A:A,A76,'Data Family'!F:F,"<>Child",'Data Family'!J:J,"Housewife")+COUNTIFS('Data Family'!A:A,A76,'Data Family'!F:F,"<>Child",'Data Family'!J:J,"Unemployment"),3) -> 2 | J76: Islam | K76: O | L76: 42732 | O76: =IF(AND(M76<>"", M76<=TODAY(), N76=""), "End of Contract", "") | P76: =IF(OR(N76<>"", AND(M76<>"",M76<=TODAY())),"Non-Active","Active") -> Active | Q76: =IF(M76="","PKWTT",IF(DATEDIF(L76,M76,"M")>63,"PKWTT",IF(DATEDIF(L76,M76,"M")>60,"PKWT",IF(DATEDIF(L76,M76,"M")>36,"PKWT",IF(DATEDIF(L76,M76,"M")>12, "PKWT","PKWT"))))) -> PKWTT | R76: High School | S76: Natural Sciences (IPA) | T76: Supply Chain Management | U76: PPIC | V76: Administrator | W76: Production Planning & Control Administrator | X76: =_xlfn.XLOOKUP(V76,Reference!$O:$O,Reference!$N:$N,"Tidak Ketemu") -> G12 | Y76: =IF(AND(G76="Female",H76="Married"),"TK/0",IF(H76="Married","K/"&I76,"TK/"&I76)) -> TK/2 | Z76: 865818580600605 | AA76: 82755897957 | AB76: 0387239765750 | AC76: BANK BCA | AD76: 7537689079 | AE76: 084234580001 | AF76: andi.santoso@dumibumi.co.id | AG76: Bekasi, Indonesia
A77: 201743003 | B77: Yusuf Nugroho | C77: 0940279985020380 | D77: 6572121056934328 | E77: Malang | F77: 35523 | G77: Male | H77: Single | I77: =MIN(COUNTIFS('Data Family'!A:A,A77,'Data Family'!F:F,"Child")+COUNTIFS('Data Family'!A:A,A77,'Data Family'!F:F,"<>Child",'Data Family'!J:J,"Housewife")+COUNTIFS('Data Family'!A:A,A77,'Data Family'!F:F,"<>Child",'Data Family'!J:J,"Unemployment"),3) -> 0 | J77: Islam | K77: A | L77: 43003 | O77: =IF(AND(M77<>"", M77<=TODAY(), N77=""), "End of Contract", "") | P77: =IF(OR(N77<>"", AND(M77<>"",M77<=TODAY())),"Non-Active","Active") -> Active | Q77: =IF(M77="","PKWTT",IF(DATEDIF(L77,M77,"M")>63,"PKWTT",IF(DATEDIF(L77,M77,"M")>60,"PKWT",IF(DATEDIF(L77,M77,"M")>36,"PKWT",IF(DATEDIF(L77,M77,"M")>12, "PKWT","PKWT"))))) -> PKWTT | R77: Associate Degree (D3) | S77: Statistics | T77: Supply Chain Management | U77: PPIC | V77: Administrator | W77: Production Planning & Control Administrator | X77: =_xlfn.XLOOKUP(V77,Reference!$O:$O,Reference!$N:$N,"Tidak Ketemu") -> G12 | Y77: =IF(AND(G77="Female",H77="Married"),"TK/0",IF(H77="Married","K/"&I77,"TK/"&I77)) -> TK/0 | Z77: 891782551015548 | AA77: 22436156760 | AB77: 4555286765186 | AC77: BANK BCA | AD77: 7868211982 | AE77: 083242325563 | AF77: yusuf.nugroho@dumibumi.co.id | AG77: Bandung, Indonesia
A78: 201843298 | B78: Septiadi | C78: 3189555924673965 | D78: 6628528609450282 | E78: Purwakarta | F78: 35434 | G78: Male | H78: Single | I78: =MIN(COUNTIFS('Data Family'!A:A,A78,'Data Family'!F:F,"Child")+COUNTIFS('Data Family'!A:A,A78,'Data Family'!F:F,"<>Child",'Data Family'!J:J,"Housewife")+COUNTIFS('Data Family'!A:A,A78,'Data Family'!F:F,"<>Child",'Data Family'!J:J,"Unemployment"),3) -> 0 | J78: Islam | K78: B | L78: 43298 | O78: =IF(AND(M78<>"", M78<=TODAY(), N78=""), "End of Contract", "") | P78: =IF(OR(N78<>"", AND(M78<>"",M78<=TODAY())),"Non-Active","Active") -> Active | Q78: =IF(M78="","PKWTT",IF(DATEDIF(L78,M78,"M")>63,"PKWTT",IF(DATEDIF(L78,M78,"M")>60,"PKWT",IF(DATEDIF(L78,M78,"M")>36,"PKWT",IF(DATEDIF(L78,M78,"M")>12, "PKWT","PKWT"))))) -> PKWTT | R78: Bachelor's Degree (S1) | S78: Accounting | T78: Supply Chain Management | U78: PPIC | V78: Administrator | W78: Production Planning & Control Administrator | X78: =_xlfn.XLOOKUP(V78,Reference!$O:$O,Reference!$N:$N,"Tidak Ketemu") -> G12 | Y78: =IF(AND(G78="Female",H78="Married"),"TK/0",IF(H78="Married","K/"&I78,"TK/"&I78)) -> TK/0 | Z78: 979865640170483 | AA78: 45514281920 | AB78: 5273870890114 | AC78: BANK BCA | AD78: 7506713448 | AE78: 088740339410 | AF78: rudi.nugroho@dumibumi.co.id | AG78: Jakarta, Indonesia
A79: 202043978 | B79: Rudi Satria | C79: 7380153756559837 | D79: 4002369205769959 | E79: Purwakarta | F79: 36126 | G79: Male | H79: Married | I79: =MIN(COUNTIFS('Data Family'!A:A,A79,'Data Family'!F:F,"Child")+COUNTIFS('Data Family'!A:A,A79,'Data Family'!F:F,"<>Child",'Data Family'!J:J,"Housewife")+COUNTIFS('Data Family'!A:A,A79,'Data Family'!F:F,"<>Child",'Data Family'!J:J,"Unemployment"),3) -> 0 | J79: Islam | K79: AB | L79: 43978 | O79: =IF(AND(M79<>"", M79<=TODAY(), N79=""), "End of Contract", "") | P79: =IF(OR(N79<>"", AND(M79<>"",M79<=TODAY())),"Non-Active","Active") -> Active | Q79: =IF(M79="","PKWTT",IF(DATEDIF(L79,M79,"M")>63,"PKWTT",IF(DATEDIF(L79,M79,"M")>60,"PKWT",IF(DATEDIF(L79,M79,"M")>36,"PKWT",IF(DATEDIF(L79,M79,"M")>12, "PKWT","PKWT"))))) -> PKWTT | R79: Bachelor's Degree (S1) | S79: Communication | T79: Supply Chain Management | U79: PPIC | V79: Officer / Executive | W79: Inventory Control & Planning Officer | X79: =_xlfn.XLOOKUP(V79,Reference!$O:$O,Reference!$N:$N,"Tidak Ketemu") -> G10 | Y79: =IF(AND(G79="Female",H79="Married"),"TK/0",IF(H79="Married","K/"&I79,"TK/"&I79)) -> K/0 | Z79: 948473842677251 | AA79: 38934561732 | AB79: 0550543195668 | AC79: BANK BCA | AD79: 0470871976 | AE79: 086185133283 | AF79: dedi.utami@dumibumi.co.id | AG79: Tangerang, Indonesia
A80: 201943552 | B80: Muhammad Yusril | C80: 3324687788722404 | D80: 0686378389397759 | E80: Purwakarta | F80: 36078 | G80: Male | H80: Single | I80: =MIN(COUNTIFS('Data Family'!A:A,A80,'Data Family'!F:F,"Child")+COUNTIFS('Data Family'!A:A,A80,'Data Family'!F:F,"<>Child",'Data Family'!J:J,"Housewife")+COUNTIFS('Data Family'!A:A,A80,'Data Family'!F:F,"<>Child",'Data Family'!J:J,"Unemployment"),3) -> 0 | J80: Islam | K80: AB | L80: 43552 | O80: =IF(AND(M80<>"", M80<=TODAY(), N80=""), "End of Contract", "") | P80: =IF(OR(N80<>"", AND(M80<>"",M80<=TODAY())),"Non-Active","Active") -> Active | Q80: =IF(M80="","PKWTT",IF(DATEDIF(L80,M80,"M")>63,"PKWTT",IF(DATEDIF(L80,M80,"M")>60,"PKWT",IF(DATEDIF(L80,M80,"M")>36,"PKWT",IF(DATEDIF(L80,M80,"M")>12, "PKWT","PKWT"))))) -> PKWTT | R80: Bachelor's Degree (S1) | S80: Management | T80: Supply Chain Management | U80: PPIC | V80: Officer / Executive | W80: Inventory Control & Planning Officer | X80: =_xlfn.XLOOKUP(V80,Reference!$O:$O,Reference!$N:$N,"Tidak Ketemu") -> G10 | Y80: =IF(AND(G80="Female",H80="Married"),"TK/0",IF(H80="Married","K/"&I80,"TK/"&I80)) -> TK/0 | Z80: 412105126061386 | AA80: 66795548152 | AB80: 1654030975905 | AC80: BANK BCA | AD80: 0526055057 | AE80: 085391607858 | AF80: andi.santoso@dumibumi.co.id | AG80: Bekasi, Indonesia
A81: 202545716 | B81: Mega Dewi Sartika | C81: 4359687242906699 | D81: 3619598676898943 | E81: Purwakarta | F81: 36265 | G81: Female | H81: Single | I81: =MIN(COUNTIFS('Data Family'!A:A,A81,'Data Family'!F:F,"Child")+COUNTIFS('Data Family'!A:A,A81,'Data Family'!F:F,"<>Child",'Data Family'!J:J,"Housewife")+COUNTIFS('Data Family'!A:A,A81,'Data Family'!F:F,"<>Child",'Data Family'!J:J,"Unemployment"),3) -> 0 | J81: Islam | K81: B | L81: 45716 | M81: 46811 | O81: =IF(AND(M81<>"", M81<=TODAY(), N81=""), "End of Contract", "") | P81: =IF(OR(N81<>"", AND(M81<>"",M81<=TODAY())),"Non-Active","Active") -> Active | Q81: =IF(M81="","PKWTT",IF(DATEDIF(L81,M81,"M")>63,"PKWTT",IF(DATEDIF(L81,M81,"M")>60,"PKWT",IF(DATEDIF(L81,M81,"M")>36,"PKWT",IF(DATEDIF(L81,M81,"M")>12, "PKWT","PKWT"))))) -> PKWT | R81: Bachelor's Degree (S1) | S81: Business Administration | T81: Supply Chain Management | U81: PPIC | V81: Staff | W81: Production Planning Analyst Staff | X81: =_xlfn.XLOOKUP(V81,Reference!$O:$O,Reference!$N:$N,"Tidak Ketemu") -> G11 | Y81: =IF(AND(G81="Female",H81="Married"),"TK/0",IF(H81="Married","K/"&I81,"TK/"&I81)) -> TK/0 | Z81: 628495068893968 | AA81: 83013503701 | AB81: 5938181069038 | AC81: BANK BCA | AD81: 8404936455 | AE81: 081949259478 | AF81: yoga.kurniawan@dumibumi.co.id | AG81: Subang, Indonesia
A82: 202144402 | B82: Agus Wijaya | C82: 5711061632369852 | D82: 9037798456738500 | E82: Pasuruan | F82: 36070 | G82: Male | H82: Single | I82: =MIN(COUNTIFS('Data Family'!A:A,A82,'Data Family'!F:F,"Child")+COUNTIFS('Data Family'!A:A,A82,'Data Family'!F:F,"<>Child",'Data Family'!J:J,"Housewife")+COUNTIFS('Data Family'!A:A,A82,'Data Family'!F:F,"<>Child",'Data Family'!J:J,"Unemployment"),3) -> 0 | J82: Islam | K82: B | L82: 44402 | M82: 46320 | O82: =IF(AND(M82<>"", M82<=TODAY(), N82=""), "End of Contract", "") | P82: =IF(OR(N82<>"", AND(M82<>"",M82<=TODAY())),"Non-Active","Active") -> Active | Q82: =IF(M82="","PKWTT",IF(DATEDIF(L82,M82,"M")>63,"PKWTT",IF(DATEDIF(L82,M82,"M")>60,"PKWT",IF(DATEDIF(L82,M82,"M")>36,"PKWT",IF(DATEDIF(L82,M82,"M")>12, "PKWT","PKWT"))))) -> PKWT | R82: Bachelor's Degree (S1) | S82: Industrial Engineering | T82: Supply Chain Management | U82: PPIC | V82: Officer / Executive | W82: Production Planning & Control Officer | X82: =_xlfn.XLOOKUP(V82,Reference!$O:$O,Reference!$N:$N,"Tidak Ketemu") -> G10 | Y82: =IF(AND(G82="Female",H82="Married"),"TK/0",IF(H82="Married","K/"&I82,"TK/"&I82)) -> TK/0 | Z82: 123893411576489 | AA82: 55176539734 | AB82: 3765016287079 | AC82: BANK BCA | AD82: 9328914021 | AE82: 081585319770 | AF82: agus.wijaya@dumibumi.co.id | AG82: Bogor, Indonesia
A83: 201742740 | B83: Andi Kurniawan | C83: 5247883182896725 | D83: 7520486332933022 | E83: Pontianak | F83: 36108 | G83: Male | H83: Single | I83: =MIN(COUNTIFS('Data Family'!A:A,A83,'Data Family'!F:F,"Child")+COUNTIFS('Data Family'!A:A,A83,'Data Family'!F:F,"<>Child",'Data Family'!J:J,"Housewife")+COUNTIFS('Data Family'!A:A,A83,'Data Family'!F:F,"<>Child",'Data Family'!J:J,"Unemployment"),3) -> 0 | J83: Islam | K83: O | L83: 42740 | O83: =IF(AND(M83<>"", M83<=TODAY(), N83=""), "End of Contract", "") | P83: =IF(OR(N83<>"", AND(M83<>"",M83<=TODAY())),"Non-Active","Active") -> Active | Q83: =IF(M83="","PKWTT",IF(DATEDIF(L83,M83,"M")>63,"PKWTT",IF(DATEDIF(L83,M83,"M")>60,"PKWT",IF(DATEDIF(L83,M83,"M")>36,"PKWT",IF(DATEDIF(L83,M83,"M")>12, "PKWT","PKWT"))))) -> PKWTT | R83: Bachelor's Degree (S1) | S83: Mechanical Engineering | T83: Supply Chain Management | U83: PPIC | V83: Officer / Executive | W83: Production Planning & Control Officer | X83: =_xlfn.XLOOKUP(V83,Reference!$O:$O,Reference!$N:$N,"Tidak Ketemu") -> G10 | Y83: =IF(AND(G83="Female",H83="Married"),"TK/0",IF(H83="Married","K/"&I83,"TK/"&I83)) -> TK/0 | Z83: 029922269024118 | AA83: 53235184673 | AB83: 8247250900831 | AC83: BANK BCA | AD83: 1901890482 | AE83: 082736493864 | AF83: andi.kurniawan@dumibumi.co.id | AG83: Bekasi, Indonesia
A84: 201943527 | B84: Bambang Wijaya | C84: 0548317562548392 | D84: 5245230852064504 | E84: Siduarjo | F84: 26709 | G84: Male | H84: Married | I84: =MIN(COUNTIFS('Data Family'!A:A,A84,'Data Family'!F:F,"Child")+COUNTIFS('Data Family'!A:A,A84,'Data Family'!F:F,"<>Child",'Data Family'!J:J,"Housewife")+COUNTIFS('Data Family'!A:A,A84,'Data Family'!F:F,"<>Child",'Data Family'!J:J,"Unemployment"),3) -> 3 | J84: Islam | K84: B | L84: 36588 | O84: =IF(AND(M84<>"", M84<=TODAY(), N84=""), "End of Contract", "") | P84: =IF(OR(N84<>"", AND(M84<>"",M84<=TODAY())),"Non-Active","Active") -> Active | Q84: =IF(M84="","PKWTT",IF(DATEDIF(L84,M84,"M")>63,"PKWTT",IF(DATEDIF(L84,M84,"M")>60,"PKWT",IF(DATEDIF(L84,M84,"M")>36,"PKWT",IF(DATEDIF(L84,M84,"M")>12, "PKWT","PKWT"))))) -> PKWTT | R84: Doctoral Degree (S3) | S84: Management | T84: Corporate Governance | U84: Board of Commissioners | V84: Commissioner | W84: Commissioner | X84: =_xlfn.XLOOKUP(V84,Reference!$O:$O,Reference!$N:$N,"Tidak Ketemu") -> G03 | Y84: =IF(AND(G84="Female",H84="Married"),"TK/0",IF(H84="Married","K/"&I84,"TK/"&I84)) -> K/3 | Z84: 042522897779760 | AA84: 84324207712 | AB84: 6855408763258 | AC84: BANK BCA | AD84: 6514728684 | AE84: 086134466406 | AF84: bbg.wijaya@dumibumi.co.id | AG84: Subang, Indonesia
A85: 202144393 | B85: Yusuf Saputra | C85: 9724027143268662 | D85: 2496360035248341 | E85: Purwakarta | F85: 32648 | G85: Male | H85: Married | I85: =MIN(COUNTIFS('Data Family'!A:A,A85,'Data Family'!F:F,"Child")+COUNTIFS('Data Family'!A:A,A85,'Data Family'!F:F,"<>Child",'Data Family'!J:J,"Housewife")+COUNTIFS('Data Family'!A:A,A85,'Data Family'!F:F,"<>Child",'Data Family'!J:J,"Unemployment"),3) -> 2 | J85: Islam | K85: A | L85: 44758 | O85: =IF(AND(M85<>"", M85<=TODAY(), N85=""), "End of Contract", "") | P85: =IF(OR(N85<>"", AND(M85<>"",M85<=TODAY())),"Non-Active","Active") -> Active | Q85: =IF(M85="","PKWTT",IF(DATEDIF(L85,M85,"M")>63,"PKWTT",IF(DATEDIF(L85,M85,"M")>60,"PKWT",IF(DATEDIF(L85,M85,"M")>36,"PKWT",IF(DATEDIF(L85,M85,"M")>12, "PKWT","PKWT"))))) -> PKWTT | R85: Vocational High School | S85: Tourism | T85: Manufacturing | U85: Production | V85: Leader | W85: Leader Engineering | X85: =_xlfn.XLOOKUP(V85,Reference!$O:$O,Reference!$N:$N,"Tidak Ketemu") -> G08 | Y85: =IF(AND(G85="Female",H85="Married"),"TK/0",IF(H85="Married","K/"&I85,"TK/"&I85)) -> K/2 | Z85: 465366701555651 | AA85: 74623006286 | AB85: 6750136175908 | AC85: BANK BCA | AD85: 8679287773 | AE85: 086885613346 | AF85: yusuf.saputra@dumibumi.co.id | AG85: Jakarta, Indonesia
A86: 202445543 | B86: Budi Wijaya | C86: 5161798772753918 | D86: 4551002570879752 | E86: Jakarta | F86: 28770 | G86: Male | H86: Divorced | I86: =MIN(COUNTIFS('Data Family'!A:A,A86,'Data Family'!F:F,"Child")+COUNTIFS('Data Family'!A:A,A86,'Data Family'!F:F,"<>Child",'Data Family'!J:J,"Housewife")+COUNTIFS('Data Family'!A:A,A86,'Data Family'!F:F,"<>Child",'Data Family'!J:J,"Unemployment"),3) -> 1 | J86: Catholicism | K86: B | L86: 43716 | O86: =IF(AND(M86<>"", M86<=TODAY(), N86=""), "End of Contract", "") | P86: =IF(OR(N86<>"", AND(M86<>"",M86<=TODAY())),"Non-Active","Active") -> Active | Q86: =IF(M86="","PKWTT",IF(DATEDIF(L86,M86,"M")>63,"PKWTT",IF(DATEDIF(L86,M86,"M")>60,"PKWT",IF(DATEDIF(L86,M86,"M")>36,"PKWT",IF(DATEDIF(L86,M86,"M")>12, "PKWT","PKWT"))))) -> PKWTT | R86: Master's Degree (S2) | S86: Mechanical Engineering | T86: Manufacturing | U86: Production | V86: Manager | W86: Production Manager | X86: =_xlfn.XLOOKUP(V86,Reference!$O:$O,Reference!$N:$N,"Tidak Ketemu") -> G06 | Y86: =IF(AND(G86="Female",H86="Married"),"TK/0",IF(H86="Married","K/"&I86,"TK/"&I86)) -> TK/1 | Z86: 509150645203487 | AA86: 84223991152 | AB86: 3312690053797 | AC86: BANK BCA | AD86: 4309145952 | AE86: 086095130435 | AF86: budi.wijaya@dumibumi.co.id | AG86: Tangerang, Indonesia
A87: 202043929 | B87: Aulia Permata | C87: 0356355813953671 | D87: 3260076619459365 | E87: Jakarta | F87: 35211 | G87: Female | H87: Married | I87: =MIN(COUNTIFS('Data Family'!A:A,A87,'Data Family'!F:F,"Child")+COUNTIFS('Data Family'!A:A,A87,'Data Family'!F:F,"<>Child",'Data Family'!J:J,"Housewife")+COUNTIFS('Data Family'!A:A,A87,'Data Family'!F:F,"<>Child",'Data Family'!J:J,"Unemployment"),3) -> 0 | J87: Islam | K87: B | L87: 43929 | O87: =IF(AND(M87<>"", M87<=TODAY(), N87=""), "End of Contract", "") | P87: =IF(OR(N87<>"", AND(M87<>"",M87<=TODAY())),"Non-Active","Active") -> Active | Q87: =IF(M87="","PKWTT",IF(DATEDIF(L87,M87,"M")>63,"PKWTT",IF(DATEDIF(L87,M87,"M")>60,"PKWT",IF(DATEDIF(L87,M87,"M")>36,"PKWT",IF(DATEDIF(L87,M87,"M")>12, "PKWT","PKWT"))))) -> PKWTT | R87: High School | S87: Natural Sciences (IPA) | T87: Manufacturing | U87: Production | V87: Leader | W87: Leader Engineering | X87: =_xlfn.XLOOKUP(V87,Reference!$O:$O,Reference!$N:$N,"Tidak Ketemu") -> G08 | Y87: =IF(AND(G87="Female",H87="Married"),"TK/0",IF(H87="Married","K/"&I87,"TK/"&I87)) -> TK/0 | Z87: 477091490328175 | AA87: 91626574876 | AB87: 8770792467891 | AC87: BANK BCA | AD87: 0742246294 | AE87: 085725030853 | AF87: aulia.permata@dumibumi.co.id | AG87: Jakarta, Indonesia
A88: 201642575 | B88: Indah Permata | C88: 5343472913697847 | D88: 0493552594574343 | E88: Jakarta | F88: 34984 | G88: Female | H88: Married | I88: =MIN(COUNTIFS('Data Family'!A:A,A88,'Data Family'!F:F,"Child")+COUNTIFS('Data Family'!A:A,A88,'Data Family'!F:F,"<>Child",'Data Family'!J:J,"Housewife")+COUNTIFS('Data Family'!A:A,A88,'Data Family'!F:F,"<>Child",'Data Family'!J:J,"Unemployment"),3) -> 1 | J88: Islam | K88: O | L88: 42575 | O88: =IF(AND(M88<>"", M88<=TODAY(), N88=""), "End of Contract", "") | P88: =IF(OR(N88<>"", AND(M88<>"",M88<=TODAY())),"Non-Active","Active") -> Active | Q88: =IF(M88="","PKWTT",IF(DATEDIF(L88,M88,"M")>63,"PKWTT",IF(DATEDIF(L88,M88,"M")>60,"PKWT",IF(DATEDIF(L88,M88,"M")>36,"PKWT",IF(DATEDIF(L88,M88,"M")>12, "PKWT","PKWT"))))) -> PKWTT | R88: Associate Degree (D3) | S88: Statistics | T88: Manufacturing | U88: Production | V88: Leader | W88: Leader Engineering | X88: =_xlfn.XLOOKUP(V88,Reference!$O:$O,Reference!$N:$N,"Tidak Ketemu") -> G08 | Y88: =IF(AND(G88="Female",H88="Married"),"TK/0",IF(H88="Married","K/"&I88,"TK/"&I88)) -> TK/0 | Z88: 480866049456598 | AA88: 64060691791 | AB88: 2836529902733 | AC88: BANK BCA | AD88: 0876516337 | AE88: 089310118303 | AF88: indah.permata@dumibumi.co.id | AG88: Bekasi, Indonesia
A89: 201742831 | B89: Dedi Hidayat | C89: 9237184536117948 | D89: 8616949168909269 | E89: Karawang | F89: 33980 | G89: Male | H89: Married | I89: =MIN(COUNTIFS('Data Family'!A:A,A89,'Data Family'!F:F,"Child")+COUNTIFS('Data Family'!A:A,A89,'Data Family'!F:F,"<>Child",'Data Family'!J:J,"Housewife")+COUNTIFS('Data Family'!A:A,A89,'Data Family'!F:F,"<>Child",'Data Family'!J:J,"Unemployment"),3) -> 3 | J89: Islam | K89: A | L89: 42831 | O89: =IF(AND(M89<>"", M89<=TODAY(), N89=""), "End of Contract", "") | P89: =IF(OR(N89<>"", AND(M89<>"",M89<=TODAY())),"Non-Active","Active") -> Active | Q89: =IF(M89="","PKWTT",IF(DATEDIF(L89,M89,"M")>63,"PKWTT",IF(DATEDIF(L89,M89,"M")>60,"PKWT",IF(DATEDIF(L89,M89,"M")>36,"PKWT",IF(DATEDIF(L89,M89,"M")>12, "PKWT","PKWT"))))) -> PKWTT | R89: Bachelor's Degree (S1) | S89: Communication | T89: Manufacturing | U89: Production | V89: Leader | W89: Leader Engineering | X89: =_xlfn.XLOOKUP(V89,Reference!$O:$O,Reference!$N:$N,"Tidak Ketemu") -> G08 | Y89: =IF(AND(G89="Female",H89="Married"),"TK/0",IF(H89="Married","K/"&I89,"TK/"&I89)) -> K/3 | Z89: 396420169754313 | AA89: 44689751350 | AB89: 2145516190184 | AC89: BANK BCA | AD89: 3825311340 | AE89: 088469960329 | AF89: dedi.hidayat@dumibumi.co.id | AG89: Subang, Indonesia
A90: 201943575 | B90: Yoga Kusuma | C90: 0865000522658401 | D90: 5339784715990609 | E90: Siduarjo | F90: 33867 | G90: Male | H90: Married | I90: =MIN(COUNTIFS('Data Family'!A:A,A90,'Data Family'!F:F,"Child")+COUNTIFS('Data Family'!A:A,A90,'Data Family'!F:F,"<>Child",'Data Family'!J:J,"Housewife")+COUNTIFS('Data Family'!A:A,A90,'Data Family'!F:F,"<>Child",'Data Family'!J:J,"Unemployment"),3) -> 2 | J90: Islam | K90: A | L90: 43575 | O90: =IF(AND(M90<>"", M90<=TODAY(), N90=""), "End of Contract", "") | P90: =IF(OR(N90<>"", AND(M90<>"",M90<=TODAY())),"Non-Active","Active") -> Active | Q90: =IF(M90="","PKWTT",IF(DATEDIF(L90,M90,"M")>63,"PKWTT",IF(DATEDIF(L90,M90,"M")>60,"PKWT",IF(DATEDIF(L90,M90,"M")>36,"PKWT",IF(DATEDIF(L90,M90,"M")>12, "PKWT","PKWT"))))) -> PKWTT | R90: Bachelor's Degree (S1) | S90: Law | T90: Manufacturing | U90: Production | V90: Leader | W90: Leader Engineering | X90: =_xlfn.XLOOKUP(V90,Reference!$O:$O,Reference!$N:$N,"Tidak Ketemu") -> G08 | Y90: =IF(AND(G90="Female",H90="Married"),"TK/0",IF(H90="Married","K/"&I90,"TK/"&I90)) -> K/2 | Z90: 451424592928880 | AA90: 95824318614 | AB90: 4668981162955 | AC90: BANK BCA | AD90: 4793555014 | AE90: 080706802656 | AF90: yoga.kusuma@dumibumi.co.id | AG90: Bogor, Indonesia
A91: 202646180 | B91: Andi Hidayat | C91: 9517875367326303 | D91: 8174727723024306 | E91: Samarinda | F91: 30841 | G91: Male | H91: Divorced | I91: =MIN(COUNTIFS('Data Family'!A:A,A91,'Data Family'!F:F,"Child")+COUNTIFS('Data Family'!A:A,A91,'Data Family'!F:F,"<>Child",'Data Family'!J:J,"Housewife")+COUNTIFS('Data Family'!A:A,A91,'Data Family'!F:F,"<>Child",'Data Family'!J:J,"Unemployment"),3) -> 2 | J91: Islam | K91: A | L91: 42528 | O91: =IF(AND(M91<>"", M91<=TODAY(), N91=""), "End of Contract", "") | P91: =IF(OR(N91<>"", AND(M91<>"",M91<=TODAY())),"Non-Active","Active") -> Active | Q91: =IF(M91="","PKWTT",IF(DATEDIF(L91,M91,"M")>63,"PKWTT",IF(DATEDIF(L91,M91,"M")>60,"PKWT",IF(DATEDIF(L91,M91,"M")>36,"PKWT",IF(DATEDIF(L91,M91,"M")>12, "PKWT","PKWT"))))) -> PKWTT | R91: Vocational High School | S91: Tourism | T91: Manufacturing | U91: Production | V91: Leader | W91: Leader Line Production | X91: =_xlfn.XLOOKUP(V91,Reference!$O:$O,Reference!$N:$N,"Tidak Ketemu") -> G08 | Y91: =IF(AND(G91="Female",H91="Married"),"TK/0",IF(H91="Married","K/"&I91,"TK/"&I91)) -> TK/2 | Z91: 128349650931857 | AA91: 35568622013 | AB91: 9620653791270 | AC91: BANK BCA | AD91: 5633687561 | AE91: 080598971169 | AF91: andi.hidayat@dumibumi.co.id | AG91: Bogor, Indonesia
A92: 202344981 | B92: Rizky Nugroho | C92: 3075390588565120 | D92: 2385996078970310 | E92: Jakarta | F92: 31452 | G92: Male | H92: Single | I92: =MIN(COUNTIFS('Data Family'!A:A,A92,'Data Family'!F:F,"Child")+COUNTIFS('Data Family'!A:A,A92,'Data Family'!F:F,"<>Child",'Data Family'!J:J,"Housewife")+COUNTIFS('Data Family'!A:A,A92,'Data Family'!F:F,"<>Child",'Data Family'!J:J,"Unemployment"),3) -> 0 | J92: Islam | K92: AB | L92: 42424 | O92: =IF(AND(M92<>"", M92<=TODAY(), N92=""), "End of Contract", "") | P92: =IF(OR(N92<>"", AND(M92<>"",M92<=TODAY())),"Non-Active","Active") -> Active | Q92: =IF(M92="","PKWTT",IF(DATEDIF(L92,M92,"M")>63,"PKWTT",IF(DATEDIF(L92,M92,"M")>60,"PKWT",IF(DATEDIF(L92,M92,"M")>36,"PKWT",IF(DATEDIF(L92,M92,"M")>12, "PKWT","PKWT"))))) -> PKWTT | R92: Vocational High School | S92: Electrical Engineering | T92: Manufacturing | U92: Production | V92: Leader | W92: Leader Line Production | X92: =_xlfn.XLOOKUP(V92,Reference!$O:$O,Reference!$N:$N,"Tidak Ketemu") -> G08 | Y92: =IF(AND(G92="Female",H92="Married"),"TK/0",IF(H92="Married","K/"&I92,"TK/"&I92)) -> TK/0 | Z92: 457138765299420 | AA92: 29131739991 | AB92: 1510407008885 | AC92: BANK BCA | AD92: 0665090539 | AE92: 085817996898 | AF92: rizky.nugroho@dumibumi.co.id | AG92: Bandung, Indonesia
A93: 202044108 | B93: Agus Kurniawan | C93: 8546749958742581 | D93: 9364628743906587 | E93: Banjarbaru | F93: 32651 | G93: Male | H93: Single | I93: =MIN(COUNTIFS('Data Family'!A:A,A93,'Data Family'!F:F,"Child")+COUNTIFS('Data Family'!A:A,A93,'Data Family'!F:F,"<>Child",'Data Family'!J:J,"Housewife")+COUNTIFS('Data Family'!A:A,A93,'Data Family'!F:F,"<>Child",'Data Family'!J:J,"Unemployment"),3) -> 0 | J93: Islam | K93: AB | L93: 43012 | O93: =IF(AND(M93<>"", M93<=TODAY(), N93=""), "End of Contract", "") | P93: =IF(OR(N93<>"", AND(M93<>"",M93<=TODAY())),"Non-Active","Active") -> Active | Q93: =IF(M93="","PKWTT",IF(DATEDIF(L93,M93,"M")>63,"PKWTT",IF(DATEDIF(L93,M93,"M")>60,"PKWT",IF(DATEDIF(L93,M93,"M")>36,"PKWT",IF(DATEDIF(L93,M93,"M")>12, "PKWT","PKWT"))))) -> PKWTT | R93: Bachelor's Degree (S1) | S93: Mechanical Engineering | T93: Manufacturing | U93: Production | V93: Supervisor | W93: Production Supervisor | X93: =_xlfn.XLOOKUP(V93,Reference!$O:$O,Reference!$N:$N,"Tidak Ketemu") -> G07 | Y93: =IF(AND(G93="Female",H93="Married"),"TK/0",IF(H93="Married","K/"&I93,"TK/"&I93)) -> TK/0 | Z93: 163299936849652 | AA93: 34941316887 | AB93: 1455544387012 | AC93: BANK BCA | AD93: 8477010591 | AE93: 086370981872 | AF93: agus.kurniawan@dumibumi.co.id | AG93: Depok, Indonesia
A94: 201542229 | B94: Budi Saputra | C94: 2173159165965906 | D94: 2072594701169996 | E94: Jakarta | F94: 31871 | G94: Male | H94: Married | I94: =MIN(COUNTIFS('Data Family'!A:A,A94,'Data Family'!F:F,"Child")+COUNTIFS('Data Family'!A:A,A94,'Data Family'!F:F,"<>Child",'Data Family'!J:J,"Housewife")+COUNTIFS('Data Family'!A:A,A94,'Data Family'!F:F,"<>Child",'Data Family'!J:J,"Unemployment"),3) -> 2 | J94: Islam | K94: A | L94: 42229 | O94: =IF(AND(M94<>"", M94<=TODAY(), N94=""), "End of Contract", "") | P94: =IF(OR(N94<>"", AND(M94<>"",M94<=TODAY())),"Non-Active","Active") -> Active | Q94: =IF(M94="","PKWTT",IF(DATEDIF(L94,M94,"M")>63,"PKWTT",IF(DATEDIF(L94,M94,"M")>60,"PKWT",IF(DATEDIF(L94,M94,"M")>36,"PKWT",IF(DATEDIF(L94,M94,"M")>12, "PKWT","PKWT"))))) -> PKWTT | R94: Vocational High School | S94: Electrical Engineering | T94: Manufacturing | U94: Production | V94: Leader | W94: Leader Line Production | X94: =_xlfn.XLOOKUP(V94,Reference!$O:$O,Reference!$N:$N,"Tidak Ketemu") -> G08 | Y94: =IF(AND(G94="Female",H94="Married"),"TK/0",IF(H94="Married","K/"&I94,"TK/"&I94)) -> K/2 | Z94: 604549423505147 | AA94: 02521550883 | AB94: 0682077902795 | AC94: BANK BCA | AD94: 0356257318 | AE94: 087444280126 | AF94: budi.saputra@dumibumi.co.id | AG94: Tangerang, Indonesia
A95: 201742748 | B95: Budi Kurniawan | C95: 9011539627779671 | D95: 0940401704809732 | E95: Jakarta | F95: 32806 | G95: Male | H95: Divorced | I95: =MIN(COUNTIFS('Data Family'!A:A,A95,'Data Family'!F:F,"Child")+COUNTIFS('Data Family'!A:A,A95,'Data Family'!F:F,"<>Child",'Data Family'!J:J,"Housewife")+COUNTIFS('Data Family'!A:A,A95,'Data Family'!F:F,"<>Child",'Data Family'!J:J,"Unemployment"),3) -> 2 | J95: Islam | K95: O | L95: 42748 | O95: =IF(AND(M95<>"", M95<=TODAY(), N95=""), "End of Contract", "") | P95: =IF(OR(N95<>"", AND(M95<>"",M95<=TODAY())),"Non-Active","Active") -> Active | Q95: =IF(M95="","PKWTT",IF(DATEDIF(L95,M95,"M")>63,"PKWTT",IF(DATEDIF(L95,M95,"M")>60,"PKWT",IF(DATEDIF(L95,M95,"M")>36,"PKWT",IF(DATEDIF(L95,M95,"M")>12, "PKWT","PKWT"))))) -> PKWTT | R95: Vocational High School | S95: Automotive Engineering | T95: Manufacturing | U95: Production | V95: Leader | W95: Leader Line Production | X95: =_xlfn.XLOOKUP(V95,Reference!$O:$O,Reference!$N:$N,"Tidak Ketemu") -> G08 | Y95: =IF(AND(G95="Female",H95="Married"),"TK/0",IF(H95="Married","K/"&I95,"TK/"&I95)) -> TK/2 | Z95: 182667933020925 | AA95: 99343729220 | AB95: 2046623316077 | AC95: BANK BCA | AD95: 8783812269 | AE95: 088147142072 | AF95: budi.kurniawan@dumibumi.co.id | AG95: Bandung, Indonesia
A96: 202445365 | B96: Budi Ramadhan | C96: 7044680841843920 | D96: 6529105927182681 | E96: Jakarta | F96: 32002 | G96: Male | H96: Single | I96: =MIN(COUNTIFS('Data Family'!A:A,A96,'Data Family'!F:F,"Child")+COUNTIFS('Data Family'!A:A,A96,'Data Family'!F:F,"<>Child",'Data Family'!J:J,"Housewife")+COUNTIFS('Data Family'!A:A,A96,'Data Family'!F:F,"<>Child",'Data Family'!J:J,"Unemployment"),3) -> 0 | J96: Islam | K96: B | L96: 41712 | O96: =IF(AND(M96<>"", M96<=TODAY(), N96=""), "End of Contract", "") | P96: =IF(OR(N96<>"", AND(M96<>"",M96<=TODAY())),"Non-Active","Active") -> Active | Q96: =IF(M96="","PKWTT",IF(DATEDIF(L96,M96,"M")>63,"PKWTT",IF(DATEDIF(L96,M96,"M")>60,"PKWT",IF(DATEDIF(L96,M96,"M")>36,"PKWT",IF(DATEDIF(L96,M96,"M")>12, "PKWT","PKWT"))))) -> PKWTT | R96: Vocational High School | S96: Electrical Engineering | T96: Manufacturing | U96: Production | V96: Leader | W96: Leader Line Production | X96: =_xlfn.XLOOKUP(V96,Reference!$O:$O,Reference!$N:$N,"Tidak Ketemu") -> G08 | Y96: =IF(AND(G96="Female",H96="Married"),"TK/0",IF(H96="Married","K/"&I96,"TK/"&I96)) -> TK/0 | Z96: 310603730546415 | AA96: 31185554810 | AB96: 9058389079562 | AC96: BANK BCA | AD96: 9922545773 | AE96: 082092848519 | AF96: budi.ramadhan@dumibumi.co.id | AG96: Bekasi, Indonesia
A97: 201742739 | B97: Budi Hidayat | C97: 9623697476481586 | D97: 1082058755579316 | E97: Kutai Kartanegara | F97: 32313 | G97: Male | H97: Single | I97: =MIN(COUNTIFS('Data Family'!A:A,A97,'Data Family'!F:F,"Child")+COUNTIFS('Data Family'!A:A,A97,'Data Family'!F:F,"<>Child",'Data Family'!J:J,"Housewife")+COUNTIFS('Data Family'!A:A,A97,'Data Family'!F:F,"<>Child",'Data Family'!J:J,"Unemployment"),3) -> 0 | J97: Islam | K97: B | L97: 42739 | O97: =IF(AND(M97<>"", M97<=TODAY(), N97=""), "End of Contract", "") | P97: =IF(OR(N97<>"", AND(M97<>"",M97<=TODAY())),"Non-Active","Active") -> Active | Q97: =IF(M97="","PKWTT",IF(DATEDIF(L97,M97,"M")>63,"PKWTT",IF(DATEDIF(L97,M97,"M")>60,"PKWT",IF(DATEDIF(L97,M97,"M")>36,"PKWT",IF(DATEDIF(L97,M97,"M")>12, "PKWT","PKWT"))))) -> PKWTT | R97: Vocational High School | S97: Metal Engineering | T97: Manufacturing | U97: Production | V97: Leader | W97: Leader Line Production | X97: =_xlfn.XLOOKUP(V97,Reference!$O:$O,Reference!$N:$N,"Tidak Ketemu") -> G08 | Y97: =IF(AND(G97="Female",H97="Married"),"TK/0",IF(H97="Married","K/"&I97,"TK/"&I97)) -> TK/0 | Z97: 072067113943937 | AA97: 47229126832 | AB97: 4535345077903 | AC97: BANK BCA | AD97: 3683094921 | AE97: 086088448222 | AF97: budi.hidayat@dumibumi.co.id | AG97: Tangerang, Indonesia
... A100: 201742809 | B100: Budi Pangestu | C100: 9784476820785676 | D100: 0292193703478534 | E100: Cikampek | F100: 32680 | G100: Male | H100: Single | I100: =MIN(COUNTIFS('Data Family'!A:A,A100,'Data Family'!F:F,"Child")+COUNTIFS('Data Family'!A:A,A100,'Data Family'!F:F,"<>Child",'Data Family'!J:J,"Housewife")+COUNTIFS('Data Family'!A:A,A100,'Data Family'!F:F,"<>Child",'Data Family'!J:J,"Unemployment"),3) -> 0 | J100: Islam | K100: O | L100: 42809 | O100: =IF(AND(M100<>"", M100<=TODAY(), N100=""), "End of Contract", "") | P100: =IF(OR(N100<>"", AND(M100<>"",M100<=TODAY())),"Non-Active","Active") -> Active | Q100: =IF(M100="","PKWTT",IF(DATEDIF(L100,M100,"M")>63,"PKWTT",IF(DATEDIF(L100,M100,"M")>60,"PKWT",IF(DATEDIF(L100,M100,"M")>36,"PKWT",IF(DATEDIF(L100,M100,"M")>12, "PKWT","PKWT"))))) -> PKWTT | R100: Vocational High School | S100: Tourism | T100: Manufacturing | U100: Production | V100: Leader | W100: Leader Line Production | X100: =_xlfn.XLOOKUP(V100,Reference!$O:$O,Reference!$N:$N,"Tidak Ketemu") -> G08 | Y100: =IF(AND(G100="Female",H100="Married"),"TK/0",IF(H100="Married","K/"&I100,"TK/"&I100)) -> TK/0 | Z100: 676232395587005 | AA100: 30520742091 | AB100: 9405102500697 | AC100: BANK BCA | AD100: 6224325677 | AE100: 089789865557 | AF100: budi.pangestu@dumibumi.co.id | AG100: Bandung, Indonesia
A101: 202646162 | B101: Dedi Kusuma | C101: 1873476915236849 | D101: 7909983589365354 | E101: Kediri | F101: 38097 | G101: Male | H101: Single | I101: =MIN(COUNTIFS('Data Family'!A:A,A101,'Data Family'!F:F,"Child")+COUNTIFS('Data Family'!A:A,A101,'Data Family'!F:F,"<>Child",'Data Family'!J:J,"Housewife")+COUNTIFS('Data Family'!A:A,A101,'Data Family'!F:F,"<>Child",'Data Family'!J:J,"Unemployment"),3) -> 0 | J101: Islam | K101: B | L101: 46162 | M101: 47258 | O101: =IF(AND(M101<>"", M101<=TODAY(), N101=""), "End of Contract", "") | P101: =IF(OR(N101<>"", AND(M101<>"",M101<=TODAY())),"Non-Active","Active") -> Active | Q101: =IF(M101="","PKWTT",IF(DATEDIF(L101,M101,"M")>63,"PKWTT",IF(DATEDIF(L101,M101,"M")>60,"PKWT",IF(DATEDIF(L101,M101,"M")>36,"PKWT",IF(DATEDIF(L101,M101,"M")>12, "PKWT","PKWT"))))) -> PKWT | R101: Vocational High School | S101: Automotive Engineering | T101: Manufacturing | U101: Quality Engineering | V101: Manager | W101: QE Manager | X101: =_xlfn.XLOOKUP(V101,Reference!$O:$O,Reference!$N:$N,"Tidak Ketemu") -> G06 | Y101: =IF(AND(G101="Female",H101="Married"),"TK/0",IF(H101="Married","K/"&I101,"TK/"&I101)) -> TK/0 | Z101: 393728565998573 | AA101: 76577618224 | AB101: 1497007935363 | AC101: BANK BCA | AD101: 4800687656 | AE101: 082651206990 | AF101: dedi.kusuma@dumibumi.co.id | AG101: Jakarta, Indonesia
A102: 201943644 | B102: Bayu Maulana | C102: 0717298336305891 | D102: 4413204743817581 | E102: Cikampek | F102: 38210 | G102: Male | H102: Single | I102: =MIN(COUNTIFS('Data Family'!A:A,A102,'Data Family'!F:F,"Child")+COUNTIFS('Data Family'!A:A,A102,'Data Family'!F:F,"<>Child",'Data Family'!J:J,"Housewife")+COUNTIFS('Data Family'!A:A,A102,'Data Family'!F:F,"<>Child",'Data Family'!J:J,"Unemployment"),3) -> 1 | J102: Islam | K102: A | L102: 45471 | M102: 46566 | O102: =IF(AND(M102<>"", M102<=TODAY(), N102=""), "End of Contract", "") | P102: =IF(OR(N102<>"", AND(M102<>"",M102<=TODAY())),"Non-Active","Active") -> Active | Q102: =IF(M102="","PKWTT",IF(DATEDIF(L102,M102,"M")>63,"PKWTT",IF(DATEDIF(L102,M102,"M")>60,"PKWT",IF(DATEDIF(L102,M102,"M")>36,"PKWT",IF(DATEDIF(L102,M102,"M")>12, "PKWT","PKWT"))))) -> PKWT | R102: Vocational High School | S102: Automotive Engineering | T102: Manufacturing | U102: Quality Assurance | V102: Manager | W102: QA Manager | X102: =_xlfn.XLOOKUP(V102,Reference!$O:$O,Reference!$N:$N,"Tidak Ketemu") -> G06 | Y102: =IF(AND(G102="Female",H102="Married"),"TK/0",IF(H102="Married","K/"&I102,"TK/"&I102)) -> TK/1 | Z102: 701706279589707 | AA102: 90056136826 | AB102: 3722945702820 | AC102: BANK BCA | AD102: 1690620008 | AE102: 087054255114 | AF102: bayu.maulana@dumibumi.co.id | AG102: Jakarta, Indonesia
...

Sheet Data Karyawan (2)
A1: Employee Number | B1: National ID Number (NIK) | C1: Family Card Number (KK) | D1: Full Name | E1: Gender | F1: Place of Birth | G1: Education | H1: Major | I1: Date of Birth | J1: Age | K1: Religion | L1: Marital Status | M1: Blood Type | N1: Nationality | O1: Mobile Phone | P1: Email | Q1: Current Address | R1: Join Date | S1: Employment Status | T1: No. Contract | U1: End Date | V1: Exit Date | W1: Reason Sapartion | X1: Employee Status | Y1: Division | Z1: Job Title | AA1: Job Level | AB1: Tax ID Number (NPWP) | AC1: BPJS-KPJ | AD1: BPJS-JKN | AE1: Bank | AF1: Bank Account Number
A2: =VALUE(YEAR(R2)&TEXT(R2,"0000")) -> 202144393 | B2: 9724027143268662 | C2: 2496360035248341 | D2: Yusuf Saputra | E2: Male | F2: Bandung | G2: SMA/K | H2: Mechanical Engineering | I2: 31552 | J2: =IF(I2="","",DATEDIF(I2,TODAY(),"Y")) -> 40 | K2: Islam | L2: Married | M2: O | N2: Indonesia | O2: 086885613346 | P2: yusuf.saputra@dumibumi.co.id | Q2: Jakarta, Indonesia | R2: 44393 | S2: =IF(AND(T2<>"",U2<>""),"PKWT","PKWTT") -> PKWTT | T2: =IF(R2>TODAY(),"",IF(DATEDIF(R2,TODAY(),"Y")>=5,"",IF(DATEDIF(R2,TODAY(),"Y")<1,1,IF(DATEDIF(R2,TODAY(),"Y")<3,2,3)))) | U2: =IF(T2="","",IF(T2=1,EDATE(R2,12)-1,IF(T2=2,EDATE(R2,36)-1,IF(T2=3,EDATE(R2,60)-1,"")))) | V2: 46218 | W2: Contract End | X2: =IF(U2<>"","Non-Active",IF(S2="PKWTT","Active",IF(U2>=TODAY(),"Active","Non-Active"))) -> Active | Y2: Manufacturing | Z2: Production Administrator | AA2: Staff | AC2: 74623006286 | AD2: 6750136175908 | AE2: BCA | AF2: 8679287773
A3: =VALUE(YEAR(R3)&TEXT(R3,"0000")) -> 202445405 | B3: 1319927713057730 | C3: 6712742096205780 | D3: Bayu Utami | E3: Male | F3: Bekasi | G3: SMA/K | H3: Mechanical Engineering | I3: 38019 | J3: =IF(I3="","",DATEDIF(I3,TODAY(),"Y")) -> 22 | K3: Islam | L3: Single | M3: O | N3: Indonesia | O3: 084700287265 | P3: bayu.utami@dumibumi.co.id | Q3: Jakarta, Indonesia | R3: 45405 | S3: =IF(AND(T3<>"",U3<>""),"PKWT","PKWTT") -> PKWT | T3: =IF(R3>TODAY(),"",IF(DATEDIF(R3,TODAY(),"Y")>=5,"",IF(DATEDIF(R3,TODAY(),"Y")<1,1,IF(DATEDIF(R3,TODAY(),"Y")<3,2,3)))) -> 2 | U3: =IF(T3="","",IF(T3=1,EDATE(R3,12)-1,IF(T3=2,EDATE(R3,36)-1,IF(T3=3,EDATE(R3,60)-1,"")))) -> 46499 | V3: 46215 | W3: Resigned | X3: =IF(V3<>"","Non-Active",IF(S3="PKWTT","Active",IF(U3>=TODAY(),"Active","Non-Active"))) -> Non-Active | Y3: Manufacturing | Z3: Production Operator | AA3: Operator | AC3: 68595819715 | AD3: 3419178413554 | AE3: BCA | AF3: 1917024454
A4: =VALUE(YEAR(R4)&TEXT(R4,"0000")) -> 201843144 | B4: 0852705160988180 | C4: 7635438031805205 | D4: Aulia Pratama | E4: Female | F4: Bandung | G4: Bachelor Degree | H4: Economics | I4: 34368 | J4: =IF(I4="","",DATEDIF(I4,TODAY(),"Y")) -> 32 | K4: Islam | L4: Married | M4: AB | N4: Indonesia | O4: 084092019210 | P4: aulia.pratama@dumibumi.co.id | Q4: Bogor, Indonesia | R4: 43144 | S4: =IF(AND(T4<>"",U4<>""),"PKWT","PKWTT") -> PKWTT | T4: =IF(R4>TODAY(),"",IF(DATEDIF(R4,TODAY(),"Y")>=5,"",IF(DATEDIF(R4,TODAY(),"Y")<1,1,IF(DATEDIF(R4,TODAY(),"Y")<3,2,3)))) | U4: =IF(T4="","",IF(T4=1,EDATE(R4,12)-1,IF(T4=2,EDATE(R4,36)-1,IF(T4=3,EDATE(R4,60)-1,"")))) | X4: =IF(V4<>"","Non-Active",IF(S4="PKWTT","Active",IF(U4>=TODAY(),"Active","Non-Active"))) -> Active | Y4: Commercial & Marketing | Z4: Marketing Officer | AA4: Officer | AC4: 39227763842 | AD4: 6156780811272 | AE4: BCA | AF4: 0197375125
A5: =VALUE(YEAR(R5)&TEXT(R5,"0000")) -> 201943549 | B5: 4137252650863604 | C5: 1415111111606982 | D5: Rizky Hidayat | E5: Male | F5: Jakarta | G5: Bachelor Degree | H5: Communication | I5: 32485 | J5: =IF(I5="","",DATEDIF(I5,TODAY(),"Y")) -> 37 | K5: Islam | L5: Married | M5: A | N5: Indonesia | O5: 085744498429 | P5: rizky.hidayat@dumibumi.co.id | Q5: Bandung, Indonesia | R5: 43549 | S5: =IF(AND(T5<>"",U5<>""),"PKWT","PKWTT") -> PKWTT | T5: =IF(R5>TODAY(),"",IF(DATEDIF(R5,TODAY(),"Y")>=5,"",IF(DATEDIF(R5,TODAY(),"Y")<1,1,IF(DATEDIF(R5,TODAY(),"Y")<3,2,3)))) | U5: =IF(T5="","",IF(T5=1,EDATE(R5,12)-1,IF(T5=2,EDATE(R5,36)-1,IF(T5=3,EDATE(R5,60)-1,"")))) | X5: =IF(V5<>"","Non-Active",IF(S5="PKWTT","Active",IF(U5>=TODAY(),"Active","Non-Active"))) -> Active | Y5: Management | Z5: General Manager Finance, Accounting & Tax | AA5: General Manager | AC5: 78480658327 | AD5: 9002621247506 | AE5: BCA | AF5: 7002852045
A6: =VALUE(YEAR(R6)&TEXT(R6,"0000")) -> 201742831 | B6: 9237184536117948 | C6: 8616949168909269 | D6: Dedi Hidayat | E6: Male | F6: Bandung | G6: SMA/K | H6: Mechanical Engineering | I6: 31788 | J6: =IF(I6="","",DATEDIF(I6,TODAY(),"Y")) -> 39 | K6: Islam | L6: Married | M6: B | N6: Indonesia | O6: 088469960329 | P6: dedi.hidayat@dumibumi.co.id | Q6: Subang, Indonesia | R6: 42831 | S6: =IF(AND(T6<>"",U6<>""),"PKWT","PKWTT") -> PKWTT | T6: =IF(R6>TODAY(),"",IF(DATEDIF(R6,TODAY(),"Y")>=5,"",IF(DATEDIF(R6,TODAY(),"Y")<1,1,IF(DATEDIF(R6,TODAY(),"Y")<3,2,3)))) | U6: =IF(T6="","",IF(T6=1,EDATE(R6,12)-1,IF(T6=2,EDATE(R6,36)-1,IF(T6=3,EDATE(R6,60)-1,"")))) | X6: =IF(V6<>"","Non-Active",IF(S6="PKWTT","Active",IF(U6>=TODAY(),"Active","Non-Active"))) -> Active | Y6: Manufacturing | Z6: Line Leader | AA6: Leader | AC6: 44689751350 | AD6: 2145516190184 | AE6: BCA | AF6: 3825311340
A7: =VALUE(YEAR(R7)&TEXT(R7,"0000")) -> 202043954 | B7: 7134371159410775 | C7: 7257837349082723 | D7: Nadia Pratama | E7: Female | F7: Bandung | G7: Bachelor Degree | H7: Accounting | I7: 28118 | J7: =IF(I7="","",DATEDIF(I7,TODAY(),"Y")) -> 49 | K7: Islam | L7: Married | M7: O | N7: Indonesia | O7: 089416729767 | P7: nadia.pratama@dumibumi.co.id | Q7: Jakarta, Indonesia | R7: 43954 | S7: =IF(AND(T7<>"",U7<>""),"PKWT","PKWTT") -> PKWTT | T7: =IF(R7>TODAY(),"",IF(DATEDIF(R7,TODAY(),"Y")>=5,"",IF(DATEDIF(R7,TODAY(),"Y")<1,1,IF(DATEDIF(R7,TODAY(),"Y")<3,2,3)))) | U7: =IF(T7="","",IF(T7=1,EDATE(R7,12)-1,IF(T7=2,EDATE(R7,36)-1,IF(T7=3,EDATE(R7,60)-1,"")))) | X7: =IF(V7<>"","Non-Active",IF(S7="PKWTT","Active",IF(U7>=TODAY(),"Active","Non-Active"))) -> Active | Y7: Research & Development | Z7: Product Development Staff | AA7: Staff | AC7: 45394320070 | AD7: 0749322108059 | AE7: BCA | AF7: 1582000195
A8: =VALUE(YEAR(R8)&TEXT(R8,"0000")) -> 202043916 | B8: 9782076164222303 | C8: 4485016280872613 | D8: Dedi Kusuma | E8: Male | F8: Bekasi | G8: Bachelor Degree | H8: Communication | I8: 30657 | J8: =IF(I8="","",DATEDIF(I8,TODAY(),"Y")) -> 42 | K8: Islam | L8: Married | M8: AB | N8: Indonesia | O8: 089342892178 | P8: dedi.kusuma@dumibumi.co.id | Q8: Jakarta, Indonesia | R8: 43916 | S8: =IF(AND(T8<>"",U8<>""),"PKWT","PKWTT") -> PKWTT | T8: =IF(R8>TODAY(),"",IF(DATEDIF(R8,TODAY(),"Y")>=5,"",IF(DATEDIF(R8,TODAY(),"Y")<1,1,IF(DATEDIF(R8,TODAY(),"Y")<3,2,3)))) | U8: =IF(T8="","",IF(T8=1,EDATE(R8,12)-1,IF(T8=2,EDATE(R8,36)-1,IF(T8=3,EDATE(R8,60)-1,"")))) | X8: =IF(V8<>"","Non-Active",IF(S8="PKWTT","Active",IF(U8>=TODAY(),"Active","Non-Active"))) -> Active | Y8: Commercial & Marketing | Z8: Marketing Officer | AA8: Officer | AC8: 60160076084 | AD8: 1218658049593 | AE8: BCA | AF8: 6240219974
A9: =VALUE(YEAR(R9)&TEXT(R9,"0000")) -> 202044026 | B9: 9083339653697797 | C9: 6513051105371010 | D9: Aulia Permata | E9: Female | F9: Bandung | G9: Bachelor Degree | H9: Information Systems | I9: 29849 | J9: =IF(I9="","",DATEDIF(I9,TODAY(),"Y")) -> 44 | K9: Islam | L9: Single | M9: AB | N9: Indonesia | O9: 085063958691 | P9: aulia.permata@dumibumi.co.id | Q9: Bekasi, Indonesia | R9: 44026 | S9: =IF(AND(T9<>"",U9<>""),"PKWT","PKWTT") -> PKWTT | T9: =IF(R9>TODAY(),"",IF(DATEDIF(R9,TODAY(),"Y")>=5,"",IF(DATEDIF(R9,TODAY(),"Y")<1,1,IF(DATEDIF(R9,TODAY(),"Y")<3,2,3)))) | U9: =IF(T9="","",IF(T9=1,EDATE(R9,12)-1,IF(T9=2,EDATE(R9,36)-1,IF(T9=3,EDATE(R9,60)-1,"")))) | X9: =IF(V9<>"","Non-Active",IF(S9="PKWTT","Active",IF(U9>=TODAY(),"Active","Non-Active"))) -> Active | Y9: Information Technology | Z9: IT Support | AA9: Staff | AC9: 98210689429 | AD9: 1918407141285 | AE9: BCA | AF9: 3788927309
A10: =VALUE(YEAR(R10)&TEXT(R10,"0000")) -> 201943527 | B10: 0548317562548392 | C10: 5245230852064504 | D10: Bambang Wijaya | E10: Male | F10: Jakarta | G10: Bachelor Degree | H10: Information Systems | I10: 27804 | J10: =IF(I10="","",DATEDIF(I10,TODAY(),"Y")) -> 50 | K10: Islam | L10: Married | M10: AB | N10: Indonesia | O10: 086134466406 | P10: agus.wijaya@dumibumi.co.id | Q10: Subang, Indonesia | R10: 43527 | S10: =IF(AND(T10<>"",U10<>""),"PKWT","PKWTT") -> PKWTT | T10: =IF(R10>TODAY(),"",IF(DATEDIF(R10,TODAY(),"Y")>=5,"",IF(DATEDIF(R10,TODAY(),"Y")<1,1,IF(DATEDIF(R10,TODAY(),"Y")<3,2,3)))) | U10: =IF(T10="","",IF(T10=1,EDATE(R10,12)-1,IF(T10=2,EDATE(R10,36)-1,IF(T10=3,EDATE(R10,60)-1,"")))) | X10: =IF(V10<>"","Non-Active",IF(S10="PKWTT","Active",IF(U10>=TODAY(),"Active","Non-Active"))) -> Active | Y10: Human Resources | Z10: Human Resources Manager | AA10: Manager | AC10: 84324207712 | AD10: 6855408763258 | AE10: BCA | AF10: 6514728684
A11: =VALUE(YEAR(R11)&TEXT(R11,"0000")) -> 202044023 | B11: 2407510482879145 | C11: 6379367309178858 | D11: Siti Maulana | E11: Female | F11: Depok | G11: SMA/K | H11: Electrical Engineering | I11: 37720 | J11: =IF(I11="","",DATEDIF(I11,TODAY(),"Y")) -> 23 | K11: Islam | L11: Single | M11: B | N11: Indonesia | O11: 088497523016 | P11: siti.maulana@dumibumi.co.id | Q11: Subang, Indonesia | R11: 44023 | S11: =IF(AND(T11<>"",U11<>""),"PKWT","PKWTT") -> PKWTT | T11: =IF(R11>TODAY(),"",IF(DATEDIF(R11,TODAY(),"Y")>=5,"",IF(DATEDIF(R11,TODAY(),"Y")<1,1,IF(DATEDIF(R11,TODAY(),"Y")<3,2,3)))) | U11: =IF(T11="","",IF(T11=1,EDATE(R11,12)-1,IF(T11=2,EDATE(R11,36)-1,IF(T11=3,EDATE(R11,60)-1,"")))) | X11: =IF(V11<>"","Non-Active",IF(S11="PKWTT","Active",IF(U11>=TODAY(),"Active","Non-Active"))) -> Active | Y11: Commercial & Marketing | Z11: Marketing Officer | AA11: Officer | AC11: 06508531356 | AD11: 4750315762832 | AE11: BCA | AF11: 0131387787
A12: =VALUE(YEAR(R12)&TEXT(R12,"0000")) -> 202044061 | B12: 5108388085833704 | C12: 7730066736813181 | D12: Lina Permata | E12: Female | F12: Subang | G12: Bachelor Degree | H12: Information Systems | I12: 28770 | J12: =IF(I12="","",DATEDIF(I12,TODAY(),"Y")) -> 47 | K12: Islam | L12: Married | M12: O | N12: Indonesia | O12: 085474863189 | P12: lina.permata@dumibumi.co.id | Q12: Jakarta, Indonesia | R12: 44061 | S12: =IF(AND(T12<>"",U12<>""),"PKWT","PKWTT") -> PKWTT | T12: =IF(R12>TODAY(),"",IF(DATEDIF(R12,TODAY(),"Y")>=5,"",IF(DATEDIF(R12,TODAY(),"Y")<1,1,IF(DATEDIF(R12,TODAY(),"Y")<3,2,3)))) | U12: =IF(T12="","",IF(T12=1,EDATE(R12,12)-1,IF(T12=2,EDATE(R12,36)-1,IF(T12=3,EDATE(R12,60)-1,"")))) | X12: =IF(V12<>"","Non-Active",IF(S12="PKWTT","Active",IF(U12>=TODAY(),"Active","Non-Active"))) -> Active | Y12: Commercial & Marketing | Z12: Marketing Officer | AA12: Officer | AC12: 47025422194 | AD12: 9856192042673 | AE12: BCA | AF12: 3810524184
A13: =VALUE(YEAR(R13)&TEXT(R13,"0000")) -> 202445365 | B13: 7044680841843920 | C13: 6529105927182681 | D13: Budi Ramadhan | E13: Male | F13: Jakarta | G13: SMA/K | H13: Informatics Engineering | I13: 32002 | J13: =IF(I13="","",DATEDIF(I13,TODAY(),"Y")) -> 38 | K13: Islam | L13: Single | M13: A | N13: Indonesia | O13: 082092848519 | P13: budi.ramadhan@dumibumi.co.id | Q13: Bekasi, Indonesia | R13: 45365 | S13: =IF(AND(T13<>"",U13<>""),"PKWT","PKWTT") -> PKWT | T13: =IF(R13>TODAY(),"",IF(DATEDIF(R13,TODAY(),"Y")>=5,"",IF(DATEDIF(R13,TODAY(),"Y")<1,1,IF(DATEDIF(R13,TODAY(),"Y")<3,2,3)))) -> 2 | U13: =IF(T13="","",IF(T13=1,EDATE(R13,12)-1,IF(T13=2,EDATE(R13,36)-1,IF(T13=3,EDATE(R13,60)-1,"")))) -> 46459 | X13: =IF(V13<>"","Non-Active",IF(S13="PKWTT","Active",IF(U13>=TODAY(),"Active","Non-Active"))) -> Active | Y13: Commercial & Marketing | Z13: Sales Executive | AA13: Staff | AC13: 31185554810 | AD13: 9058389079562 | AE13: BCA | AF13: 9922545773
A14: =VALUE(YEAR(R14)&TEXT(R14,"0000")) -> 201843451 | B14: 8966425293284516 | C14: 6444158298300135 | D14: Budi Kusuma | E14: Male | F14: Tangerang | G14: SMA/K | H14: Mechanical Engineering | I14: 36780 | J14: =IF(I14="","",DATEDIF(I14,TODAY(),"Y")) -> 25 | K14: Islam | L14: Married | M14: AB | N14: Indonesia | O14: 081490623210 | P14: budi.kusuma@dumibumi.co.id | Q14: Jakarta, Indonesia | R14: 43451 | S14: =IF(AND(T14<>"",U14<>""),"PKWT","PKWTT") -> PKWTT | T14: =IF(R14>TODAY(),"",IF(DATEDIF(R14,TODAY(),"Y")>=5,"",IF(DATEDIF(R14,TODAY(),"Y")<1,1,IF(DATEDIF(R14,TODAY(),"Y")<3,2,3)))) | U14: =IF(T14="","",IF(T14=1,EDATE(R14,12)-1,IF(T14=2,EDATE(R14,36)-1,IF(T14=3,EDATE(R14,60)-1,"")))) | X14: =IF(V14<>"","Non-Active",IF(S14="PKWTT","Active",IF(U14>=TODAY(),"Active","Non-Active"))) -> Active | Y14: Manufacturing | Z14: Production Operator | AA14: Operator | AC14: 50268051678 | AD14: 9820190273042 | AE14: BCA | AF14: 2862870575
A15: =VALUE(YEAR(R15)&TEXT(R15,"0000")) -> 202646255 | B15: 3885473725425308 | C15: 7068925847837895 | D15: Yusuf Maulana | E15: Male | F15: Bekasi | G15: SMA/K | H15: Mechanical Engineering | I15: 37521 | J15: =IF(I15="","",DATEDIF(I15,TODAY(),"Y")) -> 23 | K15: Islam | L15: Single | M15: AB | N15: Indonesia | O15: 087564520494 | P15: yusuf.maulana@dumibumi.co.id | Q15: Tangerang, Indonesia | R15: 46255 | S15: =IF(AND(T15<>"",U15<>""),"PKWT","PKWTT") -> PKWTT | T15: =IF(R15>TODAY(),"",IF(DATEDIF(R15,TODAY(),"Y")>=5,"",IF(DATEDIF(R15,TODAY(),"Y")<1,1,IF(DATEDIF(R15,TODAY(),"Y")<3,2,3)))) | U15: =IF(T15="","",IF(T15=1,EDATE(R15,12)-1,IF(T15=2,EDATE(R15,36)-1,IF(T15=3,EDATE(R15,60)-1,"")))) | X15: =IF(V15<>"","Non-Active",IF(S15="PKWTT","Active",IF(U15>=TODAY(),"Active","Non-Active"))) -> Active | Y15: Manufacturing | Z15: Production Administrator | AA15: Administrator | AC15: 73717795066 | AD15: 3225506848332 | AE15: BCA | AF15: 5313080539
... A37: =VALUE(YEAR(R37)&TEXT(R37,"0000")) -> 202144525 | B37: 2338251524100155 | C37: 1985042518665965 | D37: Yusuf Kusuma | E37: Male | F37: Bekasi | G37: SMA/K | H37: Mechanical Engineering | I37: 28372 | J37: =IF(I37="","",DATEDIF(I37,TODAY(),"Y")) -> 48 | K37: Islam | L37: Married | M37: O | N37: Indonesia | O37: 081009300087 | P37: yusuf.kusuma@dumibumi.co.id | Q37: Jakarta, Indonesia | R37: 44525 | S37: =IF(AND(T37<>"",U37<>""),"PKWT","PKWTT") -> PKWT | T37: =IF(R37>TODAY(),"",IF(DATEDIF(R37,TODAY(),"Y")>=5,"",IF(DATEDIF(R37,TODAY(),"Y")<1,1,IF(DATEDIF(R37,TODAY(),"Y")<3,2,3)))) -> 3 | U37: =IF(T37="","",IF(T37=1,EDATE(R37,12)-1,IF(T37=2,EDATE(R37,36)-1,IF(T37=3,EDATE(R37,60)-1,"")))) -> 46350 | X37: =IF(V37<>"","Non-Active",IF(S37="PKWTT","Active",IF(U37>=TODAY(),"Active","Non-Active"))) -> Active | Y37: Manufacturing | Z37: Quality Control Inspector | AA37: Staff | AC37: 29395007235 | AD37: 5174132105131 | AE37: BCA | AF37: 1759262194
A38: =VALUE(YEAR(R38)&TEXT(R38,"0000")) -> 202545888 | B38: 8628846092214915 | C38: 3398196116382853 | D38: Farhan Utami | E38: Male | F38: Jakarta | G38: SMA/K | H38: Mechanical Engineering | I38: 37776 | J38: =IF(I38="","",DATEDIF(I38,TODAY(),"Y")) -> 23 | K38: Islam | L38: Single | M38: O | N38: Indonesia | O38: 089135814002 | P38: farhan.utami@dumibumi.co.id | Q38: Bandung, Indonesia | R38: 45888 | S38: =IF(AND(T38<>"",U38<>""),"PKWT","PKWTT") -> PKWT | T38: =IF(R38>TODAY(),"",IF(DATEDIF(R38,TODAY(),"Y")>=5,"",IF(DATEDIF(R38,TODAY(),"Y")<1,1,IF(DATEDIF(R38,TODAY(),"Y")<3,2,3)))) -> 1 | U38: =IF(T38="","",IF(T38=1,EDATE(R38,12)-1,IF(T38=2,EDATE(R38,36)-1,IF(T38=3,EDATE(R38,60)-1,"")))) -> 46252 | V38: 46252 | W38: Contract End | X38: =IF(V38<>"","Non-Active",IF(S38="PKWTT","Active",IF(U38>=TODAY(),"Active","Non-Active"))) -> Non-Active | Y38: Manufacturing | Z38: Line Leader | AA38: Leader | AC38: 51075526539 | AD38: 6341322555815 | AE38: BCA | AF38: 9423475922
A39: =VALUE(YEAR(R39)&TEXT(R39,"0000")) -> 202144282 | B39: 4395464990903556 | C39: 8829509739364332 | D39: Aulia Pratama | E39: Female | F39: Bandung | G39: Bachelor Degree | H39: Information Systems | I39: 34245 | J39: =IF(I39="","",DATEDIF(I39,TODAY(),"Y")) -> 32 | K39: Islam | L39: Married | M39: B | N39: Indonesia | O39: 087184535814 | P39: aulia.pratama@dumibumi.co.id | Q39: Jakarta, Indonesia | R39: 44282 | S39: =IF(AND(T39<>"",U39<>""),"PKWT","PKWTT") -> PKWTT | T39: =IF(R39>TODAY(),"",IF(DATEDIF(R39,TODAY(),"Y")>=5,"",IF(DATEDIF(R39,TODAY(),"Y")<1,1,IF(DATEDIF(R39,TODAY(),"Y")<3,2,3)))) | U39: =IF(T39="","",IF(T39=1,EDATE(R39,12)-1,IF(T39=2,EDATE(R39,36)-1,IF(T39=3,EDATE(R39,60)-1,"")))) | X39: =IF(V39<>"","Non-Active",IF(S39="PKWTT","Active",IF(U39>=TODAY(),"Active","Non-Active"))) -> Active | Y39: Commercial & Marketing | Z39: Marketing Officer | AA39: Officer | AC39: 84894746959 | AD39: 7887224001343 | AE39: BCA | AF39: 9439069601
A40: =VALUE(YEAR(R40)&TEXT(R40,"0000")) -> 202445397 | B40: 2517196805439571 | C40: 9584530999839852 | D40: Lina Santoso | E40: Female | F40: Bandung | G40: Bachelor Degree | H40: Psychology | I40: 31452 | J40: =IF(I40="","",DATEDIF(I40,TODAY(),"Y")) -> 40 | K40: Islam | L40: Single | M40: A | N40: Indonesia | O40: 081795402547 | P40: lina.santoso@dumibumi.co.id | Q40: Depok, Indonesia | R40: 45397 | S40: =IF(AND(T40<>"",U40<>""),"PKWT","PKWTT") -> PKWT | T40: =IF(R40>TODAY(),"",IF(DATEDIF(R40,TODAY(),"Y")>=5,"",IF(DATEDIF(R40,TODAY(),"Y")<1,1,IF(DATEDIF(R40,TODAY(),"Y")<3,2,3)))) -> 2 | U40: =IF(T40="","",IF(T40=1,EDATE(R40,12)-1,IF(T40=2,EDATE(R40,36)-1,IF(T40=3,EDATE(R40,60)-1,"")))) -> 46491 | X40: =IF(V40<>"","Non-Active",IF(S40="PKWTT","Active",IF(U40>=TODAY(),"Active","Non-Active"))) -> Active | Y40: Commercial & Marketing | Z40: Sales Executive | AA40: Staff | AC40: 59505272413 | AD40: 2006102574532 | AE40: BCA | AF40: 3670684262
A41: =VALUE(YEAR(R41)&TEXT(R41,"0000")) -> 202043974 | B41: 5157201582796516 | C41: 9463795218005823 | D41: Agus Maulana | E41: Male | F41: Depok | G41: SMA/K | H41: Mechanical Engineering | I41: 35189 | J41: =IF(I41="","",DATEDIF(I41,TODAY(),"Y")) -> 30 | K41: Islam | L41: Married | M41: AB | N41: Indonesia | O41: 081141420095 | P41: agus.maulana@dumibumi.co.id | Q41: Subang, Indonesia | R41: 43974 | S41: =IF(AND(T41<>"",U41<>""),"PKWT","PKWTT") -> PKWTT | T41: =IF(R41>TODAY(),"",IF(DATEDIF(R41,TODAY(),"Y")>=5,"",IF(DATEDIF(R41,TODAY(),"Y")<1,1,IF(DATEDIF(R41,TODAY(),"Y")<3,2,3)))) | U41: =IF(T41="","",IF(T41=1,EDATE(R41,12)-1,IF(T41=2,EDATE(R41,36)-1,IF(T41=3,EDATE(R41,60)-1,"")))) | X41: =IF(V41<>"","Non-Active",IF(S41="PKWTT","Active",IF(U41>=TODAY(),"Active","Non-Active"))) -> Active | Y41: Manufacturing | Z41: Production Operator | AA41: Operator | AC41: 91829165080 | AD41: 7129556564910 | AE41: BCA | AF41: 0536905546
A42: =VALUE(YEAR(R42)&TEXT(R42,"0000")) -> 201743013 | B42: 9964177721912332 | C42: 2008506307534749 | D42: Bayu Santoso | E42: Male | F42: Bandung | G42: SMA/K | H42: Mechanical Engineering | I42: 28809 | J42: =IF(I42="","",DATEDIF(I42,TODAY(),"Y")) -> 47 | K42: Islam | L42: Married | M42: A | N42: Indonesia | O42: 080595210902 | P42: bayu.santoso@dumibumi.co.id | Q42: Bandung, Indonesia | R42: 43013 | S42: =IF(AND(T42<>"",U42<>""),"PKWT","PKWTT") -> PKWTT | T42: =IF(R42>TODAY(),"",IF(DATEDIF(R42,TODAY(),"Y")>=5,"",IF(DATEDIF(R42,TODAY(),"Y")<1,1,IF(DATEDIF(R42,TODAY(),"Y")<3,2,3)))) | U42: =IF(T42="","",IF(T42=1,EDATE(R42,12)-1,IF(T42=2,EDATE(R42,36)-1,IF(T42=3,EDATE(R42,60)-1,"")))) | X42: =IF(V42<>"","Non-Active",IF(S42="PKWTT","Active",IF(U42>=TODAY(),"Active","Non-Active"))) -> Active | Y42: Manufacturing | Z42: Production Operator | AA42: Operator | AC42: 44115713928 | AD42: 8483334572963 | AE42: BCA | AF42: 0975713985
A43: =VALUE(YEAR(R43)&TEXT(R43,"0000")) -> 201843321 | B43: 5322130789845038 | C43: 6153072484024273 | D43: Yusuf Kusuma | E43: Male | F43: Subang | G43: SMA/K | H43: Mechanical Engineering | I43: 28925 | J43: =IF(I43="","",DATEDIF(I43,TODAY(),"Y")) -> 47 | K43: Islam | L43: Single | M43: AB | N43: Indonesia | O43: 080826191332 | P43: yusuf.kusuma@dumibumi.co.id | Q43: Subang, Indonesia | R43: 43321 | S43: =IF(AND(T43<>"",U43<>""),"PKWT","PKWTT") -> PKWTT | T43: =IF(R43>TODAY(),"",IF(DATEDIF(R43,TODAY(),"Y")>=5,"",IF(DATEDIF(R43,TODAY(),"Y")<1,1,IF(DATEDIF(R43,TODAY(),"Y")<3,2,3)))) | U43: =IF(T43="","",IF(T43=1,EDATE(R43,12)-1,IF(T43=2,EDATE(R43,36)-1,IF(T43=3,EDATE(R43,60)-1,"")))) | X43: =IF(V43<>"","Non-Active",IF(S43="PKWTT","Active",IF(U43>=TODAY(),"Active","Non-Active"))) -> Active | Y43: Manufacturing | Z43: Line Leader | AA43: Leader | AC43: 70235074213 | AD43: 4747335239025 | AE43: BCA | AF43: 1525322443
A44: =VALUE(YEAR(R44)&TEXT(R44,"0000")) -> 201743013 | B44: 8497101319935159 | C44: 0197669065659725 | D44: Rudi Nugroho | E44: Male | F44: Bogor | G44: Bachelor Degree | H44: Economics | I44: 29200 | J44: =IF(I44="","",DATEDIF(I44,TODAY(),"Y")) -> 46 | K44: Islam | L44: Single | M44: AB | N44: Indonesia | O44: 083952384227 | P44: rudi.nugroho@dumibumi.co.id | Q44: Bandung, Indonesia | R44: 43013 | S44: =IF(AND(T44<>"",U44<>""),"PKWT","PKWTT") -> PKWTT | T44: =IF(R44>TODAY(),"",IF(DATEDIF(R44,TODAY(),"Y")>=5,"",IF(DATEDIF(R44,TODAY(),"Y")<1,1,IF(DATEDIF(R44,TODAY(),"Y")<3,2,3)))) | U44: =IF(T44="","",IF(T44=1,EDATE(R44,12)-1,IF(T44=2,EDATE(R44,36)-1,IF(T44=3,EDATE(R44,60)-1,"")))) | X44: =IF(V44<>"","Non-Active",IF(S44="PKWTT","Active",IF(U44>=TODAY(),"Active","Non-Active"))) -> Active | Y44: Research & Development | Z44: Product Development Staff | AA44: Staff | AC44: 57099509411 | AD44: 2661899472091 | AE44: BCA | AF44: 6415986560
A45: =VALUE(YEAR(R45)&TEXT(R45,"0000")) -> 202043922 | B45: 3784399302361858 | C45: 2535723676203132 | D45: Andi Sari | E45: Male | F45: Subang | G45: D3 | H45: Statistics | I45: 33569 | J45: =IF(I45="","",DATEDIF(I45,TODAY(),"Y")) -> 34 | K45: Islam | L45: Married | M45: AB | N45: Indonesia | O45: 084333272377 | P45: andi.sari@dumibumi.co.id | Q45: Bandung, Indonesia | R45: 43922 | S45: =IF(AND(T45<>"",U45<>""),"PKWT","PKWTT") -> PKWTT | T45: =IF(R45>TODAY(),"",IF(DATEDIF(R45,TODAY(),"Y")>=5,"",IF(DATEDIF(R45,TODAY(),"Y")<1,1,IF(DATEDIF(R45,TODAY(),"Y")<3,2,3)))) | U45: =IF(T45="","",IF(T45=1,EDATE(R45,12)-1,IF(T45=2,EDATE(R45,36)-1,IF(T45=3,EDATE(R45,60)-1,"")))) | X45: =IF(V45<>"","Non-Active",IF(S45="PKWTT","Active",IF(U45>=TODAY(),"Active","Non-Active"))) -> Active | Y45: Research & Development | Z45: Product Development Staff | AA45: Staff | AC45: 01285378396 | AD45: 5190413512851 | AE45: BCA | AF45: 4821411451
A46: =VALUE(YEAR(R46)&TEXT(R46,"0000")) -> 201642692 | B46: 0685320109630851 | C46: 6198807385386196 | D46: Siti Kurniawan | E46: Female | F46: Bandung | G46: SMA/K | H46: Mechanical Engineering | I46: 34234 | J46: =IF(I46="","",DATEDIF(I46,TODAY(),"Y")) -> 32 | K46: Islam | L46: Single | M46: AB | N46: Indonesia | O46: 086996746442 | P46: siti.kurniawan@dumibumi.co.id | Q46: Jakarta, Indonesia | R46: 42692 | S46: =IF(AND(T46<>"",U46<>""),"PKWT","PKWTT") -> PKWTT | T46: =IF(R46>TODAY(),"",IF(DATEDIF(R46,TODAY(),"Y")>=5,"",IF(DATEDIF(R46,TODAY(),"Y")<1,1,IF(DATEDIF(R46,TODAY(),"Y")<3,2,3)))) | U46: =IF(T46="","",IF(T46=1,EDATE(R46,12)-1,IF(T46=2,EDATE(R46,36)-1,IF(T46=3,EDATE(R46,60)-1,"")))) | X46: =IF(V46<>"","Non-Active",IF(S46="PKWTT","Active",IF(U46>=TODAY(),"Active","Non-Active"))) -> Active | Y46: Manufacturing | Z46: Production Administrator | AA46: Staff | AC46: 61466077473 | AD46: 3244200795939 | AE46: BCA | AF46: 1851272766
A47: =VALUE(YEAR(R47)&TEXT(R47,"0000")) -> 201943517 | B47: 4056204832021363 | C47: 1444684841150491 | D47: Yoga Kusuma | E47: Male | F47: Depok | G47: SMA/K | H47: Electrical Engineering | I47: 37084 | J47: =IF(I47="","",DATEDIF(I47,TODAY(),"Y")) -> 25 | K47: Islam | L47: Married | M47: A | N47: Indonesia | O47: 081326766416 | P47: yoga.kusuma@dumibumi.co.id | Q47: Bandung, Indonesia | R47: 43517 | S47: =IF(AND(T47<>"",U47<>""),"PKWT","PKWTT") -> PKWTT | T47: =IF(R47>TODAY(),"",IF(DATEDIF(R47,TODAY(),"Y")>=5,"",IF(DATEDIF(R47,TODAY(),"Y")<1,1,IF(DATEDIF(R47,TODAY(),"Y")<3,2,3)))) | U47: =IF(T47="","",IF(T47=1,EDATE(R47,12)-1,IF(T47=2,EDATE(R47,36)-1,IF(T47=3,EDATE(R47,60)-1,"")))) | X47: =IF(V47<>"","Non-Active",IF(S47="PKWTT","Active",IF(U47>=TODAY(),"Active","Non-Active"))) -> Active | Y47: Information Technology | Z47: IT Support | AA47: Staff | AC47: 99558694649 | AD47: 2384854049745 | AE47: BCA | AF47: 3301716355
A48: =VALUE(YEAR(R48)&TEXT(R48,"0000")) -> 201742848 | B48: 7820303562542722 | C48: 0549766391306443 | D48: Yoga Ramadhan | E48: Male | F48: Bogor | G48: Bachelor Degree | H48: Psychology | I48: 34966 | J48: =IF(I48="","",DATEDIF(I48,TODAY(),"Y")) -> 30 | K48: Islam | L48: Single | M48: B | N48: Indonesia | O48: 089688272047 | P48: yoga.ramadhan@dumibumi.co.id | Q48: Depok, Indonesia | R48: 42848 | S48: =IF(AND(T48<>"",U48<>""),"PKWT","PKWTT") -> PKWTT | T48: =IF(R48>TODAY(),"",IF(DATEDIF(R48,TODAY(),"Y")>=5,"",IF(DATEDIF(R48,TODAY(),"Y")<1,1,IF(DATEDIF(R48,TODAY(),"Y")<3,2,3)))) | U48: =IF(T48="","",IF(T48=1,EDATE(R48,12)-1,IF(T48=2,EDATE(R48,36)-1,IF(T48=3,EDATE(R48,60)-1,"")))) | X48: =IF(V48<>"","Non-Active",IF(S48="PKWTT","Active",IF(U48>=TODAY(),"Active","Non-Active"))) -> Active | Y48: Human Resources | Z48: HR Communications Officer | AA48: Officer | AC48: 23414470316 | AD48: 8936707183221 | AE48: BCA | AF48: 4668255013
A49: =VALUE(YEAR(R49)&TEXT(R49,"0000")) -> 201843184 | B49: 0721414249399351 | C49: 4109983467220732 | D49: Yusuf Kurniawan | E49: Male | F49: Depok | G49: Bachelor Degree | H49: Psychology | I49: 35348 | J49: =IF(I49="","",DATEDIF(I49,TODAY(),"Y")) -> 29 | K49: Islam | L49: Single | M49: A | N49: Indonesia | O49: 088340608193 | P49: yusuf.kurniawan@dumibumi.co.id | Q49: Subang, Indonesia | R49: 43184 | S49: =IF(AND(T49<>"",U49<>""),"PKWT","PKWTT") -> PKWTT | T49: =IF(R49>TODAY(),"",IF(DATEDIF(R49,TODAY(),"Y")>=5,"",IF(DATEDIF(R49,TODAY(),"Y")<1,1,IF(DATEDIF(R49,TODAY(),"Y")<3,2,3)))) | U49: =IF(T49="","",IF(T49=1,EDATE(R49,12)-1,IF(T49=2,EDATE(R49,36)-1,IF(T49=3,EDATE(R49,60)-1,"")))) | X49: =IF(V49<>"","Non-Active",IF(S49="PKWTT","Active",IF(U49>=TODAY(),"Active","Non-Active"))) -> Active | Y49: Human Resources | Z49: Recruitment Staff | AA49: Staff | AC49: 35214994566 | AD49: 0709381098328 | AE49: BCA | AF49: 4381145985
A50: =VALUE(YEAR(R50)&TEXT(R50,"0000")) -> 202545795 | B50: 9626289820706461 | C50: 4792039667293099 | D50: Dewi Nugroho | E50: Female | F50: Jakarta | G50: SMA/K | H50: Mechanical Engineering | I50: 37550 | J50: =IF(I50="","",DATEDIF(I50,TODAY(),"Y")) -> 23 | K50: Islam | L50: Single | M50: A | N50: Indonesia | O50: 089801319282 | P50: dewi.nugroho@dumibumi.co.id | Q50: Bandung, Indonesia | R50: 45795 | S50: =IF(AND(T50<>"",U50<>""),"PKWT","PKWTT") -> PKWT | T50: =IF(R50>TODAY(),"",IF(DATEDIF(R50,TODAY(),"Y")>=5,"",IF(DATEDIF(R50,TODAY(),"Y")<1,1,IF(DATEDIF(R50,TODAY(),"Y")<3,2,3)))) -> 2 | U50: =IF(T50="","",IF(T50=1,EDATE(R50,12)-1,IF(T50=2,EDATE(R50,36)-1,IF(T50=3,EDATE(R50,60)-1,"")))) -> 46890 | X50: =IF(V50<>"","Non-Active",IF(S50="PKWTT","Active",IF(U50>=TODAY(),"Active","Non-Active"))) -> Active | Y50: Manufacturing | Z50: Quality Control Inspector | AA50: Staff | AC50: 00092053057 | AD50: 4886520762863 | AE50: BCA | AF50: 3641476558
A51: =VALUE(YEAR(R51)&TEXT(R51,"0000")) -> 202144397 | B51: 1951868988437053 | C51: 6333807636555146 | D51: Farhan Santoso | E51: Male | F51: Bogor | G51: Bachelor Degree | H51: Psychology | I51: 32953 | J51: =IF(I51="","",DATEDIF(I51,TODAY(),"Y")) -> 36 | K51: Islam | L51: Married | M51: A | N51: Indonesia | O51: 081984483820 | P51: farhan.santoso@dumibumi.co.id | Q51: Bogor, Indonesia | R51: 44397 | S51: =IF(AND(T51<>"",U51<>""),"PKWT","PKWTT") -> PKWTT | T51: =IF(R51>TODAY(),"",IF(DATEDIF(R51,TODAY(),"Y")>=5,"",IF(DATEDIF(R51,TODAY(),"Y")<1,1,IF(DATEDIF(R51,TODAY(),"Y")<3,2,3)))) | U51: =IF(T51="","",IF(T51=1,EDATE(R51,12)-1,IF(T51=2,EDATE(R51,36)-1,IF(T51=3,EDATE(R51,60)-1,"")))) | V51: 46222 | W51: Contract Ended | X51: =IF(V51<>"","Non-Active",IF(S51="PKWTT","Active",IF(U51>=TODAY(),"Active","Non-Active"))) -> Non-Active | Y51: Human Resources | Z51: Recruitment Staff | AA51: Staff | AC51: 09241000247 | AD51: 4067667977150 | AE51: BCA | AF51: 7562380157
A52: =VALUE(YEAR(R52)&TEXT(R52,"0000")) -> 202044036 | B52: 1310199806954946 | C52: 2734915019497956 | D52: Rudi Lestari | E52: Male | F52: Tangerang | G52: Bachelor Degree | H52: Human Resource Management | I52: 35264 | J52: =IF(I52="","",DATEDIF(I52,TODAY(),"Y")) -> 30 | K52: Islam | L52: Single | M52: B | N52: Indonesia | O52: 088250900446 | P52: rudi.lestari@dumibumi.co.id | Q52: Depok, Indonesia | R52: 44036 | S52: =IF(AND(T52<>"",U52<>""),"PKWT","PKWTT") -> PKWTT | T52: =IF(R52>TODAY(),"",IF(DATEDIF(R52,TODAY(),"Y")>=5,"",IF(DATEDIF(R52,TODAY(),"Y")<1,1,IF(DATEDIF(R52,TODAY(),"Y")<3,2,3)))) | U52: =IF(T52="","",IF(T52=1,EDATE(R52,12)-1,IF(T52=2,EDATE(R52,36)-1,IF(T52=3,EDATE(R52,60)-1,"")))) | X52: =IF(V52<>"","Non-Active",IF(S52="PKWTT","Active",IF(U52>=TODAY(),"Active","Non-Active"))) -> Active | Y52: Human Resources | Z52: Employer Branding Staff | AA52: Staff | AC52: 07637763553 | AD52: 9628447519189 | AE52: BCA | AF52: 6032042040
A53: =VALUE(YEAR(R53)&TEXT(R53,"0000")) -> 201743091 | B53: 3673261338071485 | C53: 4271920405157968 | D53: Dewi Pratama | E53: Female | F53: Subang | G53: Bachelor Degree | H53: Information Systems | I53: 28510 | J53: =IF(I53="","",DATEDIF(I53,TODAY(),"Y")) -> 48 | K53: Islam | L53: Single | M53: AB | N53: Indonesia | O53: 087436886061 | P53: dewi.pratama@dumibumi.co.id | Q53: Depok, Indonesia | R53: 43091 | S53: =IF(AND(T53<>"",U53<>""),"PKWT","PKWTT") -> PKWTT | T53: =IF(R53>TODAY(),"",IF(DATEDIF(R53,TODAY(),"Y")>=5,"",IF(DATEDIF(R53,TODAY(),"Y")<1,1,IF(DATEDIF(R53,TODAY(),"Y")<3,2,3)))) | U53: =IF(T53="","",IF(T53=1,EDATE(R53,12)-1,IF(T53=2,EDATE(R53,36)-1,IF(T53=3,EDATE(R53,60)-1,"")))) | X53: =IF(V53<>"","Non-Active",IF(S53="PKWTT","Active",IF(U53>=TODAY(),"Active","Non-Active"))) -> Active | Y53: Supply Chain Management | Z53: Warehouse Supervisor | AA53: Supervisor | AC53: 82725055991 | AD53: 7530534521305 | AE53: BCA | AF53: 8222713255
A54: =VALUE(YEAR(R54)&TEXT(R54,"0000")) -> 201843355 | B54: 9513891984353357 | C54: 6595100018993041 | D54: Rudi Wijaya | E54: Male | F54: Bogor | G54: Bachelor Degree | H54: Human Resource Management | I54: 35988 | J54: =IF(I54="","",DATEDIF(I54,TODAY(),"Y")) -> 28 | K54: Islam | L54: Married | M54: B | N54: Indonesia | O54: 087667878636 | P54: rudi.wijaya@dumibumi.co.id | Q54: Tangerang, Indonesia | R54: 43355 | S54: =IF(AND(T54<>"",U54<>""),"PKWT","PKWTT") -> PKWTT | T54: =IF(R54>TODAY(),"",IF(DATEDIF(R54,TODAY(),"Y")>=5,"",IF(DATEDIF(R54,TODAY(),"Y")<1,1,IF(DATEDIF(R54,TODAY(),"Y")<3,2,3)))) | U54: =IF(T54="","",IF(T54=1,EDATE(R54,12)-1,IF(T54=2,EDATE(R54,36)-1,IF(T54=3,EDATE(R54,60)-1,"")))) | X54: =IF(V54<>"","Non-Active",IF(S54="PKWTT","Active",IF(U54>=TODAY(),"Active","Non-Active"))) -> Active | Y54: Human Resources | Z54: HR Operations & General Affairs Staff | AA54: Staff | AC54: 11498446225 | AD54: 6818673946119 | AE54: BCA | AF54: 6494758086
A55: =VALUE(YEAR(R55)&TEXT(R55,"0000")) -> 201943575 | B55: 0865000522658401 | C55: 5339784715990609 | D55: Yoga Kusuma | E55: Male | F55: Jakarta | G55: SMA/K | H55: Mechanical Engineering | I55: 31675 | J55: =IF(I55="","",DATEDIF(I55,TODAY(),"Y")) -> 39 | K55: Islam | L55: Married | M55: A | N55: Indonesia | O55: 080706802656 | P55: yoga.kusuma@dumibumi.co.id | Q55: Bogor, Indonesia | R55: 43575 | S55: =IF(AND(T55<>"",U55<>""),"PKWT","PKWTT") -> PKWTT | T55: =IF(R55>TODAY(),"",IF(DATEDIF(R55,TODAY(),"Y")>=5,"",IF(DATEDIF(R55,TODAY(),"Y")<1,1,IF(DATEDIF(R55,TODAY(),"Y")<3,2,3)))) | U55: =IF(T55="","",IF(T55=1,EDATE(R55,12)-1,IF(T55=2,EDATE(R55,36)-1,IF(T55=3,EDATE(R55,60)-1,"")))) | X55: =IF(V55<>"","Non-Active",IF(S55="PKWTT","Active",IF(U55>=TODAY(),"Active","Non-Active"))) -> Active | Y55: Manufacturing | Z55: Production Administrator | AA55: Staff | AC55: 95824318614 | AD55: 4668981162955 | AE55: BCA | AF55: 4793555014
A56: =VALUE(YEAR(R56)&TEXT(R56,"0000")) -> 201441661 | B56: 1704869632385522 | C56: 6342712616102585 | D56: Agus Wijaya | E56: Male | F56: Tangerang | G56: Bachelor Degree | H56: Economics | I56: 35911 | J56: =IF(I56="","",DATEDIF(I56,TODAY(),"Y")) -> 28 | K56: Islam | L56: Single | M56: AB | N56: Indonesia | O56: 084153448642 | P56: agus.wijaya@dumibumi.co.id | Q56: Depok, Indonesia | R56: 41661 | S56: =IF(AND(T56<>"",U56<>""),"PKWT","PKWTT") -> PKWTT | T56: =IF(R56>TODAY(),"",IF(DATEDIF(R56,TODAY(),"Y")>=5,"",IF(DATEDIF(R56,TODAY(),"Y")<1,1,IF(DATEDIF(R56,TODAY(),"Y")<3,2,3)))) | U56: =IF(T56="","",IF(T56=1,EDATE(R56,12)-1,IF(T56=2,EDATE(R56,36)-1,IF(T56=3,EDATE(R56,60)-1,"")))) | X56: =IF(V56<>"","Non-Active",IF(S56="PKWTT","Active",IF(U56>=TODAY(),"Active","Non-Active"))) -> Active | Y56: Commercial & Marketing | Z56: Marketing Officer | AA56: Officer | AC56: 56546426194 | AD56: 5864362883339 | AE56: BCA | AF56: 1500812816
A57: =VALUE(YEAR(R57)&TEXT(R57,"0000")) -> 202043936 | B57: 1641203662345718 | C57: 4630131291841621 | D57: Putri Ramadhan | E57: Female | F57: Bogor | G57: Bachelor Degree | H57: Communication | I57: 29248 | J57: =IF(I57="","",DATEDIF(I57,TODAY(),"Y")) -> 46 | K57: Islam | L57: Married | M57: AB | N57: Indonesia | O57: 085093968164 | P57: putri.ramadhan@dumibumi.co.id | Q57: Bekasi, Indonesia | R57: 43936 | S57: =IF(AND(T57<>"",U57<>""),"PKWT","PKWTT") -> PKWTT | T57: =IF(R57>TODAY(),"",IF(DATEDIF(R57,TODAY(),"Y")>=5,"",IF(DATEDIF(R57,TODAY(),"Y")<1,1,IF(DATEDIF(R57,TODAY(),"Y")<3,2,3)))) | U57: =IF(T57="","",IF(T57=1,EDATE(R57,12)-1,IF(T57=2,EDATE(R57,36)-1,IF(T57=3,EDATE(R57,60)-1,"")))) | X57: =IF(V57<>"","Non-Active",IF(S57="PKWTT","Active",IF(U57>=TODAY(),"Active","Non-Active"))) -> Active | Y57: Commercial & Marketing | Z57: Marketing Officer | AA57: Officer | AC57: 11885951137 | AD57: 2735238535208 | AE57: BCA | AF57: 1619300215
A58: =VALUE(YEAR(R58)&TEXT(R58,"0000")) -> 201441797 | B58: 1693422781672131 | C58: 6297683498710681 | D58: Dedi Permata | E58: Male | F58: Depok | G58: Bachelor Degree | H58: Economics | I58: 27784 | J58: =IF(I58="","",DATEDIF(I58,TODAY(),"Y")) -> 50 | K58: Islam | L58: Married | M58: A | N58: Indonesia | O58: 081075935793 | P58: dedi.permata@dumibumi.co.id | Q58: Bogor, Indonesia | R58: 41797 | S58: =IF(AND(T58<>"",U58<>""),"PKWT","PKWTT") -> PKWTT | T58: =IF(R58>TODAY(),"",IF(DATEDIF(R58,TODAY(),"Y")>=5,"",IF(DATEDIF(R58,TODAY(),"Y")<1,1,IF(DATEDIF(R58,TODAY(),"Y")<3,2,3)))) | U58: =IF(T58="","",IF(T58=1,EDATE(R58,12)-1,IF(T58=2,EDATE(R58,36)-1,IF(T58=3,EDATE(R58,60)-1,"")))) | X58: =IF(V58<>"","Non-Active",IF(S58="PKWTT","Active",IF(U58>=TODAY(),"Active","Non-Active"))) -> Active | Y58: Research & Development | Z58: Product Development Staff | AA58: Staff | AC58: 71401237162 | AD58: 1682486458067 | AE58: BCA | AF58: 6054335163
A59: =VALUE(YEAR(R59)&TEXT(R59,"0000")) -> 201843432 | B59: 2820290502353446 | C59: 5379411953542881 | D59: Agus Kusuma | E59: Male | F59: Bandung | G59: Bachelor Degree | H59: Human Resource Management | I59: 35203 | J59: =IF(I59="","",DATEDIF(I59,TODAY(),"Y")) -> 30 | K59: Islam | L59: Married | M59: A | N59: Indonesia | O59: 087896851971 | P59: agus.kusuma@dumibumi.co.id | Q59: Bekasi, Indonesia | R59: 43432 | S59: =IF(AND(T59<>"",U59<>""),"PKWT","PKWTT") -> PKWTT | T59: =IF(R59>TODAY(),"",IF(DATEDIF(R59,TODAY(),"Y")>=5,"",IF(DATEDIF(R59,TODAY(),"Y")<1,1,IF(DATEDIF(R59,TODAY(),"Y")<3,2,3)))) | U59: =IF(T59="","",IF(T59=1,EDATE(R59,12)-1,IF(T59=2,EDATE(R59,36)-1,IF(T59=3,EDATE(R59,60)-1,"")))) | X59: =IF(V59<>"","Non-Active",IF(S59="PKWTT","Active",IF(U59>=TODAY(),"Active","Non-Active"))) -> Active | Y59: Human Resources | Z59: HR Operations & General Affairs Staff | AA59: Staff | AC59: 50073045078 | AD59: 9656030976614 | AE59: BCA | AF59: 9062586252
A60: =VALUE(YEAR(R60)&TEXT(R60,"0000")) -> 202144404 | B60: 2427589308136896 | C60: 1505522920969456 | D60: Andi Maulana | E60: Male | F60: Bekasi | G60: Bachelor Degree | H60: Communication | I60: 37575 | J60: =IF(I60="","",DATEDIF(I60,TODAY(),"Y")) -> 23 | K60: Islam | L60: Single | M60: O | N60: Indonesia | O60: 087030051902 | P60: andi.maulana@dumibumi.co.id | Q60: Depok, Indonesia | R60: 44404 | S60: =IF(AND(T60<>"",U60<>""),"PKWT","PKWTT") -> PKWTT | T60: =IF(R60>TODAY(),"",IF(DATEDIF(R60,TODAY(),"Y")>=5,"",IF(DATEDIF(R60,TODAY(),"Y")<1,1,IF(DATEDIF(R60,TODAY(),"Y")<3,2,3)))) | U60: =IF(T60="","",IF(T60=1,EDATE(R60,12)-1,IF(T60=2,EDATE(R60,36)-1,IF(T60=3,EDATE(R60,60)-1,"")))) | X60: =IF(V60<>"","Non-Active",IF(S60="PKWTT","Active",IF(U60>=TODAY(),"Active","Non-Active"))) -> Active | Y60: Commercial & Marketing | Z60: Marketing Officer | AA60: Officer | AC60: 81082194883 | AD60: 6151539163462 | AE60: BCA | AF60: 9502077492
A61: =VALUE(YEAR(R61)&TEXT(R61,"0000")) -> 202144222 | B61: 3957605305883060 | C61: 7601986664536922 | D61: Nadia Kusuma | E61: Female | F61: Subang | G61: Bachelor Degree | H61: Human Resource Management | I61: 35851 | J61: =IF(I61="","",DATEDIF(I61,TODAY(),"Y")) -> 28 | K61: Islam | L61: Single | M61: B | N61: Indonesia | O61: 086035963276 | P61: nadia.kusuma@dumibumi.co.id | Q61: Tangerang, Indonesia | R61: 44222 | S61: =IF(AND(T61<>"",U61<>""),"PKWT","PKWTT") -> PKWTT | T61: =IF(R61>TODAY(),"",IF(DATEDIF(R61,TODAY(),"Y")>=5,"",IF(DATEDIF(R61,TODAY(),"Y")<1,1,IF(DATEDIF(R61,TODAY(),"Y")<3,2,3)))) | U61: =IF(T61="","",IF(T61=1,EDATE(R61,12)-1,IF(T61=2,EDATE(R61,36)-1,IF(T61=3,EDATE(R61,60)-1,"")))) | X61: =IF(V61<>"","Non-Active",IF(S61="PKWTT","Active",IF(U61>=TODAY(),"Active","Non-Active"))) -> Active | Y61: Human Resources | Z61: HR Communications Officer | AA61: Officer | AC61: 78082684373 | AD61: 9314776012877 | AE61: BCA | AF61: 8162934541
A62: =VALUE(YEAR(R62)&TEXT(R62,"0000")) -> 201843228 | B62: 6583433931378082 | C62: 5074515261456100 | D62: Aulia Kurniawan | E62: Female | F62: Subang | G62: Bachelor Degree | H62: Accounting | I62: 28382 | J62: =IF(I62="","",DATEDIF(I62,TODAY(),"Y")) -> 48 | K62: Islam | L62: Single | M62: B | N62: Indonesia | O62: 089998014789 | P62: aulia.kurniawan@dumibumi.co.id | Q62: Depok, Indonesia | R62: 43228 | S62: =IF(AND(T62<>"",U62<>""),"PKWT","PKWTT") -> PKWTT | T62: =IF(R62>TODAY(),"",IF(DATEDIF(R62,TODAY(),"Y")>=5,"",IF(DATEDIF(R62,TODAY(),"Y")<1,1,IF(DATEDIF(R62,TODAY(),"Y")<3,2,3)))) | U62: =IF(T62="","",IF(T62=1,EDATE(R62,12)-1,IF(T62=2,EDATE(R62,36)-1,IF(T62=3,EDATE(R62,60)-1,"")))) | X62: =IF(V62<>"","Non-Active",IF(S62="PKWTT","Active",IF(U62>=TODAY(),"Active","Non-Active"))) -> Active | Y62: Supply Chain Management | Z62: Warehouse Manager | AA62: Manager | AC62: 02808925599 | AD62: 2285754017046 | AE62: BCA | AF62: 2075046802
A63: =VALUE(YEAR(R63)&TEXT(R63,"0000")) -> 202144512 | B63: 5857745349964183 | C63: 2141561672139967 | D63: Indah Kurniawan | E63: Female | F63: Jakarta | G63: SMA/K | H63: Natural Sciences | I63: 34465 | J63: =IF(I63="","",DATEDIF(I63,TODAY(),"Y")) -> 32 | K63: Islam | L63: Married | M63: AB | N63: Indonesia | O63: 080348433193 | P63: indah.kurniawan@dumibumi.co.id | Q63: Bogor, Indonesia | R63: 44512 | S63: =IF(AND(T63<>"",U63<>""),"PKWT","PKWTT") -> PKWT | T63: =IF(R63>TODAY(),"",IF(DATEDIF(R63,TODAY(),"Y")>=5,"",IF(DATEDIF(R63,TODAY(),"Y")<1,1,IF(DATEDIF(R63,TODAY(),"Y")<3,2,3)))) -> 3 | U63: =IF(T63="","",IF(T63=1,EDATE(R63,12)-1,IF(T63=2,EDATE(R63,36)-1,IF(T63=3,EDATE(R63,60)-1,"")))) -> 46337 | X63: =IF(V63<>"","Non-Active",IF(S63="PKWTT","Active",IF(U63>=TODAY(),"Active","Non-Active"))) -> Active | Y63: Manufacturing | Z63: Line Leader | AA63: Leader | AC63: 44036647790 | AD63: 8436871664564 | AE63: BCA | AF63: 6871415377
... A111: =VALUE(YEAR(R111)&TEXT(R111,"0000")) -> 201843269 | B111: 5466657241139332 | C111: 9630161641854481 | D111: Lina Santoso | E111: Female | F111: Tangerang | G111: D3 | H111: Statistics | I111: 33534 | J111: =IF(I111="","",DATEDIF(I111,TODAY(),"Y")) -> 34 | K111: Islam | L111: Single | M111: O | N111: Indonesia | O111: 082891955195 | P111: lina.santoso@dumibumi.co.id | Q111: Bandung, Indonesia | R111: 43269 | S111: =IF(AND(T111<>"",U111<>""),"PKWT","PKWTT") -> PKWTT | T111: =IF(R111>TODAY(),"",IF(DATEDIF(R111,TODAY(),"Y")>=5,"",IF(DATEDIF(R111,TODAY(),"Y")<1,1,IF(DATEDIF(R111,TODAY(),"Y")<3,2,3)))) | U111: =IF(T111="","",IF(T111=1,EDATE(R111,12)-1,IF(T111=2,EDATE(R111,36)-1,IF(T111=3,EDATE(R111,60)-1,"")))) | X111: =IF(V111<>"","Non-Active",IF(S111="PKWTT","Active",IF(U111>=TODAY(),"Active","Non-Active"))) -> Active | Y111: Legal | Z111: Legal Officer | AA111: Officer | AC111: 22165667986 | AD111: 3126736271019 | AE111: BCA | AF111: 9107113666
A112: =VALUE(YEAR(R112)&TEXT(R112,"0000")) -> 202545977 | B112: 0653548589918503 | C112: 1696039419532972 | D112: Yoga Permata | E112: Male | F112: Jakarta | G112: D3 | H112: Statistics | I112: 36381 | J112: =IF(I112="","",DATEDIF(I112,TODAY(),"Y")) -> 26 | K112: Islam | L112: Devorce | M112: AB | N112: Indonesia | O112: 088895007865 | P112: yoga.permata@dumibumi.co.id | Q112: Depok, Indonesia | R112: 45977 | S112: =IF(AND(T112<>"",U112<>""),"PKWT","PKWTT") -> PKWT | T112: =IF(R112>TODAY(),"",IF(DATEDIF(R112,TODAY(),"Y")>=5,"",IF(DATEDIF(R112,TODAY(),"Y")<1,1,IF(DATEDIF(R112,TODAY(),"Y")<3,2,3)))) -> 1 | U112: =IF(T112="","",IF(T112=1,EDATE(R112,12)-1,IF(T112=2,EDATE(R112,36)-1,IF(T112=3,EDATE(R112,60)-1,"")))) -> 46341 | V112: 46127 | W112: Resigned | X112: =IF(V112<>"","Non-Active",IF(S112="PKWTT","Active",IF(U112>=TODAY(),"Active","Non-Active"))) -> Non-Active | Y112: Commercial & Marketing | Z112: Sales Executive | AA112: Staff | AC112: 11052942596 | AD112: 8997513813118 | AE112: BCA | AF112: 4654570280
A113: =VALUE(YEAR(R113)&TEXT(R113,"0000")) -> 202445629 | B113: 3877001018943814 | C113: 2206649275120289 | D113: Aulia Kusuma | E113: Female | F113: Tangerang | G113: D3 | H113: Statistics | I113: 28077 | J113: =IF(I113="","",DATEDIF(I113,TODAY(),"Y")) -> 49 | K113: Islam | L113: Single | M113: O | N113: Indonesia | O113: 085964897453 | P113: aulia.kusuma@dumibumi.co.id | Q113: Bandung, Indonesia | R113: 45629 | S113: =IF(AND(T113<>"",U113<>""),"PKWT","PKWTT") -> PKWT | T113: =IF(R113>TODAY(),"",IF(DATEDIF(R113,TODAY(),"Y")>=5,"",IF(DATEDIF(R113,TODAY(),"Y")<1,1,IF(DATEDIF(R113,TODAY(),"Y")<3,2,3)))) -> 2 | U113: =IF(T113="","",IF(T113=1,EDATE(R113,12)-1,IF(T113=2,EDATE(R113,36)-1,IF(T113=3,EDATE(R113,60)-1,"")))) -> 46723 | V113: 45994 | W113: Resigned | X113: =IF(V113<>"","Non-Active",IF(S113="PKWTT","Active",IF(U113>=TODAY(),"Active","Non-Active"))) -> Non-Active | Y113: Commercial & Marketing | Z113: Sales Executive | AA113: Staff | AC113: 06411236925 | AD113: 8723672671458 | AE113: BCA | AF113: 4821837876
A114: =VALUE(YEAR(R114)&TEXT(R114,"0000")) -> 201943797 | B114: 7403172700086770 | C114: 3533153524965294 | D114: Fajar Ramadhan | E114: Male | F114: Bekasi | G114: D3 | H114: Statistics | I114: 34702 | J114: =IF(I114="","",DATEDIF(I114,TODAY(),"Y")) -> 31 | K114: Islam | L114: Single | M114: O | N114: Indonesia | O114: 087489139759 | P114: fajar.ramadhan@dumibumi.co.id | Q114: Jakarta, Indonesia | R114: 43797 | S114: =IF(AND(T114<>"",U114<>""),"PKWT","PKWTT") -> PKWTT | T114: =IF(R114>TODAY(),"",IF(DATEDIF(R114,TODAY(),"Y")>=5,"",IF(DATEDIF(R114,TODAY(),"Y")<1,1,IF(DATEDIF(R114,TODAY(),"Y")<3,2,3)))) | U114: =IF(T114="","",IF(T114=1,EDATE(R114,12)-1,IF(T114=2,EDATE(R114,36)-1,IF(T114=3,EDATE(R114,60)-1,"")))) | X114: =IF(V114<>"","Non-Active",IF(S114="PKWTT","Active",IF(U114>=TODAY(),"Active","Non-Active"))) -> Active | Y114: Information Technology | Z114: IT Support | AA114: Staff | AC114: 88817614875 | AD114: 7853449624885 | AE114: BCA | AF114: 4896614579
A115: =VALUE(YEAR(R115)&TEXT(R115,"0000")) -> 201943543 | B115: 8816524994934713 | C115: 5313204453528030 | D115: Budi Hidayat | E115: Male | F115: Subang | G115: D3 | H115: Statistics | I115: 29690 | J115: =IF(I115="","",DATEDIF(I115,TODAY(),"Y")) -> 45 | K115: Catholic | L115: Single | M115: O | N115: Indonesia | O115: 085479905718 | P115: budi.hidayat@dumibumi.co.id | Q115: Bekasi, Indonesia | R115: 43543 | S115: =IF(AND(T115<>"",U115<>""),"PKWT","PKWTT") -> PKWTT | T115: =IF(R115>TODAY(),"",IF(DATEDIF(R115,TODAY(),"Y")>=5,"",IF(DATEDIF(R115,TODAY(),"Y")<1,1,IF(DATEDIF(R115,TODAY(),"Y")<3,2,3)))) | U115: =IF(T115="","",IF(T115=1,EDATE(R115,12)-1,IF(T115=2,EDATE(R115,36)-1,IF(T115=3,EDATE(R115,60)-1,"")))) | X115: =IF(V115<>"","Non-Active",IF(S115="PKWTT","Active",IF(U115>=TODAY(),"Active","Non-Active"))) -> Active | Y115: Research & Development | Z115: Product Development Staff | AA115: Staff | AC115: 12739079843 | AD115: 1485264714899 | AE115: BCA | AF115: 0359637095
A116: =VALUE(YEAR(R116)&TEXT(R116,"0000")) -> 201843377 | B116: 2864405270891096 | C116: 5012106483619561 | D116: Rudi Lestari | E116: Male | F116: Bogor | G116: D3 | H116: Statistics | I116: 29152 | J116: =IF(I116="","",DATEDIF(I116,TODAY(),"Y")) -> 46 | K116: Islam | L116: Devorce | M116: A | N116: Indonesia | O116: 086279933565 | P116: rudi.lestari@dumibumi.co.id | Q116: Subang, Indonesia | R116: 43377 | S116: =IF(AND(T116<>"",U116<>""),"PKWT","PKWTT") -> PKWTT | T116: =IF(R116>TODAY(),"",IF(DATEDIF(R116,TODAY(),"Y")>=5,"",IF(DATEDIF(R116,TODAY(),"Y")<1,1,IF(DATEDIF(R116,TODAY(),"Y")<3,2,3)))) | U116: =IF(T116="","",IF(T116=1,EDATE(R116,12)-1,IF(T116=2,EDATE(R116,36)-1,IF(T116=3,EDATE(R116,60)-1,"")))) | X116: =IF(V116<>"","Non-Active",IF(S116="PKWTT","Active",IF(U116>=TODAY(),"Active","Non-Active"))) -> Active | Y116: Research & Development | Z116: Product Development Staff | AA116: Staff | AC116: 83251599547 | AD116: 4773687220575 | AE116: BCA | AF116: 8673316611
A117: =VALUE(YEAR(R117)&TEXT(R117,"0000")) -> 201843195 | B117: 2810026473048455 | C117: 3986044438448019 | D117: Dewi Wijaya | E117: Female | F117: Jakarta | G117: SMA/K | H117: Social Sciences | I117: 30683 | J117: =IF(I117="","",DATEDIF(I117,TODAY(),"Y")) -> 42 | K117: Islam | L117: Single | M117: O | N117: Indonesia | O117: 083796185600 | P117: dewi.wijaya@dumibumi.co.id | Q117: Jakarta, Indonesia | R117: 43195 | S117: =IF(AND(T117<>"",U117<>""),"PKWT","PKWTT") -> PKWTT | T117: =IF(R117>TODAY(),"",IF(DATEDIF(R117,TODAY(),"Y")>=5,"",IF(DATEDIF(R117,TODAY(),"Y")<1,1,IF(DATEDIF(R117,TODAY(),"Y")<3,2,3)))) | U117: =IF(T117="","",IF(T117=1,EDATE(R117,12)-1,IF(T117=2,EDATE(R117,36)-1,IF(T117=3,EDATE(R117,60)-1,"")))) | X117: =IF(V117<>"","Non-Active",IF(S117="PKWTT","Active",IF(U117>=TODAY(),"Active","Non-Active"))) -> Active | Y117: Manufacturing | Z117: Quality Control Inspector | AA117: Staff | AC117: 44022479767 | AD117: 7679086809357 | AE117: BCA | AF117: 2337743036
A118: =VALUE(YEAR(R118)&TEXT(R118,"0000")) -> 201943823 | B118: 8698033968323955 | C118: 5246238651221120 | D118: Rizky Nugroho | E118: Male | F118: Depok | G118: SMA/K | H118: Social Sciences | I118: 32850 | J118: =IF(I118="","",DATEDIF(I118,TODAY(),"Y")) -> 36 | K118: Islam | L118: Single | M118: O | N118: Indonesia | O118: 089418922823 | P118: rizky.nugroho@dumibumi.co.id | Q118: Bandung, Indonesia | R118: 43823 | S118: =IF(AND(T118<>"",U118<>""),"PKWT","PKWTT") -> PKWTT | T118: =IF(R118>TODAY(),"",IF(DATEDIF(R118,TODAY(),"Y")>=5,"",IF(DATEDIF(R118,TODAY(),"Y")<1,1,IF(DATEDIF(R118,TODAY(),"Y")<3,2,3)))) | U118: =IF(T118="","",IF(T118=1,EDATE(R118,12)-1,IF(T118=2,EDATE(R118,36)-1,IF(T118=3,EDATE(R118,60)-1,"")))) | X118: =IF(V118<>"","Non-Active",IF(S118="PKWTT","Active",IF(U118>=TODAY(),"Active","Non-Active"))) -> Active | Y118: Manufacturing | Z118: Production Operator | AA118: Operator | AC118: 73731593225 | AD118: 1981507611524 | AE118: BCA | AF118: 3770960777
A119: =VALUE(YEAR(R119)&TEXT(R119,"0000")) -> 201642410 | B119: 2955052372617768 | C119: 8308884190330878 | D119: Putri Sari | E119: Female | F119: Depok | G119: D3 | H119: Statistics | I119: 32072 | J119: =IF(I119="","",DATEDIF(I119,TODAY(),"Y")) -> 38 | K119: Islam | L119: Devorce | M119: O | N119: Indonesia | O119: 083480227307 | P119: putri.sari@dumibumi.co.id | Q119: Tangerang, Indonesia | R119: 42410 | S119: =IF(AND(T119<>"",U119<>""),"PKWT","PKWTT") -> PKWTT | T119: =IF(R119>TODAY(),"",IF(DATEDIF(R119,TODAY(),"Y")>=5,"",IF(DATEDIF(R119,TODAY(),"Y")<1,1,IF(DATEDIF(R119,TODAY(),"Y")<3,2,3)))) | U119: =IF(T119="","",IF(T119=1,EDATE(R119,12)-1,IF(T119=2,EDATE(R119,36)-1,IF(T119=3,EDATE(R119,60)-1,"")))) | X119: =IF(V119<>"","Non-Active",IF(S119="PKWTT","Active",IF(U119>=TODAY(),"Active","Non-Active"))) -> Active | Y119: Information Technology | Z119: IT Support | AA119: Staff | AC119: 52066772425 | AD119: 8770238491848 | AE119: BCA | AF119: 3940414243
A120: =VALUE(YEAR(R120)&TEXT(R120,"0000")) -> 202144402 | B120: 5711061632369852 | C120: 9037798456738500 | D120: Agus Wijaya | E120: Male | F120: Tangerang | G120: Bachelor Degree | H120: Economics | I120: 30226 | J120: =IF(I120="","",DATEDIF(I120,TODAY(),"Y")) -> 43 | K120: Islam | L120: Single | M120: O | N120: Indonesia | O120: 081585319770 | P120: agus.wijaya@dumibumi.co.id | Q120: Bogor, Indonesia | R120: 44402 | S120: =IF(AND(T120<>"",U120<>""),"PKWT","PKWTT") -> PKWTT | T120: =IF(R120>TODAY(),"",IF(DATEDIF(R120,TODAY(),"Y")>=5,"",IF(DATEDIF(R120,TODAY(),"Y")<1,1,IF(DATEDIF(R120,TODAY(),"Y")<3,2,3)))) | U120: =IF(T120="","",IF(T120=1,EDATE(R120,12)-1,IF(T120=2,EDATE(R120,36)-1,IF(T120=3,EDATE(R120,60)-1,"")))) | X120: =IF(V120<>"","Non-Active",IF(S120="PKWTT","Active",IF(U120>=TODAY(),"Active","Non-Active"))) -> Active | Y120: Supply Chain Management | Z120: Production Planning & Control Supervisor | AA120: Supervisor | AC120: 55176539734 | AD120: 3765016287079 | AE120: BCA | AF120: 9328914021
